Workbook

Sheet Info
B7: Business planning | AG7: Modèle Zafy Tody
B10: Outil financier pour les startups
C21: Construire son business model et sa stratégie | O21: Gérer votre trésorerie et structurer votre plan de financement | AA21: Itérer et améliorer votre projet de startup | AM21: Exporter votre prévisionnel pour votre Business Plan
B27: Ceci est un outil conçu pour être simple et complet, dans le but d'aider l'entrepreneur dans la modélisation financière de son projet de création d'entreprise. Une connaissance minimale de la finance est néanmoins préférable pour tirer pleinement partie de l'outil. Conseil : Commencer par lire l'onglet "GUIDE" avant de démarrer l'utilisation.

Sheet Guide
B2: GUIDE
B5: Etape 0 : Introduction Un outil financier est un support d'aide à la réflexion de construction et de validation d'une stratégie d'entreprise. Pour utiliser cet outil, il faudra : 1 - Commencer par renseigner des informations sur le projet d'entreprise (ONGLETS CLAIRS) 2 - Analyser les résultats (ONGLETS FONCES) Une approche itérative de ces phases est généralement nécessaire pour affiner votre projet. Toute l'articulation de l'outil repose sur la possibilité de différencier plusieurs activités de revenus au sein de votre projet. Nous vous proposons de pouvoir gérer jusqu'à 12 "activités", même si la majorité des projets n'auront besoin de gérer qu'une ou deux activité(s). Les montants doivent être indiqués en Ar HT. Tous les calculs de TVA seront gérés automatiquement. La TVA est par défaut fixée à 20% mais peut être configurée dans l'onglet "CONFIG". Les feuilles sont "protégées" pour éviter que des erreurs de manipulations endommagent l'outil. Vous pouvez cependant dévérouiller ces feuilles sans mot de passe si vous souhaitez les personnaliser (clic droit sur l'onglet, puis "Ôter la protection des feuilles"). Certains onglets de calculs automatiques sont "masqués". Pour les visualiser, faites un clic droit sur la barre des onglets et choisissez "Afficher", puis sélectionnez l'onglet à afficher. Vous pouvez également si besoin créer des onglets personnalisés pour des calculs personnalisés.
B7: Etape 1 : Renseigner l'onglet "CONFIG" C'est le point de départ de la prise en main de l'outil. Commencez par renseigner les informations de "Configuration de base". Vous pourrez attaquer le renseignement des informations de "Configuration avancée" dans un second temps : ces informations sont pré-remplies pour vous simplifier la prise en main. Il vous sera très probablement nécéssaire de les ajuster à vos besoins par la suite.
B9: Etape 2 : Renseigner l'onglet "Personnel" Précisez les besoins en ressources humaines du projet au court du temps. Vous aurez à renseigner le salaire brut des personnes, mensuellement pour les années 1 et 2 et semestriellement pour les années 3 à 5. Les charges patronales sont calculées automatiquement. Vous pourrez modifier le taux de charges dans l'onglet "CONFIG". Pour les dirigeants au régime TNS, précisez directement un salaire totalement chargé.
B11: Etape 3 : Renseigner l'onglet "Charges externes" Précisez les charges externes de l'entreprise. Une partie est calculée automatiquement à partir d'informations, que vous pouvez modifier, définies dans la partie "Configuration avancée" de l'onglet "CONFIG". Vous pouvez également préciser d'autres charges mensuellement.
B13: Etape 4 : Renseigner l'onglet "Investissements" Précisez les investissements nécessaires pour le projet. Vous pouvez dissocier les types investissements par ligne. Pour chaque ligne, vous pourrez préciser les montants d'investisements mensuellement ainsi que les durées d'amortissement (tout à droite du tableau). Vous pouvez également préciser dans cet onglet les éventuels apports en nature que vous intégrez à l'entreprise.
B15: Etape 5 : Renseigner l'onglet "Commandes" Précisez les prévisions de commandes mensuelles par type d'activité. Le modèle propose un renseignement mensuel sur 5 ans pour vous faciliter la construction de prévisions estimatives à partir de fomules (fonction de votre business model et de vos hypothèses). Les encaissements et les décaissements liés à ces commandes (chiffres d'affaires et charges variables associées) seront calculés automatiquement sur la base des informations précisées dans l'onglet "CONFIG" (dans les tableaux "Chiffres d'Affaires" et "Charges variables").,
B17: Etape 6 : Renseigner l'onglet "Trésorerie" Préciser les financements identifiés pour le projet d'entreprise : capital (initial et augmentation par levée de fonds), prêts bancaires, subventions, … ainsi que certains besoins en financements à couvrir : stock moyen, remboursement de comptes courants et/ou d'avances, ...
B19: Etape 7 : Analyser les onglets "Synthèse", "Comptes de résultats", "Plan de financement" et "Bilans" Une fois les informations renseignées, l'outil générera les comptes de résultats de l'entreprise, les bilans, le plan de trésorerie menusel, le plan de financement, les points morts par années d'activités, le BFR ... et des graphiques que vous retrouverez dans l'onglet de synthèse. Ces informations vous permettront d'analyser le potentiel du projet, les enjeux commerciaux, les enjeux de financements, ... Vous pouvez désormais travailler par itération pour affiner votre vision financière de votre projet et votre stratégie d'entreprise.

Sheet Config
B2: CONFIGURATION DE BASE
B5: Note : Informations à renseigner pour démarrer votre prévisionnel. L'onglet "CONFIG" possède plus bas une deuxième zone de "Configuration avancée" à ne remplir qu'une fois que l'outil vous est plus familier.
B7: Date de démarrage de l'activité | C7: 45505
B9: CHIFFRE D'AFFAIRES
B11: Note sur la construction du chiffre d'affaires : Vous pouvez gérer plusieurs activités de revenus dans ce prévisionnel financier. Commencez par indiquer les intitulés de vos activités. Renseignez par activité de revenus : - Le revenu unitaire (par unité commandée. Le nombre d'unités commandées étant défini mensuellement dans l'onglet "Commandes") - Le délai de livraison (temps de production+livraison) - Le délai de paiement client - L'acompte éventuellement payé par le client à la commande - Le solde final payé à date de livraison + délai de paiement (automatique)
B13: Dénomination de l'activité | C13: Prix unitaire (en HT) | D13: Délai de livraison (en mois) | E13: Délai de paiement (en mois) | F13: Acompte initial (en %) | G13: Solde (en %)
B14: Abonnement Basique | C14: 15000 | D14: 0 | E14: 0 | F14: 0 | G14: =1-F14 -> 1
B15: Abonnement Premium | C15: 25000 | D15: 0 | E15: 0 | F15: 0 | G15: =1-F15 -> 1
B16: Conseil Personnalisé | C16: 12000 | D16: 0 | E16: 0 | F16: 0 | G16: =1-F16 -> 1
B17: Plateforme de Marché en Ligne | C17: 8000 | D17: 0 | E17: 0 | F17: 0 | G17: =1-F17 -> 1
B18: Formations et Ateliers | C18: 10000 | D18: 0 | E18: 0 | F18: 0 | G18: =1-F18 -> 1
B19: Commission ventes 2% | C19: 3000 | D19: 0 | E19: 0 | F19: 0 | G19: =1-F19 -> 1
G20: =1-F20 -> 1
G21: =1-F21 -> 1
G22: =1-F22 -> 1
G23: =1-F23 -> 1
G24: =1-F24 -> 1
G25: =1-F25 -> 1
B27: CHARGES VARIABLES
B29: Note sur les charges variables : Ces informations permettent de calculer automatiquement les charges variables associées aux commandes précisées dans l'onglet "Commandes". Les données à renseigner suivent le même modèle que le tableau ci-dessus. Les charges variables pour une activité donnée correspondent aux achats de matières premières et de sous-traitances que votre entreprises devra faire pour réaliser et livrer une unité commandée. Les informations sont donc liées à vos conditions commerciales négociées avec vos fournisseurs et prestataires : prix, délai de livraison, délai de paiement, acompte initial et solde du paiement.
B31: Dénomination de l'activité | C31: Coût unitaire (en HT) | D31: Délai de livraison (en mois) | E31: Délai de paiement (en mois) | F31: Acompte initial (en %) | G31: Solde (en %)
B32: =B14 -> Abonnement Basique | C32: 15000 | D32: 0 | G32: =1-F32 -> 1
B33: =B15 -> Abonnement Premium | C33: 25000 | D33: 0 | G33: =1-F33 -> 1
B34: =B16 -> Conseil Personnalisé | C34: 12000 | D34: 0 | G34: =1-F34 -> 1
B35: =B17 -> Plateforme de Marché en Ligne | C35: 8000 | D35: 0 | G35: =1-F35 -> 1
B36: =B18 -> Formations et Ateliers | C36: 10000 | D36: 0 | G36: =1-F36 -> 1
B37: =B19 -> Commission ventes 2% | C37: 3000 | D37: 0 | G37: =1-F37 -> 1
B38: =B20 | G38: =1-F38 -> 1
B39: =B21 | G39: =1-F39 -> 1
B40: =B22 | G40: =1-F40 -> 1
B41: =B23 | G41: =1-F41 -> 1
B42: =B24 | G42: =1-F42 -> 1
B43: =B25 | G43: =1-F43 -> 1
B45: CONFIGURATION AVANCEE
B48: Note : Une fois que vous avez pris en main l'outil, vous pouvez affiner vos prévisions en personnalisant les données par défaut de cette partie "Configuration avancée".
B50: CHARGES EXTERNES ANNUELLES
B52: Note : Ce tableau permet de calculer automatiquement les charges externes de l'entreprise. Pour mieux comprendre comment est calculée chaque ligne, veuillez vous référer aux commentaires associés. Des valeurs par défaut sont proposées à titre indicatif pour simplifier la prise en main initiale de l'outil et seront à affiner en fonction du projet. Vous pouvez aussi définir des charges externes sur mesure dans l'onglet "Charges externes".
B54: Poste | C54: Fixe ( HT) | D54: Variable | E54: Commentaires
B55: Frais de déplacement | C55: 450000 | D55: 0.01 | E55: Calculé sur la base d'un forfait fixe annuel + variable en % du CA
B56: Honoraires | C56: 4800000 | D56: 0 | E56: Calculé sur la base d'un forfait fixe annuel + variable par salarié
B57: Marketing | C57: 3600000 | D57: 0.02 | E57: Calculé sur la base d'un forfait fixe annuel + variable en % du CA
B58: Locaux | C58: 960000 | D58: 200000 | E58: Calculé sur la base d'un forfait fixe annuel + variable par salarié
B59: Téléphonie | C59: 2400000 | D59: 0 | E59: Calculé sur la base d'un forfait fixe annuel + variable par salarié
B60: Assurance | C60: 600000 | D60: 0.01 | E60: Calculé sur la base d'un forfait fixe annuel + variable en % du CA
B61: Fournitures | C61: 12000000 | D61: 0 | E61: Calculé sur la base d'un forfait fixe annuel + variable par salarié
B62: Informatique | C62: 6000000 | D62: 0 | E62: Calculé sur la base d'un forfait fixe annuel + variable par salarié
B63: Frais bancaires | C63: 250000 | D63: 0.005 | E63: Calculé sur la base d'un forfait fixe annuel + variable en % du CA
B64: Divers | C64: 120000 | D64: 0 | E64: Calculé sur la base d'un forfait fixe annuel + variable en % du CA
B66: CHARGES DE PERSONNEL
B68: Note sur les charges : Il est possible de modifier le taux de charges salariales moyen proposé.
B70: Charges patronales (% du salaire brut) | C70: 0.19
B71: Charges salariales (% du salaire brut) | C71: 0.02
B72: Gratification minimale de stagiaire | C72: 0
B74: TVA
B76: Note sur la TVA : Vous pouvez définir un taux de TVA par type d'activité, qui sera utilisé aussi bien pour les encaissements de TVA liés au Chiffre d'affaires que pour les décaissements de TVA liés aux charges variables. Vous pouvez également définir un taux de TVA générique pour les investissements et les charges externes.
B78: Intitulés | C78: TVA - Charges variables | D78: TVA - Chiffre d'affaires
B79: =Config!$B$14 -> Abonnement Basique | C79: 0.2 | D79: 0.2
B80: =Config!$B$15 -> Abonnement Premium | C80: 0.2 | D80: 0.2
B81: =Config!$B$16 -> Conseil Personnalisé | C81: 0.2 | D81: 0.2
B82: =Config!$B$17 -> Plateforme de Marché en Ligne | C82: 0.2 | D82: 0.2
B83: =Config!$B$18 -> Formations et Ateliers | C83: 0.2 | D83: 0.2
B84: =Config!$B$19 -> Commission ventes 2% | C84: 0.2 | D84: 0.2
B85: =Config!$B$20 | C85: 0.2 | D85: 0.2
B86: =Config!$B$21 | C86: 0.2 | D86: 0.2
B87: =Config!$B$22 | C87: 0.2 | D87: 0.2
B88: =Config!$B$23 | C88: 0.2 | D88: 0.2
B89: =Config!$B$24 | C89: 0.2 | D89: 0.2
B90: =Config!$B$25 | C90: 0.2 | D90: 0.2
B92: Taux générique (investissements et charges externes) | C92: 0.2
B94: FINANCEMENTS
B96: Note sur le financement : Vous pouvez définir un taux ainsi qu'une durée de remboursement pour les prêts court et moyen/long termes.
C98: Court Terme | D98: Moyen/Long Terme
B99: Taux de prêt bancaire | C99: 0.17 | D99: 0.12
B100: Taux actuariel (taux sur la période globale d'emprunt) | C100: =-((PMT(C99/12,C101,10,,)*C101)+10)/10 -> 0.28349819 | D100: =-((PMT(D99/12,D101,10,,)*D101)+10)/10 -> 0.33466686
B101: Durée de remboursement (en mois) | C101: 36 | D101: 60

Sheet Personnel
B2: PERSONNEL
B5: Note : Renseignez dans cet onglet les informations sur le personnel de l'entreprise : Type de poste, salaires bruts annuels et nombre de salariés (par mois pour les années 1 et 2, puis par semestre). Pour les régimes TNS, précisez les salaires totalement chargés.
B7: Poste | C7: Année 1 | Q7: Année 2 | AE7: Année 3 | AI7: Année 4 | AM7: Année 5
C8: Salaires bruts annuels | D8: Nombre de salariés | Q8: Salaires bruts annuels | R8: Nombre de salariés | AE8: Salaires bruts annuels | AF8: Nombre de salariés | AI8: Salaires bruts annuels | AJ8: Nombre de salariés | AM8: Salaires bruts annuels | AN8: Nombre de salariés
D9: =Config!$C$7 -> 45505 | E9: =DATE(YEAR(D9),MONTH(D9)+1,DAY(D9)) -> 45536 | F9: =DATE(YEAR(E9),MONTH(E9)+1,DAY(E9)) -> 45566 | G9: =DATE(YEAR(F9),MONTH(F9)+1,DAY(F9)) -> 45597 | H9: =DATE(YEAR(G9),MONTH(G9)+1,DAY(G9)) -> 45627 | I9: =DATE(YEAR(H9),MONTH(H9)+1,DAY(H9)) -> 45658 | J9: =DATE(YEAR(I9),MONTH(I9)+1,DAY(I9)) -> 45689 | K9: =DATE(YEAR(J9),MONTH(J9)+1,DAY(J9)) -> 45717 | L9: =DATE(YEAR(K9),MONTH(K9)+1,DAY(K9)) -> 45748 | ... O9: =DATE(YEAR(N9),MONTH(N9)+1,DAY(N9)) -> 45839 | P9: ETP | R9: =DATE(YEAR(O9),MONTH(O9)+1,DAY(O9)) -> 45870 | S9: =DATE(YEAR(R9),MONTH(R9)+1,DAY(R9)) -> 45901 | T9: =DATE(YEAR(S9),MONTH(S9)+1,DAY(S9)) -> 45931 | U9: =DATE(YEAR(T9),MONTH(T9)+1,DAY(T9)) -> 45962 | V9: =DATE(YEAR(U9),MONTH(U9)+1,DAY(U9)) -> 45992 | W9: =DATE(YEAR(V9),MONTH(V9)+1,DAY(V9)) -> 46023 | X9: =DATE(YEAR(W9),MONTH(W9)+1,DAY(W9)) -> 46054 | Y9: =DATE(YEAR(X9),MONTH(X9)+1,DAY(X9)) -> 46082 | Z9: =DATE(YEAR(Y9),MONTH(Y9)+1,DAY(Y9)) -> 46113 | ... AC9: =DATE(YEAR(AB9),MONTH(AB9)+1,DAY(AB9)) -> 46204 | AD9: ETP | AF9: S1 | AG9: S2 | AH9: ETP | AJ9: S1 | AK9: S2 | AL9: ETP | AN9: S1 | AO9: S2 | AP9: ETP
B10: Dirigeant (régime TNS) | C10: 34000 | P10: =SUM(D10:O10)/12 -> 0 | AD10: =SUM(R10:AC10)/12 -> 0 | AH10: =SUM(AF10:AG10)/2 -> 0 | AL10: =SUM(AJ10:AK10)/2 -> 0 | AP10: =SUM(AN10:AO10)/2 -> 0
B11: Dirigeant (régime TNS) | P11: =SUM(D11:O11)/12 -> 0 | AD11: =SUM(R11:AC11)/12 -> 0 | AH11: =SUM(AF11:AG11)/2 -> 0 | AL11: =SUM(AJ11:AK11)/2 -> 0 | AP11: =SUM(AN11:AO11)/2 -> 0
B12: Dirigeant (salarié) | C12: 15600000 | D12: 1 | E12: 1 | F12: 1 | G12: 1 | H12: 1 | I12: 1 | J12: 1 | K12: 1 | L12: 1 | M12: 1 | N12: 1 | O12: 1 | P12: =SUM(D12:O12)/12 -> 1 | Q12: 31400000 | R12: 1 | S12: 1 | T12: 1 | U12: 1 | V12: 1 | W12: 1 | X12: 1 | Y12: 1 | Z12: 1 | AA12: 1 | AB12: 1 | AC12: 1 | AD12: =SUM(R12:AC12)/12 -> 1 | AE12: 47700000 | AF12: 1 | AG12: 1 | AH12: =SUM(AF12:AG12)/2 -> 1 | AL12: =SUM(AJ12:AK12)/2 -> 0 | AP12: =SUM(AN12:AO12)/2 -> 0
B13: Dirigeant (salarié) | C13: 15600000 | D13: 1 | E13: 1 | F13: 1 | G13: 1 | H13: 1 | I13: 1 | J13: 1 | K13: 1 | L13: 1 | M13: 1 | N13: 1 | O13: 1 | P13: =SUM(D13:O13)/12 -> 1 | Q13: 31400000 | R13: 1 | S13: 1 | T13: 1 | U13: 1 | V13: 1 | W13: 1 | X13: 1 | Y13: 1 | Z13: 1 | AA13: 1 | AB13: 1 | AC13: 1 | AD13: =SUM(R13:AC13)/12 -> 1 | AE13: 47700000 | AF13: 1 | AG13: 1 | AH13: =SUM(AF13:AG13)/2 -> 1 | AL13: =SUM(AJ13:AK13)/2 -> 0 | AP13: =SUM(AN13:AO13)/2 -> 0
B14: Réceptionniste | C14: 7800000 | I14: 1 | J14: 1 | K14: 1 | L14: 1 | M14: 1 | N14: 1 | O14: 1 | P14: =SUM(D14:O14)/12 -> 0.58333333 | Q14: 9600000 | R14: 1 | S14: 1 | T14: 1 | U14: 1 | V14: 1 | W14: 2 | X14: 2 | Y14: 2 | Z14: 2 | AA14: 2 | AB14: 2 | AC14: 2 | AD14: =SUM(R14:AC14)/12 -> 1.5833333 | AE14: 15600000 | AF14: 2 | AG14: 3 | AH14: =SUM(AF14:AG14)/2 -> 2.5 | AL14: =SUM(AJ14:AK14)/2 -> 0 | AP14: =SUM(AN14:AO14)/2 -> 0
B15: Couturière | C15: 9600000 | I15: 1 | J15: 1 | K15: 1 | L15: 1 | M15: 1 | N15: 1 | O15: 1 | P15: =SUM(D15:O15)/12 -> 0.58333333 | Q15: 15600000 | R15: 1 | S15: 1 | T15: 1 | U15: 1 | V15: 1 | W15: 1 | X15: 1 | Y15: 1 | Z15: 1 | AA15: 1 | AB15: 1 | AC15: 1 | AD15: =SUM(R15:AC15)/12 -> 1 | AE15: 21400000 | AF15: 2 | AG15: 2 | AH15: =SUM(AF15:AG15)/2 -> 2 | AL15: =SUM(AJ15:AK15)/2 -> 0 | AP15: =SUM(AN15:AO15)/2 -> 0
P16: =SUM(D16:O16)/12 -> 0 | AD16: =SUM(R16:AC16)/12 -> 0 | AH16: =SUM(AF16:AG16)/2 -> 0 | AL16: =SUM(AJ16:AK16)/2 -> 0 | AP16: =SUM(AN16:AO16)/2 -> 0
P17: =SUM(D17:O17)/12 -> 0 | AD17: =SUM(R17:AC17)/12 -> 0 | AH17: =SUM(AF17:AG17)/2 -> 0 | AL17: =SUM(AJ17:AK17)/2 -> 0 | AP17: =SUM(AN17:AO17)/2 -> 0
P18: =SUM(D18:O18)/12 -> 0 | AD18: =SUM(R18:AC18)/12 -> 0 | AH18: =SUM(AF18:AG18)/2 -> 0 | AL18: =SUM(AJ18:AK18)/2 -> 0 | AP18: =SUM(AN18:AO18)/2 -> 0
P19: =SUM(D19:O19)/12 -> 0 | AD19: =SUM(R19:AC19)/12 -> 0 | AH19: =SUM(AF19:AG19)/2 -> 0 | AL19: =SUM(AJ19:AK19)/2 -> 0 | AP19: =SUM(AN19:AO19)/2 -> 0
P20: =SUM(D20:O20)/12 -> 0 | AD20: =SUM(R20:AC20)/12 -> 0 | AH20: =SUM(AF20:AG20)/2 -> 0 | AL20: =SUM(AJ20:AK20)/2 -> 0 | AP20: =SUM(AN20:AO20)/2 -> 0
P21: =SUM(D21:O21)/12 -> 0 | AD21: =SUM(R21:AC21)/12 -> 0 | AH21: =SUM(AF21:AG21)/2 -> 0 | AL21: =SUM(AJ21:AK21)/2 -> 0 | AP21: =SUM(AN21:AO21)/2 -> 0
P22: =SUM(D22:O22)/12 -> 0 | AD22: =SUM(R22:AC22)/12 -> 0 | AH22: =SUM(AF22:AG22)/2 -> 0 | AL22: =SUM(AJ22:AK22)/2 -> 0 | AP22: =SUM(AN22:AO22)/2 -> 0
P23: =SUM(D23:O23)/12 -> 0 | AD23: =SUM(R23:AC23)/12 -> 0 | AH23: =SUM(AF23:AG23)/2 -> 0 | AL23: =SUM(AJ23:AK23)/2 -> 0 | AP23: =SUM(AN23:AO23)/2 -> 0
P24: =SUM(D24:O24)/12 -> 0 | AD24: =SUM(R24:AC24)/12 -> 0 | AH24: =SUM(AF24:AG24)/2 -> 0 | AL24: =SUM(AJ24:AK24)/2 -> 0 | AP24: =SUM(AN24:AO24)/2 -> 0
P25: =SUM(D25:O25)/12 -> 0 | AD25: =SUM(R25:AC25)/12 -> 0 | AH25: =SUM(AF25:AG25)/2 -> 0 | AL25: =SUM(AJ25:AK25)/2 -> 0 | AP25: =SUM(AN25:AO25)/2 -> 0
P26: =SUM(D26:O26)/12 -> 0 | AD26: =SUM(R26:AC26)/12 -> 0 | AH26: =SUM(AF26:AG26)/2 -> 0 | AL26: =SUM(AJ26:AK26)/2 -> 0 | AP26: =SUM(AN26:AO26)/2 -> 0
P27: =SUM(D27:O27)/12 -> 0 | AD27: =SUM(R27:AC27)/12 -> 0 | AH27: =SUM(AF27:AG27)/2 -> 0 | AL27: =SUM(AJ27:AK27)/2 -> 0 | AP27: =SUM(AN27:AO27)/2 -> 0
... P29: =SUM(D29:O29)/12 -> 0 | AD29: =SUM(R29:AC29)/12 -> 0 | AH29: =SUM(AF29:AG29)/2 -> 0 | AL29: =SUM(AJ29:AK29)/2 -> 0 | AP29: =SUM(AN29:AO29)/2 -> 0
B30: TOTAL | D30: =SUM(D10:D29) -> 2 | E30: =SUM(E10:E29) -> 2 | F30: =SUM(F10:F29) -> 2 | G30: =SUM(G10:G29) -> 2 | H30: =SUM(H10:H29) -> 2 | I30: =SUM(I10:I29) -> 4 | J30: =SUM(J10:J29) -> 4 | K30: =SUM(K10:K29) -> 4 | ... P30: =SUM(P10:P29) -> 3.1666667 | R30: =SUM(R10:R29) -> 4 | S30: =SUM(S10:S29) -> 4 | T30: =SUM(T10:T29) -> 4 | U30: =SUM(U10:U29) -> 4 | V30: =SUM(V10:V29) -> 4 | W30: =SUM(W10:W29) -> 5 | X30: =SUM(X10:X29) -> 5 | Y30: =SUM(Y10:Y29) -> 5 | ... AD30: =SUM(AD10:AD29) -> 4.5833333 | AF30: =SUM(AF10:AF29) -> 6 | AG30: =SUM(AG10:AG29) -> 7 | AH30: =SUM(AH10:AH29) -> 6.5 | AJ30: =SUM(AJ10:AJ29) -> 0 | AK30: =SUM(AK10:AK29) -> 0 | AL30: =SUM(AL10:AL29) -> 0 | AN30: =SUM(AN10:AN29) -> 0 | AO30: =SUM(AO10:AO29) -> 0 | AP30: =SUM(AP10:AP29) -> 0

Sheet Charges variables
B2: Charges variables (en € HT)
B5: Note : Ces tableaux sont remplis automatiquement après avoir complété les informations dans l'onglet "Configuration" liées aux "Charges variables" et les informations des commandes prévisionnelles dans l'onglet "Commandes".
C7: Année 1 | O7: Année 2 | AA7: Année 3 | AM7: Année 4 | AY7: Année 5
B8: Charges totales décaissées | C8: =Config!$C$7 -> 45505 | D8: =DATE(YEAR(C8),MONTH(C8)+1,DAY(C8)) -> 45536 | E8: =DATE(YEAR(D8),MONTH(D8)+1,DAY(D8)) -> 45566 | F8: =DATE(YEAR(E8),MONTH(E8)+1,DAY(E8)) -> 45597 | G8: =DATE(YEAR(F8),MONTH(F8)+1,DAY(F8)) -> 45627 | H8: =DATE(YEAR(G8),MONTH(G8)+1,DAY(G8)) -> 45658 | I8: =DATE(YEAR(H8),MONTH(H8)+1,DAY(H8)) -> 45689 | J8: =DATE(YEAR(I8),MONTH(I8)+1,DAY(I8)) -> 45717 | K8: =DATE(YEAR(J8),MONTH(J8)+1,DAY(J8)) -> 45748 | ... BJ8: =DATE(YEAR(BI8),MONTH(BI8)+1,DAY(BI8)) -> 47300
B9: =Config!$B$14 -> Abonnement Basique | C9: {=((Config!$F32*Commandes!C9)+IF(ROUND((C$8-Config!$C$7)/31,0)>=(Config!$D32+Config!$E32),INDEX(Commandes!$C9:Commandes!$BJ9,,COLUMN(C$8)-COLUMN($C$8)+1-(Config!$D32+Config!$E32)),0)*(1-Config!$F32))*Config!$C32} -> 0 | D9: {=((Config!$F32*Commandes!D9)+IF(ROUND((D$8-Config!$C$7)/31,0)>=(Config!$D32+Config!$E32),INDEX(Commandes!$C9:Commandes!$BJ9,,COLUMN(D$8)-COLUMN($C$8)+1-(Config!$D32+Config!$E32)),0)*(1-Config!$F32))*Config!$C32} -> 0 | E9: {=((Config!$F32*Commandes!E9)+IF(ROUND((E$8-Config!$C$7)/31,0)>=(Config!$D32+Config!$E32),INDEX(Commandes!$C9:Commandes!$BJ9,,COLUMN(E$8)-COLUMN($C$8)+1-(Config!$D32+Config!$E32)),0)*(1-Config!$F32))*Config!$C32} -> 450000 | F9: {=((Config!$F32*Commandes!F9)+IF(ROUND((F$8-Config!$C$7)/31,0)>=(Config!$D32+Config!$E32),INDEX(Commandes!$C9:Commandes!$BJ9,,COLUMN(F$8)-COLUMN($C$8)+1-(Config!$D32+Config!$E32)),0)*(1-Config!$F32))*Config!$C32} -> 750000 | G9: {=((Config!$F32*Commandes!G9)+IF(ROUND((G$8-Config!$C$7)/31,0)>=(Config!$D32+Config!$E32),INDEX(Commandes!$C9:Commandes!$BJ9,,COLUMN(G$8)-COLUMN($C$8)+1-(Config!$D32+Config!$E32)),0)*(1-Config!$F32))*Config!$C32} -> 1125000 | H9: {=((Config!$F32*Commandes!H9)+IF(ROUND((H$8-Config!$C$7)/31,0)>=(Config!$D32+Config!$E32),INDEX(Commandes!$C9:Commandes!$BJ9,,COLUMN(H$8)-COLUMN($C$8)+1-(Config!$D32+Config!$E32)),0)*(1-Config!$F32))*Config!$C32} -> 1500000 | I9: {=((Config!$F32*Commandes!I9)+IF(ROUND((I$8-Config!$C$7)/31,0)>=(Config!$D32+Config!$E32),INDEX(Commandes!$C9:Commandes!$BJ9,,COLUMN(I$8)-COLUMN($C$8)+1-(Config!$D32+Config!$E32)),0)*(1-Config!$F32))*Config!$C32} -> 1650000 | J9: {=((Config!$F32*Commandes!J9)+IF(ROUND((J$8-Config!$C$7)/31,0)>=(Config!$D32+Config!$E32),INDEX(Commandes!$C9:Commandes!$BJ9,,COLUMN(J$8)-COLUMN($C$8)+1-(Config!$D32+Config!$E32)),0)*(1-Config!$F32))*Config!$C32} -> 1815000 | ... BJ9: {=((Config!$F32*Commandes!BJ9)+IF(ROUND((BJ$8-Config!$C$7)/31,0)>=(Config!$D32+Config!$E32),INDEX(Commandes!$C9:Commandes!$BJ9,,COLUMN(BJ$8)-COLUMN($C$8)+1-(Config!$D32+Config!$E32)),0)*(1-Config!$F32))*Config!$C32} -> 450000000
B10: =Config!$B$15 -> Abonnement Premium | C10: {=((Config!$F33*Commandes!C10)+IF(ROUND((C$8-Config!$C$7)/31,0)>=(Config!$D33+Config!$E33),INDEX(Commandes!$C10:Commandes!$BJ10,,COLUMN(C$8)-COLUMN($C$8)+1-(Config!$D33+Config!$E33)),0)*(1-Config!$F33))*Config!$C33} -> 0 | D10: {=((Config!$F33*Commandes!D10)+IF(ROUND((D$8-Config!$C$7)/31,0)>=(Config!$D33+Config!$E33),INDEX(Commandes!$C10:Commandes!$BJ10,,COLUMN(D$8)-COLUMN($C$8)+1-(Config!$D33+Config!$E33)),0)*(1-Config!$F33))*Config!$C33} -> 0 | E10: {=((Config!$F33*Commandes!E10)+IF(ROUND((E$8-Config!$C$7)/31,0)>=(Config!$D33+Config!$E33),INDEX(Commandes!$C10:Commandes!$BJ10,,COLUMN(E$8)-COLUMN($C$8)+1-(Config!$D33+Config!$E33)),0)*(1-Config!$F33))*Config!$C33} -> 1250000 | F10: {=((Config!$F33*Commandes!F10)+IF(ROUND((F$8-Config!$C$7)/31,0)>=(Config!$D33+Config!$E33),INDEX(Commandes!$C10:Commandes!$BJ10,,COLUMN(F$8)-COLUMN($C$8)+1-(Config!$D33+Config!$E33)),0)*(1-Config!$F33))*Config!$C33} -> 2500000 | G10: {=((Config!$F33*Commandes!G10)+IF(ROUND((G$8-Config!$C$7)/31,0)>=(Config!$D33+Config!$E33),INDEX(Commandes!$C10:Commandes!$BJ10,,COLUMN(G$8)-COLUMN($C$8)+1-(Config!$D33+Config!$E33)),0)*(1-Config!$F33))*Config!$C33} -> 5000000 | H10: {=((Config!$F33*Commandes!H10)+IF(ROUND((H$8-Config!$C$7)/31,0)>=(Config!$D33+Config!$E33),INDEX(Commandes!$C10:Commandes!$BJ10,,COLUMN(H$8)-COLUMN($C$8)+1-(Config!$D33+Config!$E33)),0)*(1-Config!$F33))*Config!$C33} -> 12500000 | I10: {=((Config!$F33*Commandes!I10)+IF(ROUND((I$8-Config!$C$7)/31,0)>=(Config!$D33+Config!$E33),INDEX(Commandes!$C10:Commandes!$BJ10,,COLUMN(I$8)-COLUMN($C$8)+1-(Config!$D33+Config!$E33)),0)*(1-Config!$F33))*Config!$C33} -> 20000000 | J10: {=((Config!$F33*Commandes!J10)+IF(ROUND((J$8-Config!$C$7)/31,0)>=(Config!$D33+Config!$E33),INDEX(Commandes!$C10:Commandes!$BJ10,,COLUMN(J$8)-COLUMN($C$8)+1-(Config!$D33+Config!$E33)),0)*(1-Config!$F33))*Config!$C33} -> 25000000 | ... BJ10: {=((Config!$F33*Commandes!BJ10)+IF(ROUND((BJ$8-Config!$C$7)/31,0)>=(Config!$D33+Config!$E33),INDEX(Commandes!$C10:Commandes!$BJ10,,COLUMN(BJ$8)-COLUMN($C$8)+1-(Config!$D33+Config!$E33)),0)*(1-Config!$F33))*Config!$C33} -> 500000000
B11: =Config!$B$16 -> Conseil Personnalisé | C11: {=((Config!$F34*Commandes!C11)+IF(ROUND((C$8-Config!$C$7)/31,0)>=(Config!$D34+Config!$E34),INDEX(Commandes!$C11:Commandes!$BJ11,,COLUMN(C$8)-COLUMN($C$8)+1-(Config!$D34+Config!$E34)),0)*(1-Config!$F34))*Config!$C34} -> 0 | D11: {=((Config!$F34*Commandes!D11)+IF(ROUND((D$8-Config!$C$7)/31,0)>=(Config!$D34+Config!$E34),INDEX(Commandes!$C11:Commandes!$BJ11,,COLUMN(D$8)-COLUMN($C$8)+1-(Config!$D34+Config!$E34)),0)*(1-Config!$F34))*Config!$C34} -> 0 | E11: {=((Config!$F34*Commandes!E11)+IF(ROUND((E$8-Config!$C$7)/31,0)>=(Config!$D34+Config!$E34),INDEX(Commandes!$C11:Commandes!$BJ11,,COLUMN(E$8)-COLUMN($C$8)+1-(Config!$D34+Config!$E34)),0)*(1-Config!$F34))*Config!$C34} -> 0 | F11: {=((Config!$F34*Commandes!F11)+IF(ROUND((F$8-Config!$C$7)/31,0)>=(Config!$D34+Config!$E34),INDEX(Commandes!$C11:Commandes!$BJ11,,COLUMN(F$8)-COLUMN($C$8)+1-(Config!$D34+Config!$E34)),0)*(1-Config!$F34))*Config!$C34} -> 0 | G11: {=((Config!$F34*Commandes!G11)+IF(ROUND((G$8-Config!$C$7)/31,0)>=(Config!$D34+Config!$E34),INDEX(Commandes!$C11:Commandes!$BJ11,,COLUMN(G$8)-COLUMN($C$8)+1-(Config!$D34+Config!$E34)),0)*(1-Config!$F34))*Config!$C34} -> 0 | H11: {=((Config!$F34*Commandes!H11)+IF(ROUND((H$8-Config!$C$7)/31,0)>=(Config!$D34+Config!$E34),INDEX(Commandes!$C11:Commandes!$BJ11,,COLUMN(H$8)-COLUMN($C$8)+1-(Config!$D34+Config!$E34)),0)*(1-Config!$F34))*Config!$C34} -> 7200000 | I11: {=((Config!$F34*Commandes!I11)+IF(ROUND((I$8-Config!$C$7)/31,0)>=(Config!$D34+Config!$E34),INDEX(Commandes!$C11:Commandes!$BJ11,,COLUMN(I$8)-COLUMN($C$8)+1-(Config!$D34+Config!$E34)),0)*(1-Config!$F34))*Config!$C34} -> 7200000 | J11: {=((Config!$F34*Commandes!J11)+IF(ROUND((J$8-Config!$C$7)/31,0)>=(Config!$D34+Config!$E34),INDEX(Commandes!$C11:Commandes!$BJ11,,COLUMN(J$8)-COLUMN($C$8)+1-(Config!$D34+Config!$E34)),0)*(1-Config!$F34))*Config!$C34} -> 7200000 | ... BJ11: {=((Config!$F34*Commandes!BJ11)+IF(ROUND((BJ$8-Config!$C$7)/31,0)>=(Config!$D34+Config!$E34),INDEX(Commandes!$C11:Commandes!$BJ11,,COLUMN(BJ$8)-COLUMN($C$8)+1-(Config!$D34+Config!$E34)),0)*(1-Config!$F34))*Config!$C34} -> 18000000
B12: =Config!$B$17 -> Plateforme de Marché en Ligne | C12: {=((Config!$F35*Commandes!C12)+IF(ROUND((C$8-Config!$C$7)/31,0)>=(Config!$D35+Config!$E35),INDEX(Commandes!$C12:Commandes!$BJ12,,COLUMN(C$8)-COLUMN($C$8)+1-(Config!$D35+Config!$E35)),0)*(1-Config!$F35))*Config!$C35} -> 0 | D12: {=((Config!$F35*Commandes!D12)+IF(ROUND((D$8-Config!$C$7)/31,0)>=(Config!$D35+Config!$E35),INDEX(Commandes!$C12:Commandes!$BJ12,,COLUMN(D$8)-COLUMN($C$8)+1-(Config!$D35+Config!$E35)),0)*(1-Config!$F35))*Config!$C35} -> 0 | E12: {=((Config!$F35*Commandes!E12)+IF(ROUND((E$8-Config!$C$7)/31,0)>=(Config!$D35+Config!$E35),INDEX(Commandes!$C12:Commandes!$BJ12,,COLUMN(E$8)-COLUMN($C$8)+1-(Config!$D35+Config!$E35)),0)*(1-Config!$F35))*Config!$C35} -> 0 | F12: {=((Config!$F35*Commandes!F12)+IF(ROUND((F$8-Config!$C$7)/31,0)>=(Config!$D35+Config!$E35),INDEX(Commandes!$C12:Commandes!$BJ12,,COLUMN(F$8)-COLUMN($C$8)+1-(Config!$D35+Config!$E35)),0)*(1-Config!$F35))*Config!$C35} -> 0 | G12: {=((Config!$F35*Commandes!G12)+IF(ROUND((G$8-Config!$C$7)/31,0)>=(Config!$D35+Config!$E35),INDEX(Commandes!$C12:Commandes!$BJ12,,COLUMN(G$8)-COLUMN($C$8)+1-(Config!$D35+Config!$E35)),0)*(1-Config!$F35))*Config!$C35} -> 0 | H12: {=((Config!$F35*Commandes!H12)+IF(ROUND((H$8-Config!$C$7)/31,0)>=(Config!$D35+Config!$E35),INDEX(Commandes!$C12:Commandes!$BJ12,,COLUMN(H$8)-COLUMN($C$8)+1-(Config!$D35+Config!$E35)),0)*(1-Config!$F35))*Config!$C35} -> 0 | I12: {=((Config!$F35*Commandes!I12)+IF(ROUND((I$8-Config!$C$7)/31,0)>=(Config!$D35+Config!$E35),INDEX(Commandes!$C12:Commandes!$BJ12,,COLUMN(I$8)-COLUMN($C$8)+1-(Config!$D35+Config!$E35)),0)*(1-Config!$F35))*Config!$C35} -> 0 | J12: {=((Config!$F35*Commandes!J12)+IF(ROUND((J$8-Config!$C$7)/31,0)>=(Config!$D35+Config!$E35),INDEX(Commandes!$C12:Commandes!$BJ12,,COLUMN(J$8)-COLUMN($C$8)+1-(Config!$D35+Config!$E35)),0)*(1-Config!$F35))*Config!$C35} -> 0 | ... BJ12: {=((Config!$F35*Commandes!BJ12)+IF(ROUND((BJ$8-Config!$C$7)/31,0)>=(Config!$D35+Config!$E35),INDEX(Commandes!$C12:Commandes!$BJ12,,COLUMN(BJ$8)-COLUMN($C$8)+1-(Config!$D35+Config!$E35)),0)*(1-Config!$F35))*Config!$C35} -> 0
B13: =Config!$B$18 -> Formations et Ateliers | C13: {=((Config!$F36*Commandes!C13)+IF(ROUND((C$8-Config!$C$7)/31,0)>=(Config!$D36+Config!$E36),INDEX(Commandes!$C13:Commandes!$BJ13,,COLUMN(C$8)-COLUMN($C$8)+1-(Config!$D36+Config!$E36)),0)*(1-Config!$F36))*Config!$C36} -> 0 | D13: {=((Config!$F36*Commandes!D13)+IF(ROUND((D$8-Config!$C$7)/31,0)>=(Config!$D36+Config!$E36),INDEX(Commandes!$C13:Commandes!$BJ13,,COLUMN(D$8)-COLUMN($C$8)+1-(Config!$D36+Config!$E36)),0)*(1-Config!$F36))*Config!$C36} -> 0 | E13: {=((Config!$F36*Commandes!E13)+IF(ROUND((E$8-Config!$C$7)/31,0)>=(Config!$D36+Config!$E36),INDEX(Commandes!$C13:Commandes!$BJ13,,COLUMN(E$8)-COLUMN($C$8)+1-(Config!$D36+Config!$E36)),0)*(1-Config!$F36))*Config!$C36} -> 0 | F13: {=((Config!$F36*Commandes!F13)+IF(ROUND((F$8-Config!$C$7)/31,0)>=(Config!$D36+Config!$E36),INDEX(Commandes!$C13:Commandes!$BJ13,,COLUMN(F$8)-COLUMN($C$8)+1-(Config!$D36+Config!$E36)),0)*(1-Config!$F36))*Config!$C36} -> 0 | G13: {=((Config!$F36*Commandes!G13)+IF(ROUND((G$8-Config!$C$7)/31,0)>=(Config!$D36+Config!$E36),INDEX(Commandes!$C13:Commandes!$BJ13,,COLUMN(G$8)-COLUMN($C$8)+1-(Config!$D36+Config!$E36)),0)*(1-Config!$F36))*Config!$C36} -> 0 | H13: {=((Config!$F36*Commandes!H13)+IF(ROUND((H$8-Config!$C$7)/31,0)>=(Config!$D36+Config!$E36),INDEX(Commandes!$C13:Commandes!$BJ13,,COLUMN(H$8)-COLUMN($C$8)+1-(Config!$D36+Config!$E36)),0)*(1-Config!$F36))*Config!$C36} -> 0 | I13: {=((Config!$F36*Commandes!I13)+IF(ROUND((I$8-Config!$C$7)/31,0)>=(Config!$D36+Config!$E36),INDEX(Commandes!$C13:Commandes!$BJ13,,COLUMN(I$8)-COLUMN($C$8)+1-(Config!$D36+Config!$E36)),0)*(1-Config!$F36))*Config!$C36} -> 0 | J13: {=((Config!$F36*Commandes!J13)+IF(ROUND((J$8-Config!$C$7)/31,0)>=(Config!$D36+Config!$E36),INDEX(Commandes!$C13:Commandes!$BJ13,,COLUMN(J$8)-COLUMN($C$8)+1-(Config!$D36+Config!$E36)),0)*(1-Config!$F36))*Config!$C36} -> 0 | ... BJ13: {=((Config!$F36*Commandes!BJ13)+IF(ROUND((BJ$8-Config!$C$7)/31,0)>=(Config!$D36+Config!$E36),INDEX(Commandes!$C13:Commandes!$BJ13,,COLUMN(BJ$8)-COLUMN($C$8)+1-(Config!$D36+Config!$E36)),0)*(1-Config!$F36))*Config!$C36} -> 0
B14: =Config!$B$19 -> Commission ventes 2% | C14: {=((Config!$F37*Commandes!C14)+IF(ROUND((C$8-Config!$C$7)/31,0)>=(Config!$D37+Config!$E37),INDEX(Commandes!$C14:Commandes!$BJ14,,COLUMN(C$8)-COLUMN($C$8)+1-(Config!$D37+Config!$E37)),0)*(1-Config!$F37))*Config!$C37} -> 0 | D14: {=((Config!$F37*Commandes!D14)+IF(ROUND((D$8-Config!$C$7)/31,0)>=(Config!$D37+Config!$E37),INDEX(Commandes!$C14:Commandes!$BJ14,,COLUMN(D$8)-COLUMN($C$8)+1-(Config!$D37+Config!$E37)),0)*(1-Config!$F37))*Config!$C37} -> 0 | E14: {=((Config!$F37*Commandes!E14)+IF(ROUND((E$8-Config!$C$7)/31,0)>=(Config!$D37+Config!$E37),INDEX(Commandes!$C14:Commandes!$BJ14,,COLUMN(E$8)-COLUMN($C$8)+1-(Config!$D37+Config!$E37)),0)*(1-Config!$F37))*Config!$C37} -> 0 | F14: {=((Config!$F37*Commandes!F14)+IF(ROUND((F$8-Config!$C$7)/31,0)>=(Config!$D37+Config!$E37),INDEX(Commandes!$C14:Commandes!$BJ14,,COLUMN(F$8)-COLUMN($C$8)+1-(Config!$D37+Config!$E37)),0)*(1-Config!$F37))*Config!$C37} -> 0 | G14: {=((Config!$F37*Commandes!G14)+IF(ROUND((G$8-Config!$C$7)/31,0)>=(Config!$D37+Config!$E37),INDEX(Commandes!$C14:Commandes!$BJ14,,COLUMN(G$8)-COLUMN($C$8)+1-(Config!$D37+Config!$E37)),0)*(1-Config!$F37))*Config!$C37} -> 0 | H14: {=((Config!$F37*Commandes!H14)+IF(ROUND((H$8-Config!$C$7)/31,0)>=(Config!$D37+Config!$E37),INDEX(Commandes!$C14:Commandes!$BJ14,,COLUMN(H$8)-COLUMN($C$8)+1-(Config!$D37+Config!$E37)),0)*(1-Config!$F37))*Config!$C37} -> 0 | I14: {=((Config!$F37*Commandes!I14)+IF(ROUND((I$8-Config!$C$7)/31,0)>=(Config!$D37+Config!$E37),INDEX(Commandes!$C14:Commandes!$BJ14,,COLUMN(I$8)-COLUMN($C$8)+1-(Config!$D37+Config!$E37)),0)*(1-Config!$F37))*Config!$C37} -> 0 | J14: {=((Config!$F37*Commandes!J14)+IF(ROUND((J$8-Config!$C$7)/31,0)>=(Config!$D37+Config!$E37),INDEX(Commandes!$C14:Commandes!$BJ14,,COLUMN(J$8)-COLUMN($C$8)+1-(Config!$D37+Config!$E37)),0)*(1-Config!$F37))*Config!$C37} -> 0 | ... BJ14: {=((Config!$F37*Commandes!BJ14)+IF(ROUND((BJ$8-Config!$C$7)/31,0)>=(Config!$D37+Config!$E37),INDEX(Commandes!$C14:Commandes!$BJ14,,COLUMN(BJ$8)-COLUMN($C$8)+1-(Config!$D37+Config!$E37)),0)*(1-Config!$F37))*Config!$C37} -> 0
B15: =Config!$B$20 | C15: {=((Config!$F38*Commandes!C15)+IF(ROUND((C$8-Config!$C$7)/31,0)>=(Config!$D38+Config!$E38),INDEX(Commandes!$C15:Commandes!$BJ15,,COLUMN(C$8)-COLUMN($C$8)+1-(Config!$D38+Config!$E38)),0)*(1-Config!$F38))*Config!$C38} -> 0 | D15: {=((Config!$F38*Commandes!D15)+IF(ROUND((D$8-Config!$C$7)/31,0)>=(Config!$D38+Config!$E38),INDEX(Commandes!$C15:Commandes!$BJ15,,COLUMN(D$8)-COLUMN($C$8)+1-(Config!$D38+Config!$E38)),0)*(1-Config!$F38))*Config!$C38} -> 0 | E15: {=((Config!$F38*Commandes!E15)+IF(ROUND((E$8-Config!$C$7)/31,0)>=(Config!$D38+Config!$E38),INDEX(Commandes!$C15:Commandes!$BJ15,,COLUMN(E$8)-COLUMN($C$8)+1-(Config!$D38+Config!$E38)),0)*(1-Config!$F38))*Config!$C38} -> 0 | F15: {=((Config!$F38*Commandes!F15)+IF(ROUND((F$8-Config!$C$7)/31,0)>=(Config!$D38+Config!$E38),INDEX(Commandes!$C15:Commandes!$BJ15,,COLUMN(F$8)-COLUMN($C$8)+1-(Config!$D38+Config!$E38)),0)*(1-Config!$F38))*Config!$C38} -> 0 | G15: {=((Config!$F38*Commandes!G15)+IF(ROUND((G$8-Config!$C$7)/31,0)>=(Config!$D38+Config!$E38),INDEX(Commandes!$C15:Commandes!$BJ15,,COLUMN(G$8)-COLUMN($C$8)+1-(Config!$D38+Config!$E38)),0)*(1-Config!$F38))*Config!$C38} -> 0 | H15: {=((Config!$F38*Commandes!H15)+IF(ROUND((H$8-Config!$C$7)/31,0)>=(Config!$D38+Config!$E38),INDEX(Commandes!$C15:Commandes!$BJ15,,COLUMN(H$8)-COLUMN($C$8)+1-(Config!$D38+Config!$E38)),0)*(1-Config!$F38))*Config!$C38} -> 0 | I15: {=((Config!$F38*Commandes!I15)+IF(ROUND((I$8-Config!$C$7)/31,0)>=(Config!$D38+Config!$E38),INDEX(Commandes!$C15:Commandes!$BJ15,,COLUMN(I$8)-COLUMN($C$8)+1-(Config!$D38+Config!$E38)),0)*(1-Config!$F38))*Config!$C38} -> 0 | J15: {=((Config!$F38*Commandes!J15)+IF(ROUND((J$8-Config!$C$7)/31,0)>=(Config!$D38+Config!$E38),INDEX(Commandes!$C15:Commandes!$BJ15,,COLUMN(J$8)-COLUMN($C$8)+1-(Config!$D38+Config!$E38)),0)*(1-Config!$F38))*Config!$C38} -> 0 | ... BJ15: {=((Config!$F38*Commandes!BJ15)+IF(ROUND((BJ$8-Config!$C$7)/31,0)>=(Config!$D38+Config!$E38),INDEX(Commandes!$C15:Commandes!$BJ15,,COLUMN(BJ$8)-COLUMN($C$8)+1-(Config!$D38+Config!$E38)),0)*(1-Config!$F38))*Config!$C38} -> 0
B16: =Config!$B$21 | C16: {=((Config!$F39*Commandes!C16)+IF(ROUND((C$8-Config!$C$7)/31,0)>=(Config!$D39+Config!$E39),INDEX(Commandes!$C16:Commandes!$BJ16,,COLUMN(C$8)-COLUMN($C$8)+1-(Config!$D39+Config!$E39)),0)*(1-Config!$F39))*Config!$C39} -> 0 | D16: {=((Config!$F39*Commandes!D16)+IF(ROUND((D$8-Config!$C$7)/31,0)>=(Config!$D39+Config!$E39),INDEX(Commandes!$C16:Commandes!$BJ16,,COLUMN(D$8)-COLUMN($C$8)+1-(Config!$D39+Config!$E39)),0)*(1-Config!$F39))*Config!$C39} -> 0 | E16: {=((Config!$F39*Commandes!E16)+IF(ROUND((E$8-Config!$C$7)/31,0)>=(Config!$D39+Config!$E39),INDEX(Commandes!$C16:Commandes!$BJ16,,COLUMN(E$8)-COLUMN($C$8)+1-(Config!$D39+Config!$E39)),0)*(1-Config!$F39))*Config!$C39} -> 0 | F16: {=((Config!$F39*Commandes!F16)+IF(ROUND((F$8-Config!$C$7)/31,0)>=(Config!$D39+Config!$E39),INDEX(Commandes!$C16:Commandes!$BJ16,,COLUMN(F$8)-COLUMN($C$8)+1-(Config!$D39+Config!$E39)),0)*(1-Config!$F39))*Config!$C39} -> 0 | G16: {=((Config!$F39*Commandes!G16)+IF(ROUND((G$8-Config!$C$7)/31,0)>=(Config!$D39+Config!$E39),INDEX(Commandes!$C16:Commandes!$BJ16,,COLUMN(G$8)-COLUMN($C$8)+1-(Config!$D39+Config!$E39)),0)*(1-Config!$F39))*Config!$C39} -> 0 | H16: {=((Config!$F39*Commandes!H16)+IF(ROUND((H$8-Config!$C$7)/31,0)>=(Config!$D39+Config!$E39),INDEX(Commandes!$C16:Commandes!$BJ16,,COLUMN(H$8)-COLUMN($C$8)+1-(Config!$D39+Config!$E39)),0)*(1-Config!$F39))*Config!$C39} -> 0 | I16: {=((Config!$F39*Commandes!I16)+IF(ROUND((I$8-Config!$C$7)/31,0)>=(Config!$D39+Config!$E39),INDEX(Commandes!$C16:Commandes!$BJ16,,COLUMN(I$8)-COLUMN($C$8)+1-(Config!$D39+Config!$E39)),0)*(1-Config!$F39))*Config!$C39} -> 0 | J16: {=((Config!$F39*Commandes!J16)+IF(ROUND((J$8-Config!$C$7)/31,0)>=(Config!$D39+Config!$E39),INDEX(Commandes!$C16:Commandes!$BJ16,,COLUMN(J$8)-COLUMN($C$8)+1-(Config!$D39+Config!$E39)),0)*(1-Config!$F39))*Config!$C39} -> 0 | ... BJ16: {=((Config!$F39*Commandes!BJ16)+IF(ROUND((BJ$8-Config!$C$7)/31,0)>=(Config!$D39+Config!$E39),INDEX(Commandes!$C16:Commandes!$BJ16,,COLUMN(BJ$8)-COLUMN($C$8)+1-(Config!$D39+Config!$E39)),0)*(1-Config!$F39))*Config!$C39} -> 0
B17: =Config!$B$22 | C17: {=((Config!$F40*Commandes!C17)+IF(ROUND((C$8-Config!$C$7)/31,0)>=(Config!$D40+Config!$E40),INDEX(Commandes!$C17:Commandes!$BJ17,,COLUMN(C$8)-COLUMN($C$8)+1-(Config!$D40+Config!$E40)),0)*(1-Config!$F40))*Config!$C40} -> 0 | D17: {=((Config!$F40*Commandes!D17)+IF(ROUND((D$8-Config!$C$7)/31,0)>=(Config!$D40+Config!$E40),INDEX(Commandes!$C17:Commandes!$BJ17,,COLUMN(D$8)-COLUMN($C$8)+1-(Config!$D40+Config!$E40)),0)*(1-Config!$F40))*Config!$C40} -> 0 | E17: {=((Config!$F40*Commandes!E17)+IF(ROUND((E$8-Config!$C$7)/31,0)>=(Config!$D40+Config!$E40),INDEX(Commandes!$C17:Commandes!$BJ17,,COLUMN(E$8)-COLUMN($C$8)+1-(Config!$D40+Config!$E40)),0)*(1-Config!$F40))*Config!$C40} -> 0 | F17: {=((Config!$F40*Commandes!F17)+IF(ROUND((F$8-Config!$C$7)/31,0)>=(Config!$D40+Config!$E40),INDEX(Commandes!$C17:Commandes!$BJ17,,COLUMN(F$8)-COLUMN($C$8)+1-(Config!$D40+Config!$E40)),0)*(1-Config!$F40))*Config!$C40} -> 0 | G17: {=((Config!$F40*Commandes!G17)+IF(ROUND((G$8-Config!$C$7)/31,0)>=(Config!$D40+Config!$E40),INDEX(Commandes!$C17:Commandes!$BJ17,,COLUMN(G$8)-COLUMN($C$8)+1-(Config!$D40+Config!$E40)),0)*(1-Config!$F40))*Config!$C40} -> 0 | H17: {=((Config!$F40*Commandes!H17)+IF(ROUND((H$8-Config!$C$7)/31,0)>=(Config!$D40+Config!$E40),INDEX(Commandes!$C17:Commandes!$BJ17,,COLUMN(H$8)-COLUMN($C$8)+1-(Config!$D40+Config!$E40)),0)*(1-Config!$F40))*Config!$C40} -> 0 | I17: {=((Config!$F40*Commandes!I17)+IF(ROUND((I$8-Config!$C$7)/31,0)>=(Config!$D40+Config!$E40),INDEX(Commandes!$C17:Commandes!$BJ17,,COLUMN(I$8)-COLUMN($C$8)+1-(Config!$D40+Config!$E40)),0)*(1-Config!$F40))*Config!$C40} -> 0 | J17: {=((Config!$F40*Commandes!J17)+IF(ROUND((J$8-Config!$C$7)/31,0)>=(Config!$D40+Config!$E40),INDEX(Commandes!$C17:Commandes!$BJ17,,COLUMN(J$8)-COLUMN($C$8)+1-(Config!$D40+Config!$E40)),0)*(1-Config!$F40))*Config!$C40} -> 0 | ... BJ17: {=((Config!$F40*Commandes!BJ17)+IF(ROUND((BJ$8-Config!$C$7)/31,0)>=(Config!$D40+Config!$E40),INDEX(Commandes!$C17:Commandes!$BJ17,,COLUMN(BJ$8)-COLUMN($C$8)+1-(Config!$D40+Config!$E40)),0)*(1-Config!$F40))*Config!$C40} -> 0
B18: =Config!$B$23 | C18: {=((Config!$F41*Commandes!C18)+IF(ROUND((C$8-Config!$C$7)/31,0)>=(Config!$D41+Config!$E41),INDEX(Commandes!$C18:Commandes!$BJ18,,COLUMN(C$8)-COLUMN($C$8)+1-(Config!$D41+Config!$E41)),0)*(1-Config!$F41))*Config!$C41} -> 0 | D18: {=((Config!$F41*Commandes!D18)+IF(ROUND((D$8-Config!$C$7)/31,0)>=(Config!$D41+Config!$E41),INDEX(Commandes!$C18:Commandes!$BJ18,,COLUMN(D$8)-COLUMN($C$8)+1-(Config!$D41+Config!$E41)),0)*(1-Config!$F41))*Config!$C41} -> 0 | E18: {=((Config!$F41*Commandes!E18)+IF(ROUND((E$8-Config!$C$7)/31,0)>=(Config!$D41+Config!$E41),INDEX(Commandes!$C18:Commandes!$BJ18,,COLUMN(E$8)-COLUMN($C$8)+1-(Config!$D41+Config!$E41)),0)*(1-Config!$F41))*Config!$C41} -> 0 | F18: {=((Config!$F41*Commandes!F18)+IF(ROUND((F$8-Config!$C$7)/31,0)>=(Config!$D41+Config!$E41),INDEX(Commandes!$C18:Commandes!$BJ18,,COLUMN(F$8)-COLUMN($C$8)+1-(Config!$D41+Config!$E41)),0)*(1-Config!$F41))*Config!$C41} -> 0 | G18: {=((Config!$F41*Commandes!G18)+IF(ROUND((G$8-Config!$C$7)/31,0)>=(Config!$D41+Config!$E41),INDEX(Commandes!$C18:Commandes!$BJ18,,COLUMN(G$8)-COLUMN($C$8)+1-(Config!$D41+Config!$E41)),0)*(1-Config!$F41))*Config!$C41} -> 0 | H18: {=((Config!$F41*Commandes!H18)+IF(ROUND((H$8-Config!$C$7)/31,0)>=(Config!$D41+Config!$E41),INDEX(Commandes!$C18:Commandes!$BJ18,,COLUMN(H$8)-COLUMN($C$8)+1-(Config!$D41+Config!$E41)),0)*(1-Config!$F41))*Config!$C41} -> 0 | I18: {=((Config!$F41*Commandes!I18)+IF(ROUND((I$8-Config!$C$7)/31,0)>=(Config!$D41+Config!$E41),INDEX(Commandes!$C18:Commandes!$BJ18,,COLUMN(I$8)-COLUMN($C$8)+1-(Config!$D41+Config!$E41)),0)*(1-Config!$F41))*Config!$C41} -> 0 | J18: {=((Config!$F41*Commandes!J18)+IF(ROUND((J$8-Config!$C$7)/31,0)>=(Config!$D41+Config!$E41),INDEX(Commandes!$C18:Commandes!$BJ18,,COLUMN(J$8)-COLUMN($C$8)+1-(Config!$D41+Config!$E41)),0)*(1-Config!$F41))*Config!$C41} -> 0 | ... BJ18: {=((Config!$F41*Commandes!BJ18)+IF(ROUND((BJ$8-Config!$C$7)/31,0)>=(Config!$D41+Config!$E41),INDEX(Commandes!$C18:Commandes!$BJ18,,COLUMN(BJ$8)-COLUMN($C$8)+1-(Config!$D41+Config!$E41)),0)*(1-Config!$F41))*Config!$C41} -> 0
B19: =Config!$B$24 | C19: {=((Config!$F42*Commandes!C19)+IF(ROUND((C$8-Config!$C$7)/31,0)>=(Config!$D42+Config!$E42),INDEX(Commandes!$C19:Commandes!$BJ19,,COLUMN(C$8)-COLUMN($C$8)+1-(Config!$D42+Config!$E42)),0)*(1-Config!$F42))*Config!$C42} -> 0 | D19: {=((Config!$F42*Commandes!D19)+IF(ROUND((D$8-Config!$C$7)/31,0)>=(Config!$D42+Config!$E42),INDEX(Commandes!$C19:Commandes!$BJ19,,COLUMN(D$8)-COLUMN($C$8)+1-(Config!$D42+Config!$E42)),0)*(1-Config!$F42))*Config!$C42} -> 0 | E19: {=((Config!$F42*Commandes!E19)+IF(ROUND((E$8-Config!$C$7)/31,0)>=(Config!$D42+Config!$E42),INDEX(Commandes!$C19:Commandes!$BJ19,,COLUMN(E$8)-COLUMN($C$8)+1-(Config!$D42+Config!$E42)),0)*(1-Config!$F42))*Config!$C42} -> 0 | F19: {=((Config!$F42*Commandes!F19)+IF(ROUND((F$8-Config!$C$7)/31,0)>=(Config!$D42+Config!$E42),INDEX(Commandes!$C19:Commandes!$BJ19,,COLUMN(F$8)-COLUMN($C$8)+1-(Config!$D42+Config!$E42)),0)*(1-Config!$F42))*Config!$C42} -> 0 | G19: {=((Config!$F42*Commandes!G19)+IF(ROUND((G$8-Config!$C$7)/31,0)>=(Config!$D42+Config!$E42),INDEX(Commandes!$C19:Commandes!$BJ19,,COLUMN(G$8)-COLUMN($C$8)+1-(Config!$D42+Config!$E42)),0)*(1-Config!$F42))*Config!$C42} -> 0 | H19: {=((Config!$F42*Commandes!H19)+IF(ROUND((H$8-Config!$C$7)/31,0)>=(Config!$D42+Config!$E42),INDEX(Commandes!$C19:Commandes!$BJ19,,COLUMN(H$8)-COLUMN($C$8)+1-(Config!$D42+Config!$E42)),0)*(1-Config!$F42))*Config!$C42} -> 0 | I19: {=((Config!$F42*Commandes!I19)+IF(ROUND((I$8-Config!$C$7)/31,0)>=(Config!$D42+Config!$E42),INDEX(Commandes!$C19:Commandes!$BJ19,,COLUMN(I$8)-COLUMN($C$8)+1-(Config!$D42+Config!$E42)),0)*(1-Config!$F42))*Config!$C42} -> 0 | J19: {=((Config!$F42*Commandes!J19)+IF(ROUND((J$8-Config!$C$7)/31,0)>=(Config!$D42+Config!$E42),INDEX(Commandes!$C19:Commandes!$BJ19,,COLUMN(J$8)-COLUMN($C$8)+1-(Config!$D42+Config!$E42)),0)*(1-Config!$F42))*Config!$C42} -> 0 | ... BJ19: {=((Config!$F42*Commandes!BJ19)+IF(ROUND((BJ$8-Config!$C$7)/31,0)>=(Config!$D42+Config!$E42),INDEX(Commandes!$C19:Commandes!$BJ19,,COLUMN(BJ$8)-COLUMN($C$8)+1-(Config!$D42+Config!$E42)),0)*(1-Config!$F42))*Config!$C42} -> 0
B20: =Config!$B$25 | C20: {=((Config!$F43*Commandes!C20)+IF(ROUND((C$8-Config!$C$7)/31,0)>=(Config!$D43+Config!$E43),INDEX(Commandes!$C20:Commandes!$BJ20,,COLUMN(C$8)-COLUMN($C$8)+1-(Config!$D43+Config!$E43)),0)*(1-Config!$F43))*Config!$C43} -> 0 | D20: {=((Config!$F43*Commandes!D20)+IF(ROUND((D$8-Config!$C$7)/31,0)>=(Config!$D43+Config!$E43),INDEX(Commandes!$C20:Commandes!$BJ20,,COLUMN(D$8)-COLUMN($C$8)+1-(Config!$D43+Config!$E43)),0)*(1-Config!$F43))*Config!$C43} -> 0 | E20: {=((Config!$F43*Commandes!E20)+IF(ROUND((E$8-Config!$C$7)/31,0)>=(Config!$D43+Config!$E43),INDEX(Commandes!$C20:Commandes!$BJ20,,COLUMN(E$8)-COLUMN($C$8)+1-(Config!$D43+Config!$E43)),0)*(1-Config!$F43))*Config!$C43} -> 0 | F20: {=((Config!$F43*Commandes!F20)+IF(ROUND((F$8-Config!$C$7)/31,0)>=(Config!$D43+Config!$E43),INDEX(Commandes!$C20:Commandes!$BJ20,,COLUMN(F$8)-COLUMN($C$8)+1-(Config!$D43+Config!$E43)),0)*(1-Config!$F43))*Config!$C43} -> 0 | G20: {=((Config!$F43*Commandes!G20)+IF(ROUND((G$8-Config!$C$7)/31,0)>=(Config!$D43+Config!$E43),INDEX(Commandes!$C20:Commandes!$BJ20,,COLUMN(G$8)-COLUMN($C$8)+1-(Config!$D43+Config!$E43)),0)*(1-Config!$F43))*Config!$C43} -> 0 | H20: {=((Config!$F43*Commandes!H20)+IF(ROUND((H$8-Config!$C$7)/31,0)>=(Config!$D43+Config!$E43),INDEX(Commandes!$C20:Commandes!$BJ20,,COLUMN(H$8)-COLUMN($C$8)+1-(Config!$D43+Config!$E43)),0)*(1-Config!$F43))*Config!$C43} -> 0 | I20: {=((Config!$F43*Commandes!I20)+IF(ROUND((I$8-Config!$C$7)/31,0)>=(Config!$D43+Config!$E43),INDEX(Commandes!$C20:Commandes!$BJ20,,COLUMN(I$8)-COLUMN($C$8)+1-(Config!$D43+Config!$E43)),0)*(1-Config!$F43))*Config!$C43} -> 0 | J20: {=((Config!$F43*Commandes!J20)+IF(ROUND((J$8-Config!$C$7)/31,0)>=(Config!$D43+Config!$E43),INDEX(Commandes!$C20:Commandes!$BJ20,,COLUMN(J$8)-COLUMN($C$8)+1-(Config!$D43+Config!$E43)),0)*(1-Config!$F43))*Config!$C43} -> 0 | ... BJ20: {=((Config!$F43*Commandes!BJ20)+IF(ROUND((BJ$8-Config!$C$7)/31,0)>=(Config!$D43+Config!$E43),INDEX(Commandes!$C20:Commandes!$BJ20,,COLUMN(BJ$8)-COLUMN($C$8)+1-(Config!$D43+Config!$E43)),0)*(1-Config!$F43))*Config!$C43} -> 0
B22: TOTAL | C22: =SUM(C9:C20) -> 0 | D22: =SUM(D9:D20) -> 0 | E22: =SUM(E9:E20) -> 1700000 | F22: =SUM(F9:F20) -> 3250000 | G22: =SUM(G9:G20) -> 6125000 | H22: =SUM(H9:H20) -> 21200000 | I22: =SUM(I9:I20) -> 28850000 | J22: =SUM(J9:J20) -> 34015000 | ... BJ22: =SUM(BJ9:BJ20) -> 968000000
B23: TOTAL annuel cumulé | C23: =C22 -> 0 | D23: =C23+D22 -> 0 | E23: =D23+E22 -> 1700000 | F23: =E23+F22 -> 4950000 | G23: =F23+G22 -> 11075000 | H23: =G23+H22 -> 32275000 | I23: =H23+I22 -> 61125000 | J23: =I23+J22 -> 95140000 | K23: =J23+K22 -> 134336500 | ... N23: =M23+N22 -> 2.6820576e+08 | O23: =O22 -> 63723076 | P23: =O23+P22 -> 1.3317692e+08 | Q23: =P23+Q22 -> 2.1104423e+08 | R23: =Q23+R22 -> 292553358 | S23: =R23+S22 -> 3.7798977e+08 | T23: =S23+T22 -> 4.7021029e+08 | U23: =T23+U22 -> 5.6716094e+08 | V23: =U23+V22 -> 6.7189925e+08 | W23: =V23+W22 -> 7.8512214e+08 | ... Z23: =Y23+Z22 -> 1171803094 | AA23: =AA22 -> 1.5803635e+08 | AB23: =AA23+AB22 -> 3.2920679e+08 | AC23: =AB23+AC22 -> 5.1366983e+08 | AD23: =AC23+AD22 -> 7.1474864e+08 | AE23: =AD23+AE22 -> 936597146 | AF23: =AE23+AF22 -> 1184407782 | AG23: =AF23+AG22 -> 1464671076 | AH23: =AG23+AH22 -> 1785500194 | AI23: =AH23+AI22 -> 2157036592 | ... AL23: =AK23+AL22 -> 3374107710 | AM23: =AM22 -> 373000000 | AN23: =AM23+AN22 -> 746000000 | AO23: =AN23+AO22 -> 1119000000 | AP23: =AO23+AP22 -> 1537000000 | AQ23: =AP23+AQ22 -> 1955000000 | AR23: =AQ23+AR22 -> 2373000000 | AS23: =AR23+AS22 -> 2896000000 | AT23: =AS23+AT22 -> 3419000000 | AU23: =AT23+AU22 -> 3942000000 | ... AX23: =AW23+AX22 -> 5646000000 | AY23: =AY22 -> 768000000 | AZ23: =AY23+AZ22 -> 1536000000 | BA23: =AZ23+BA22 -> 2304000000 | BB23: =BA23+BB22 -> 3072000000 | BC23: =BB23+BC22 -> 3840000000 | BD23: =BC23+BD22 -> 4608000000 | BE23: =BD23+BE22 -> 5576000000 | BF23: =BE23+BF22 -> 6544000000 | BG23: =BF23+BG22 -> 7512000000 | ... BJ23: =BI23+BJ22 -> 10416000000
C25: Année 1 | O25: Année 2 | AA25: Année 3 | AN25: Année 4 | AY25: Année 5
B26: Charges totales | C26: =Config!$C$7 -> 45505 | D26: =DATE(YEAR(C26),MONTH(C26)+1,DAY(C26)) -> 45536 | E26: =DATE(YEAR(D26),MONTH(D26)+1,DAY(D26)) -> 45566 | F26: =DATE(YEAR(E26),MONTH(E26)+1,DAY(E26)) -> 45597 | G26: =DATE(YEAR(F26),MONTH(F26)+1,DAY(F26)) -> 45627 | H26: =DATE(YEAR(G26),MONTH(G26)+1,DAY(G26)) -> 45658 | I26: =DATE(YEAR(H26),MONTH(H26)+1,DAY(H26)) -> 45689 | J26: =DATE(YEAR(I26),MONTH(I26)+1,DAY(I26)) -> 45717 | K26: =DATE(YEAR(J26),MONTH(J26)+1,DAY(J26)) -> 45748 | ... BJ26: =DATE(YEAR(BI26),MONTH(BI26)+1,DAY(BI26)) -> 47300
B27: =Config!$B$14 -> Abonnement Basique | C27: =Config!$C32*Commandes!C9 -> 0 | D27: =Config!$C32*Commandes!D9 -> 0 | E27: =Config!$C32*Commandes!E9 -> 450000 | F27: =Config!$C32*Commandes!F9 -> 750000 | G27: =Config!$C32*Commandes!G9 -> 1125000 | H27: =Config!$C32*Commandes!H9 -> 1500000 | I27: =Config!$C32*Commandes!I9 -> 1650000 | J27: =Config!$C32*Commandes!J9 -> 1815000 | ... BJ27: =Config!$C32*Commandes!BJ9 -> 450000000
B28: =Config!$B$15 -> Abonnement Premium | C28: =Config!$C33*Commandes!C10 -> 0 | D28: =Config!$C33*Commandes!D10 -> 0 | E28: =Config!$C33*Commandes!E10 -> 1250000 | F28: =Config!$C33*Commandes!F10 -> 2500000 | G28: =Config!$C33*Commandes!G10 -> 5000000 | H28: =Config!$C33*Commandes!H10 -> 12500000 | I28: =Config!$C33*Commandes!I10 -> 20000000 | J28: =Config!$C33*Commandes!J10 -> 25000000 | ... BJ28: =Config!$C33*Commandes!BJ10 -> 500000000
B29: =Config!$B$16 -> Conseil Personnalisé | C29: =Config!$C34*Commandes!C11 -> 0 | D29: =Config!$C34*Commandes!D11 -> 0 | E29: =Config!$C34*Commandes!E11 -> 0 | F29: =Config!$C34*Commandes!F11 -> 0 | G29: =Config!$C34*Commandes!G11 -> 0 | H29: =Config!$C34*Commandes!H11 -> 7200000 | I29: =Config!$C34*Commandes!I11 -> 7200000 | J29: =Config!$C34*Commandes!J11 -> 7200000 | ... BJ29: =Config!$C34*Commandes!BJ11 -> 18000000
B30: =Config!$B$17 -> Plateforme de Marché en Ligne | C30: =Config!$C35*Commandes!C12 -> 0 | D30: =Config!$C35*Commandes!D12 -> 0 | E30: =Config!$C35*Commandes!E12 -> 0 | F30: =Config!$C35*Commandes!F12 -> 0 | G30: =Config!$C35*Commandes!G12 -> 0 | H30: =Config!$C35*Commandes!H12 -> 0 | I30: =Config!$C35*Commandes!I12 -> 0 | J30: =Config!$C35*Commandes!J12 -> 0 | ... BJ30: =Config!$C35*Commandes!BJ12 -> 0
B31: =Config!$B$18 -> Formations et Ateliers | C31: =Config!$C36*Commandes!C13 -> 0 | D31: =Config!$C36*Commandes!D13 -> 0 | E31: =Config!$C36*Commandes!E13 -> 0 | F31: =Config!$C36*Commandes!F13 -> 0 | G31: =Config!$C36*Commandes!G13 -> 0 | H31: =Config!$C36*Commandes!H13 -> 0 | I31: =Config!$C36*Commandes!I13 -> 0 | J31: =Config!$C36*Commandes!J13 -> 0 | ... BJ31: =Config!$C36*Commandes!BJ13 -> 0
B32: =Config!$B$19 -> Commission ventes 2% | C32: =Config!$C37*Commandes!C14 -> 0 | D32: =Config!$C37*Commandes!D14 -> 0 | E32: =Config!$C37*Commandes!E14 -> 0 | F32: =Config!$C37*Commandes!F14 -> 0 | G32: =Config!$C37*Commandes!G14 -> 0 | H32: =Config!$C37*Commandes!H14 -> 0 | I32: =Config!$C37*Commandes!I14 -> 0 | J32: =Config!$C37*Commandes!J14 -> 0 | ... BJ32: =Config!$C37*Commandes!BJ14 -> 0
B33: =Config!$B$20 | C33: =Config!$C38*Commandes!C15 -> 0 | D33: =Config!$C38*Commandes!D15 -> 0 | E33: =Config!$C38*Commandes!E15 -> 0 | F33: =Config!$C38*Commandes!F15 -> 0 | G33: =Config!$C38*Commandes!G15 -> 0 | H33: =Config!$C38*Commandes!H15 -> 0 | I33: =Config!$C38*Commandes!I15 -> 0 | J33: =Config!$C38*Commandes!J15 -> 0 | ... BJ33: =Config!$C38*Commandes!BJ15 -> 0
B34: =Config!$B$21 | C34: =Config!$C39*Commandes!C16 -> 0 | D34: =Config!$C39*Commandes!D16 -> 0 | E34: =Config!$C39*Commandes!E16 -> 0 | F34: =Config!$C39*Commandes!F16 -> 0 | G34: =Config!$C39*Commandes!G16 -> 0 | H34: =Config!$C39*Commandes!H16 -> 0 | I34: =Config!$C39*Commandes!I16 -> 0 | J34: =Config!$C39*Commandes!J16 -> 0 | ... BJ34: =Config!$C39*Commandes!BJ16 -> 0
B35: =Config!$B$22 | C35: =Config!$C40*Commandes!C17 -> 0 | D35: =Config!$C40*Commandes!D17 -> 0 | E35: =Config!$C40*Commandes!E17 -> 0 | F35: =Config!$C40*Commandes!F17 -> 0 | G35: =Config!$C40*Commandes!G17 -> 0 | H35: =Config!$C40*Commandes!H17 -> 0 | I35: =Config!$C40*Commandes!I17 -> 0 | J35: =Config!$C40*Commandes!J17 -> 0 | ... BJ35: =Config!$C40*Commandes!BJ17 -> 0
B36: =Config!$B$23 | C36: =Config!$C41*Commandes!C18 -> 0 | D36: =Config!$C41*Commandes!D18 -> 0 | E36: =Config!$C41*Commandes!E18 -> 0 | F36: =Config!$C41*Commandes!F18 -> 0 | G36: =Config!$C41*Commandes!G18 -> 0 | H36: =Config!$C41*Commandes!H18 -> 0 | I36: =Config!$C41*Commandes!I18 -> 0 | J36: =Config!$C41*Commandes!J18 -> 0 | ... BJ36: =Config!$C41*Commandes!BJ18 -> 0
B37: =Config!$B$24 | C37: =Config!$C42*Commandes!C19 -> 0 | D37: =Config!$C42*Commandes!D19 -> 0 | E37: =Config!$C42*Commandes!E19 -> 0 | F37: =Config!$C42*Commandes!F19 -> 0 | G37: =Config!$C42*Commandes!G19 -> 0 | H37: =Config!$C42*Commandes!H19 -> 0 | I37: =Config!$C42*Commandes!I19 -> 0 | J37: =Config!$C42*Commandes!J19 -> 0 | ... BJ37: =Config!$C42*Commandes!BJ19 -> 0
B38: =Config!$B$25 | C38: =Config!$C43*Commandes!C20 -> 0 | D38: =Config!$C43*Commandes!D20 -> 0 | E38: =Config!$C43*Commandes!E20 -> 0 | F38: =Config!$C43*Commandes!F20 -> 0 | G38: =Config!$C43*Commandes!G20 -> 0 | H38: =Config!$C43*Commandes!H20 -> 0 | I38: =Config!$C43*Commandes!I20 -> 0 | J38: =Config!$C43*Commandes!J20 -> 0 | ... BJ38: =Config!$C43*Commandes!BJ20 -> 0
B40: TOTAL | C40: =SUM(C27:C38) -> 0 | D40: =SUM(D27:D38) -> 0 | E40: =SUM(E27:E38) -> 1700000 | F40: =SUM(F27:F38) -> 3250000 | G40: =SUM(G27:G38) -> 6125000 | H40: =SUM(H27:H38) -> 21200000 | I40: =SUM(I27:I38) -> 28850000 | J40: =SUM(J27:J38) -> 34015000 | ... BJ40: =SUM(BJ27:BJ38) -> 968000000
B41: TOTAL annuel cumulé | C41: =C40 -> 0 | D41: =C41+D40 -> 0 | E41: =D41+E40 -> 1700000 | F41: =E41+F40 -> 4950000 | G41: =F41+G40 -> 11075000 | H41: =G41+H40 -> 32275000 | I41: =H41+I40 -> 61125000 | J41: =I41+J40 -> 95140000 | K41: =J41+K40 -> 134336500 | ... N41: =M41+N40 -> 2.6820576e+08 | O41: =O40 -> 63723076 | P41: =O41+P40 -> 1.3317692e+08 | Q41: =P41+Q40 -> 2.1104423e+08 | R41: =Q41+R40 -> 292553358 | S41: =R41+S40 -> 3.7798977e+08 | T41: =S41+T40 -> 4.7021029e+08 | U41: =T41+U40 -> 5.6716094e+08 | V41: =U41+V40 -> 6.7189925e+08 | W41: =V41+W40 -> 7.8512214e+08 | ... Z41: =Y41+Z40 -> 1171803094 | AA41: =AA40 -> 1.5803635e+08 | AB41: =AA41+AB40 -> 3.2920679e+08 | AC41: =AB41+AC40 -> 5.1366983e+08 | AD41: =AC41+AD40 -> 7.1474864e+08 | AE41: =AD41+AE40 -> 936597146 | AF41: =AE41+AF40 -> 1184407782 | AG41: =AF41+AG40 -> 1464671076 | AH41: =AG41+AH40 -> 1785500194 | AI41: =AH41+AI40 -> 2157036592 | ... AL41: =AK41+AL40 -> 3374107710 | AM41: =AM40 -> 373000000 | AN41: =AM41+AN40 -> 746000000 | AO41: =AN41+AO40 -> 1119000000 | AP41: =AO41+AP40 -> 1537000000 | AQ41: =AP41+AQ40 -> 1955000000 | AR41: =AQ41+AR40 -> 2373000000 | AS41: =AR41+AS40 -> 2896000000 | AT41: =AS41+AT40 -> 3419000000 | AU41: =AT41+AU40 -> 3942000000 | ... AX41: =AW41+AX40 -> 5646000000 | AY41: =AY40 -> 768000000 | AZ41: =AY41+AZ40 -> 1536000000 | BA41: =AZ41+BA40 -> 2304000000 | BB41: =BA41+BB40 -> 3072000000 | BC41: =BB41+BC40 -> 3840000000 | BD41: =BC41+BD40 -> 4608000000 | BE41: =BD41+BE40 -> 5576000000 | BF41: =BE41+BF40 -> 6544000000 | BG41: =BF41+BG40 -> 7512000000 | ... BJ41: =BI41+BJ40 -> 10416000000

Sheet Personnel - Calculs auto
B2: Calculs auto liés au Personnel
C5: Année 1 | D5: Année 2 | E5: Année 3 | F5: Année 4 | G5: Année 5
B6: Nb employés | C6: =Personnel!P30 -> 3.1666667 | D6: =Personnel!AD30 -> 4.5833333 | E6: =Personnel!AH30 -> 6.5 | F6: =Personnel!AL30 -> 0 | G6: =Personnel!AP30 -> 0
B8: Salaires bruts
B9: Année 1 | O9: Année 2 | AB9: Année 3 | AE9: Année 4 | AH9: Année 5
B10: =Config!$C$7 -> 45505 | C10: =DATE(YEAR(B10),MONTH(B10)+1,DAY(B10)) -> 45536 | D10: =DATE(YEAR(C10),MONTH(C10)+1,DAY(C10)) -> 45566 | E10: =DATE(YEAR(D10),MONTH(D10)+1,DAY(D10)) -> 45597 | F10: =DATE(YEAR(E10),MONTH(E10)+1,DAY(E10)) -> 45627 | G10: =DATE(YEAR(F10),MONTH(F10)+1,DAY(F10)) -> 45658 | H10: =DATE(YEAR(G10),MONTH(G10)+1,DAY(G10)) -> 45689 | I10: =DATE(YEAR(H10),MONTH(H10)+1,DAY(H10)) -> 45717 | J10: =DATE(YEAR(I10),MONTH(I10)+1,DAY(I10)) -> 45748 | ... M10: =DATE(YEAR(L10),MONTH(L10)+1,DAY(L10)) -> 45839 | N10: Total | O10: =DATE(YEAR(M10),MONTH(M10)+1,DAY(M10)) -> 45870 | P10: =DATE(YEAR(O10),MONTH(O10)+1,DAY(O10)) -> 45901 | Q10: =DATE(YEAR(P10),MONTH(P10)+1,DAY(P10)) -> 45931 | R10: =DATE(YEAR(Q10),MONTH(Q10)+1,DAY(Q10)) -> 45962 | S10: =DATE(YEAR(R10),MONTH(R10)+1,DAY(R10)) -> 45992 | T10: =DATE(YEAR(S10),MONTH(S10)+1,DAY(S10)) -> 46023 | U10: =DATE(YEAR(T10),MONTH(T10)+1,DAY(T10)) -> 46054 | V10: =DATE(YEAR(U10),MONTH(U10)+1,DAY(U10)) -> 46082 | W10: =DATE(YEAR(V10),MONTH(V10)+1,DAY(V10)) -> 46113 | ... Z10: =DATE(YEAR(Y10),MONTH(Y10)+1,DAY(Y10)) -> 46204 | AA10: Total | AB10: S1 | AC10: S2 | AD10: Total | AE10: S1 | AF10: S2 | AG10: Total | AH10: S1 | AI10: S2 | AJ10: Total
B11: =Personnel!$C10*Personnel!D10/12 -> 0 | C11: =Personnel!$C10*Personnel!E10/12 -> 0 | D11: =Personnel!$C10*Personnel!F10/12 -> 0 | E11: =Personnel!$C10*Personnel!G10/12 -> 0 | F11: =Personnel!$C10*Personnel!H10/12 -> 0 | G11: =Personnel!$C10*Personnel!I10/12 -> 0 | H11: =Personnel!$C10*Personnel!J10/12 -> 0 | I11: =Personnel!$C10*Personnel!K10/12 -> 0 | ... M11: =Personnel!$C10*Personnel!O10/12 -> 0 | N11: =SUM(B11:M11) -> 0 | O11: =Personnel!$Q10*Personnel!R10/12 -> 0 | P11: =Personnel!$Q10*Personnel!S10/12 -> 0 | Q11: =Personnel!$Q10*Personnel!T10/12 -> 0 | R11: =Personnel!$Q10*Personnel!U10/12 -> 0 | S11: =Personnel!$Q10*Personnel!V10/12 -> 0 | T11: =Personnel!$Q10*Personnel!W10/12 -> 0 | U11: =Personnel!$Q10*Personnel!X10/12 -> 0 | V11: =Personnel!$Q10*Personnel!Y10/12 -> 0 | ... Z11: =Personnel!$Q10*Personnel!AC10/12 -> 0 | AA11: =SUM(O11:Z11) -> 0 | AB11: =Personnel!$AE10*Personnel!AF10/2 -> 0 | AC11: =Personnel!$AE10*Personnel!AG10/2 -> 0 | AD11: =SUM(AB11:AC11) -> 0 | AE11: =Personnel!$AI10*Personnel!AJ10/2 -> 0 | AF11: =Personnel!$AI10*Personnel!AK10/2 -> 0 | AG11: =SUM(AE11:AF11) -> 0 | AH11: =Personnel!$AM10*Personnel!AN10/2 -> 0 | AI11: =Personnel!$AM10*Personnel!AO10/2 -> 0 | AJ11: =SUM(AH11:AI11) -> 0
B12: =Personnel!$C11*Personnel!D11/12 -> 0 | C12: =Personnel!$C11*Personnel!E11/12 -> 0 | D12: =Personnel!$C11*Personnel!F11/12 -> 0 | E12: =Personnel!$C11*Personnel!G11/12 -> 0 | F12: =Personnel!$C11*Personnel!H11/12 -> 0 | G12: =Personnel!$C11*Personnel!I11/12 -> 0 | H12: =Personnel!$C11*Personnel!J11/12 -> 0 | I12: =Personnel!$C11*Personnel!K11/12 -> 0 | ... M12: =Personnel!$C11*Personnel!O11/12 -> 0 | N12: =SUM(B12:M12) -> 0 | O12: =Personnel!$Q11*Personnel!R11/12 -> 0 | P12: =Personnel!$Q11*Personnel!S11/12 -> 0 | Q12: =Personnel!$Q11*Personnel!T11/12 -> 0 | R12: =Personnel!$Q11*Personnel!U11/12 -> 0 | S12: =Personnel!$Q11*Personnel!V11/12 -> 0 | T12: =Personnel!$Q11*Personnel!W11/12 -> 0 | U12: =Personnel!$Q11*Personnel!X11/12 -> 0 | V12: =Personnel!$Q11*Personnel!Y11/12 -> 0 | ... Z12: =Personnel!$Q11*Personnel!AC11/12 -> 0 | AA12: =SUM(O12:Z12) -> 0 | AB12: =Personnel!$AE11*Personnel!AF11/2 -> 0 | AC12: =Personnel!$AE11*Personnel!AG11/2 -> 0 | AD12: =SUM(AB12:AC12) -> 0 | AE12: =Personnel!$AI11*Personnel!AJ11/2 -> 0 | AF12: =Personnel!$AI11*Personnel!AK11/2 -> 0 | AG12: =SUM(AE12:AF12) -> 0 | AH12: =Personnel!$AM11*Personnel!AN11/2 -> 0 | AI12: =Personnel!$AM11*Personnel!AO11/2 -> 0 | AJ12: =SUM(AH12:AI12) -> 0
B13: =Personnel!$C12*Personnel!D12/12 -> 1300000 | C13: =Personnel!$C12*Personnel!E12/12 -> 1300000 | D13: =Personnel!$C12*Personnel!F12/12 -> 1300000 | E13: =Personnel!$C12*Personnel!G12/12 -> 1300000 | F13: =Personnel!$C12*Personnel!H12/12 -> 1300000 | G13: =Personnel!$C12*Personnel!I12/12 -> 1300000 | H13: =Personnel!$C12*Personnel!J12/12 -> 1300000 | I13: =Personnel!$C12*Personnel!K12/12 -> 1300000 | ... M13: =Personnel!$C12*Personnel!O12/12 -> 1300000 | N13: =SUM(B13:M13) -> 15600000 | O13: =Personnel!$Q12*Personnel!R12/12 -> 2616666.7 | P13: =Personnel!$Q12*Personnel!S12/12 -> 2616666.7 | Q13: =Personnel!$Q12*Personnel!T12/12 -> 2616666.7 | R13: =Personnel!$Q12*Personnel!U12/12 -> 2616666.7 | S13: =Personnel!$Q12*Personnel!V12/12 -> 2616666.7 | T13: =Personnel!$Q12*Personnel!W12/12 -> 2616666.7 | U13: =Personnel!$Q12*Personnel!X12/12 -> 2616666.7 | V13: =Personnel!$Q12*Personnel!Y12/12 -> 2616666.7 | ... Z13: =Personnel!$Q12*Personnel!AC12/12 -> 2616666.7 | AA13: =SUM(O13:Z13) -> 31400000 | AB13: =Personnel!$AE12*Personnel!AF12/2 -> 23850000 | AC13: =Personnel!$AE12*Personnel!AG12/2 -> 23850000 | AD13: =SUM(AB13:AC13) -> 47700000 | AE13: =Personnel!$AI12*Personnel!AJ12/2 -> 0 | AF13: =Personnel!$AI12*Personnel!AK12/2 -> 0 | AG13: =SUM(AE13:AF13) -> 0 | AH13: =Personnel!$AM12*Personnel!AN12/2 -> 0 | AI13: =Personnel!$AM12*Personnel!AO12/2 -> 0 | AJ13: =SUM(AH13:AI13) -> 0
B14: =Personnel!$C13*Personnel!D13/12 -> 1300000 | C14: =Personnel!$C13*Personnel!E13/12 -> 1300000 | D14: =Personnel!$C13*Personnel!F13/12 -> 1300000 | E14: =Personnel!$C13*Personnel!G13/12 -> 1300000 | F14: =Personnel!$C13*Personnel!H13/12 -> 1300000 | G14: =Personnel!$C13*Personnel!I13/12 -> 1300000 | H14: =Personnel!$C13*Personnel!J13/12 -> 1300000 | I14: =Personnel!$C13*Personnel!K13/12 -> 1300000 | ... M14: =Personnel!$C13*Personnel!O13/12 -> 1300000 | N14: =SUM(B14:M14) -> 15600000 | O14: =Personnel!$Q13*Personnel!R13/12 -> 2616666.7 | P14: =Personnel!$Q13*Personnel!S13/12 -> 2616666.7 | Q14: =Personnel!$Q13*Personnel!T13/12 -> 2616666.7 | R14: =Personnel!$Q13*Personnel!U13/12 -> 2616666.7 | S14: =Personnel!$Q13*Personnel!V13/12 -> 2616666.7 | T14: =Personnel!$Q13*Personnel!W13/12 -> 2616666.7 | U14: =Personnel!$Q13*Personnel!X13/12 -> 2616666.7 | V14: =Personnel!$Q13*Personnel!Y13/12 -> 2616666.7 | ... Z14: =Personnel!$Q13*Personnel!AC13/12 -> 2616666.7 | AA14: =SUM(O14:Z14) -> 31400000 | AB14: =Personnel!$AE13*Personnel!AF13/2 -> 23850000 | AC14: =Personnel!$AE13*Personnel!AG13/2 -> 23850000 | AD14: =SUM(AB14:AC14) -> 47700000 | AE14: =Personnel!$AI13*Personnel!AJ13/2 -> 0 | AF14: =Personnel!$AI13*Personnel!AK13/2 -> 0 | AG14: =SUM(AE14:AF14) -> 0 | AH14: =Personnel!$AM13*Personnel!AN13/2 -> 0 | AI14: =Personnel!$AM13*Personnel!AO13/2 -> 0 | AJ14: =SUM(AH14:AI14) -> 0
B15: =Personnel!$C14*Personnel!D14/12 -> 0 | C15: =Personnel!$C14*Personnel!E14/12 -> 0 | D15: =Personnel!$C14*Personnel!F14/12 -> 0 | E15: =Personnel!$C14*Personnel!G14/12 -> 0 | F15: =Personnel!$C14*Personnel!H14/12 -> 0 | G15: =Personnel!$C14*Personnel!I14/12 -> 650000 | H15: =Personnel!$C14*Personnel!J14/12 -> 650000 | I15: =Personnel!$C14*Personnel!K14/12 -> 650000 | ... M15: =Personnel!$C14*Personnel!O14/12 -> 650000 | N15: =SUM(B15:M15) -> 4550000 | O15: =Personnel!$Q14*Personnel!R14/12 -> 800000 | P15: =Personnel!$Q14*Personnel!S14/12 -> 800000 | Q15: =Personnel!$Q14*Personnel!T14/12 -> 800000 | R15: =Personnel!$Q14*Personnel!U14/12 -> 800000 | S15: =Personnel!$Q14*Personnel!V14/12 -> 800000 | T15: =Personnel!$Q14*Personnel!W14/12 -> 1600000 | U15: =Personnel!$Q14*Personnel!X14/12 -> 1600000 | V15: =Personnel!$Q14*Personnel!Y14/12 -> 1600000 | ... Z15: =Personnel!$Q14*Personnel!AC14/12 -> 1600000 | AA15: =SUM(O15:Z15) -> 15200000 | AB15: =Personnel!$AE14*Personnel!AF14/2 -> 15600000 | AC15: =Personnel!$AE14*Personnel!AG14/2 -> 23400000 | AD15: =SUM(AB15:AC15) -> 39000000 | AE15: =Personnel!$AI14*Personnel!AJ14/2 -> 0 | AF15: =Personnel!$AI14*Personnel!AK14/2 -> 0 | AG15: =SUM(AE15:AF15) -> 0 | AH15: =Personnel!$AM14*Personnel!AN14/2 -> 0 | AI15: =Personnel!$AM14*Personnel!AO14/2 -> 0 | AJ15: =SUM(AH15:AI15) -> 0
B16: =Personnel!$C15*Personnel!D15/12 -> 0 | C16: =Personnel!$C15*Personnel!E15/12 -> 0 | D16: =Personnel!$C15*Personnel!F15/12 -> 0 | E16: =Personnel!$C15*Personnel!G15/12 -> 0 | F16: =Personnel!$C15*Personnel!H15/12 -> 0 | G16: =Personnel!$C15*Personnel!I15/12 -> 800000 | H16: =Personnel!$C15*Personnel!J15/12 -> 800000 | I16: =Personnel!$C15*Personnel!K15/12 -> 800000 | ... M16: =Personnel!$C15*Personnel!O15/12 -> 800000 | N16: =SUM(B16:M16) -> 5600000 | O16: =Personnel!$Q15*Personnel!R15/12 -> 1300000 | P16: =Personnel!$Q15*Personnel!S15/12 -> 1300000 | Q16: =Personnel!$Q15*Personnel!T15/12 -> 1300000 | R16: =Personnel!$Q15*Personnel!U15/12 -> 1300000 | S16: =Personnel!$Q15*Personnel!V15/12 -> 1300000 | T16: =Personnel!$Q15*Personnel!W15/12 -> 1300000 | U16: =Personnel!$Q15*Personnel!X15/12 -> 1300000 | V16: =Personnel!$Q15*Personnel!Y15/12 -> 1300000 | ... Z16: =Personnel!$Q15*Personnel!AC15/12 -> 1300000 | AA16: =SUM(O16:Z16) -> 15600000 | AB16: =Personnel!$AE15*Personnel!AF15/2 -> 21400000 | AC16: =Personnel!$AE15*Personnel!AG15/2 -> 21400000 | AD16: =SUM(AB16:AC16) -> 42800000 | AE16: =Personnel!$AI15*Personnel!AJ15/2 -> 0 | AF16: =Personnel!$AI15*Personnel!AK15/2 -> 0 | AG16: =SUM(AE16:AF16) -> 0 | AH16: =Personnel!$AM15*Personnel!AN15/2 -> 0 | AI16: =Personnel!$AM15*Personnel!AO15/2 -> 0 | AJ16: =SUM(AH16:AI16) -> 0
B17: =Personnel!$C16*Personnel!D16/12 -> 0 | C17: =Personnel!$C16*Personnel!E16/12 -> 0 | D17: =Personnel!$C16*Personnel!F16/12 -> 0 | E17: =Personnel!$C16*Personnel!G16/12 -> 0 | F17: =Personnel!$C16*Personnel!H16/12 -> 0 | G17: =Personnel!$C16*Personnel!I16/12 -> 0 | H17: =Personnel!$C16*Personnel!J16/12 -> 0 | I17: =Personnel!$C16*Personnel!K16/12 -> 0 | ... M17: =Personnel!$C16*Personnel!O16/12 -> 0 | N17: =SUM(B17:M17) -> 0 | O17: =Personnel!$Q16*Personnel!R16/12 -> 0 | P17: =Personnel!$Q16*Personnel!S16/12 -> 0 | Q17: =Personnel!$Q16*Personnel!T16/12 -> 0 | R17: =Personnel!$Q16*Personnel!U16/12 -> 0 | S17: =Personnel!$Q16*Personnel!V16/12 -> 0 | T17: =Personnel!$Q16*Personnel!W16/12 -> 0 | U17: =Personnel!$Q16*Personnel!X16/12 -> 0 | V17: =Personnel!$Q16*Personnel!Y16/12 -> 0 | ... Z17: =Personnel!$Q16*Personnel!AC16/12 -> 0 | AA17: =SUM(O17:Z17) -> 0 | AB17: =Personnel!$AE16*Personnel!AF16/2 -> 0 | AC17: =Personnel!$AE16*Personnel!AG16/2 -> 0 | AD17: =SUM(AB17:AC17) -> 0 | AE17: =Personnel!$AI16*Personnel!AJ16/2 -> 0 | AF17: =Personnel!$AI16*Personnel!AK16/2 -> 0 | AG17: =SUM(AE17:AF17) -> 0 | AH17: =Personnel!$AM16*Personnel!AN16/2 -> 0 | AI17: =Personnel!$AM16*Personnel!AO16/2 -> 0 | AJ17: =SUM(AH17:AI17) -> 0
B18: =Personnel!$C17*Personnel!D17/12 -> 0 | C18: =Personnel!$C17*Personnel!E17/12 -> 0 | D18: =Personnel!$C17*Personnel!F17/12 -> 0 | E18: =Personnel!$C17*Personnel!G17/12 -> 0 | F18: =Personnel!$C17*Personnel!H17/12 -> 0 | G18: =Personnel!$C17*Personnel!I17/12 -> 0 | H18: =Personnel!$C17*Personnel!J17/12 -> 0 | I18: =Personnel!$C17*Personnel!K17/12 -> 0 | ... M18: =Personnel!$C17*Personnel!O17/12 -> 0 | N18: =SUM(B18:M18) -> 0 | O18: =Personnel!$Q17*Personnel!R17/12 -> 0 | P18: =Personnel!$Q17*Personnel!S17/12 -> 0 | Q18: =Personnel!$Q17*Personnel!T17/12 -> 0 | R18: =Personnel!$Q17*Personnel!U17/12 -> 0 | S18: =Personnel!$Q17*Personnel!V17/12 -> 0 | T18: =Personnel!$Q17*Personnel!W17/12 -> 0 | U18: =Personnel!$Q17*Personnel!X17/12 -> 0 | V18: =Personnel!$Q17*Personnel!Y17/12 -> 0 | ... Z18: =Personnel!$Q17*Personnel!AC17/12 -> 0 | AA18: =SUM(O18:Z18) -> 0 | AB18: =Personnel!$AE17*Personnel!AF17/2 -> 0 | AC18: =Personnel!$AE17*Personnel!AG17/2 -> 0 | AD18: =SUM(AB18:AC18) -> 0 | AE18: =Personnel!$AI17*Personnel!AJ17/2 -> 0 | AF18: =Personnel!$AI17*Personnel!AK17/2 -> 0 | AG18: =SUM(AE18:AF18) -> 0 | AH18: =Personnel!$AM17*Personnel!AN17/2 -> 0 | AI18: =Personnel!$AM17*Personnel!AO17/2 -> 0 | AJ18: =SUM(AH18:AI18) -> 0
B19: =Personnel!$C18*Personnel!D18/12 -> 0 | C19: =Personnel!$C18*Personnel!E18/12 -> 0 | D19: =Personnel!$C18*Personnel!F18/12 -> 0 | E19: =Personnel!$C18*Personnel!G18/12 -> 0 | F19: =Personnel!$C18*Personnel!H18/12 -> 0 | G19: =Personnel!$C18*Personnel!I18/12 -> 0 | H19: =Personnel!$C18*Personnel!J18/12 -> 0 | I19: =Personnel!$C18*Personnel!K18/12 -> 0 | ... M19: =Personnel!$C18*Personnel!O18/12 -> 0 | N19: =SUM(B19:M19) -> 0 | O19: =Personnel!$Q18*Personnel!R18/12 -> 0 | P19: =Personnel!$Q18*Personnel!S18/12 -> 0 | Q19: =Personnel!$Q18*Personnel!T18/12 -> 0 | R19: =Personnel!$Q18*Personnel!U18/12 -> 0 | S19: =Personnel!$Q18*Personnel!V18/12 -> 0 | T19: =Personnel!$Q18*Personnel!W18/12 -> 0 | U19: =Personnel!$Q18*Personnel!X18/12 -> 0 | V19: =Personnel!$Q18*Personnel!Y18/12 -> 0 | ... Z19: =Personnel!$Q18*Personnel!AC18/12 -> 0 | AA19: =SUM(O19:Z19) -> 0 | AB19: =Personnel!$AE18*Personnel!AF18/2 -> 0 | AC19: =Personnel!$AE18*Personnel!AG18/2 -> 0 | AD19: =SUM(AB19:AC19) -> 0 | AE19: =Personnel!$AI18*Personnel!AJ18/2 -> 0 | AF19: =Personnel!$AI18*Personnel!AK18/2 -> 0 | AG19: =SUM(AE19:AF19) -> 0 | AH19: =Personnel!$AM18*Personnel!AN18/2 -> 0 | AI19: =Personnel!$AM18*Personnel!AO18/2 -> 0 | AJ19: =SUM(AH19:AI19) -> 0
B20: =Personnel!$C19*Personnel!D19/12 -> 0 | C20: =Personnel!$C19*Personnel!E19/12 -> 0 | D20: =Personnel!$C19*Personnel!F19/12 -> 0 | E20: =Personnel!$C19*Personnel!G19/12 -> 0 | F20: =Personnel!$C19*Personnel!H19/12 -> 0 | G20: =Personnel!$C19*Personnel!I19/12 -> 0 | H20: =Personnel!$C19*Personnel!J19/12 -> 0 | I20: =Personnel!$C19*Personnel!K19/12 -> 0 | ... M20: =Personnel!$C19*Personnel!O19/12 -> 0 | N20: =SUM(B20:M20) -> 0 | O20: =Personnel!$Q19*Personnel!R19/12 -> 0 | P20: =Personnel!$Q19*Personnel!S19/12 -> 0 | Q20: =Personnel!$Q19*Personnel!T19/12 -> 0 | R20: =Personnel!$Q19*Personnel!U19/12 -> 0 | S20: =Personnel!$Q19*Personnel!V19/12 -> 0 | T20: =Personnel!$Q19*Personnel!W19/12 -> 0 | U20: =Personnel!$Q19*Personnel!X19/12 -> 0 | V20: =Personnel!$Q19*Personnel!Y19/12 -> 0 | ... Z20: =Personnel!$Q19*Personnel!AC19/12 -> 0 | AA20: =SUM(O20:Z20) -> 0 | AB20: =Personnel!$AE19*Personnel!AF19/2 -> 0 | AC20: =Personnel!$AE19*Personnel!AG19/2 -> 0 | AD20: =SUM(AB20:AC20) -> 0 | AE20: =Personnel!$AI19*Personnel!AJ19/2 -> 0 | AF20: =Personnel!$AI19*Personnel!AK19/2 -> 0 | AG20: =SUM(AE20:AF20) -> 0 | AH20: =Personnel!$AM19*Personnel!AN19/2 -> 0 | AI20: =Personnel!$AM19*Personnel!AO19/2 -> 0 | AJ20: =SUM(AH20:AI20) -> 0
B21: =Personnel!$C20*Personnel!D20/12 -> 0 | C21: =Personnel!$C20*Personnel!E20/12 -> 0 | D21: =Personnel!$C20*Personnel!F20/12 -> 0 | E21: =Personnel!$C20*Personnel!G20/12 -> 0 | F21: =Personnel!$C20*Personnel!H20/12 -> 0 | G21: =Personnel!$C20*Personnel!I20/12 -> 0 | H21: =Personnel!$C20*Personnel!J20/12 -> 0 | I21: =Personnel!$C20*Personnel!K20/12 -> 0 | ... M21: =Personnel!$C20*Personnel!O20/12 -> 0 | N21: =SUM(B21:M21) -> 0 | O21: =Personnel!$Q20*Personnel!R20/12 -> 0 | P21: =Personnel!$Q20*Personnel!S20/12 -> 0 | Q21: =Personnel!$Q20*Personnel!T20/12 -> 0 | R21: =Personnel!$Q20*Personnel!U20/12 -> 0 | S21: =Personnel!$Q20*Personnel!V20/12 -> 0 | T21: =Personnel!$Q20*Personnel!W20/12 -> 0 | U21: =Personnel!$Q20*Personnel!X20/12 -> 0 | V21: =Personnel!$Q20*Personnel!Y20/12 -> 0 | ... Z21: =Personnel!$Q20*Personnel!AC20/12 -> 0 | AA21: =SUM(O21:Z21) -> 0 | AB21: =Personnel!$AE20*Personnel!AF20/2 -> 0 | AC21: =Personnel!$AE20*Personnel!AG20/2 -> 0 | AD21: =SUM(AB21:AC21) -> 0 | AE21: =Personnel!$AI20*Personnel!AJ20/2 -> 0 | AF21: =Personnel!$AI20*Personnel!AK20/2 -> 0 | AG21: =SUM(AE21:AF21) -> 0 | AH21: =Personnel!$AM20*Personnel!AN20/2 -> 0 | AI21: =Personnel!$AM20*Personnel!AO20/2 -> 0 | AJ21: =SUM(AH21:AI21) -> 0
B22: =Personnel!$C21*Personnel!D21/12 -> 0 | C22: =Personnel!$C21*Personnel!E21/12 -> 0 | D22: =Personnel!$C21*Personnel!F21/12 -> 0 | E22: =Personnel!$C21*Personnel!G21/12 -> 0 | F22: =Personnel!$C21*Personnel!H21/12 -> 0 | G22: =Personnel!$C21*Personnel!I21/12 -> 0 | H22: =Personnel!$C21*Personnel!J21/12 -> 0 | I22: =Personnel!$C21*Personnel!K21/12 -> 0 | ... M22: =Personnel!$C21*Personnel!O21/12 -> 0 | N22: =SUM(B22:M22) -> 0 | O22: =Personnel!$Q21*Personnel!R21/12 -> 0 | P22: =Personnel!$Q21*Personnel!S21/12 -> 0 | Q22: =Personnel!$Q21*Personnel!T21/12 -> 0 | R22: =Personnel!$Q21*Personnel!U21/12 -> 0 | S22: =Personnel!$Q21*Personnel!V21/12 -> 0 | T22: =Personnel!$Q21*Personnel!W21/12 -> 0 | U22: =Personnel!$Q21*Personnel!X21/12 -> 0 | V22: =Personnel!$Q21*Personnel!Y21/12 -> 0 | ... Z22: =Personnel!$Q21*Personnel!AC21/12 -> 0 | AA22: =SUM(O22:Z22) -> 0 | AB22: =Personnel!$AE21*Personnel!AF21/2 -> 0 | AC22: =Personnel!$AE21*Personnel!AG21/2 -> 0 | AD22: =SUM(AB22:AC22) -> 0 | AE22: =Personnel!$AI21*Personnel!AJ21/2 -> 0 | AF22: =Personnel!$AI21*Personnel!AK21/2 -> 0 | AG22: =SUM(AE22:AF22) -> 0 | AH22: =Personnel!$AM21*Personnel!AN21/2 -> 0 | AI22: =Personnel!$AM21*Personnel!AO21/2 -> 0 | AJ22: =SUM(AH22:AI22) -> 0
... B30: =Personnel!$C29*Personnel!D29/12 -> 0 | C30: =Personnel!$C29*Personnel!E29/12 -> 0 | D30: =Personnel!$C29*Personnel!F29/12 -> 0 | E30: =Personnel!$C29*Personnel!G29/12 -> 0 | F30: =Personnel!$C29*Personnel!H29/12 -> 0 | G30: =Personnel!$C29*Personnel!I29/12 -> 0 | H30: =Personnel!$C29*Personnel!J29/12 -> 0 | I30: =Personnel!$C29*Personnel!K29/12 -> 0 | ... M30: =Personnel!$C29*Personnel!O29/12 -> 0 | N30: =SUM(B30:M30) -> 0 | O30: =Personnel!$Q29*Personnel!R29/12 -> 0 | P30: =Personnel!$Q29*Personnel!S29/12 -> 0 | Q30: =Personnel!$Q29*Personnel!T29/12 -> 0 | R30: =Personnel!$Q29*Personnel!U29/12 -> 0 | S30: =Personnel!$Q29*Personnel!V29/12 -> 0 | T30: =Personnel!$Q29*Personnel!W29/12 -> 0 | U30: =Personnel!$Q29*Personnel!X29/12 -> 0 | V30: =Personnel!$Q29*Personnel!Y29/12 -> 0 | ... Z30: =Personnel!$Q29*Personnel!AC29/12 -> 0 | AA30: =SUM(O30:Z30) -> 0 | AB30: =Personnel!$AE29*Personnel!AF29/2 -> 0 | AC30: =Personnel!$AE29*Personnel!AG29/2 -> 0 | AD30: =SUM(AB30:AC30) -> 0 | AE30: =Personnel!$AI29*Personnel!AJ29/2 -> 0 | AF30: =Personnel!$AI29*Personnel!AK29/2 -> 0 | AG30: =SUM(AE30:AF30) -> 0 | AH30: =Personnel!$AM29*Personnel!AN29/2 -> 0 | AI30: =Personnel!$AM29*Personnel!AO29/2 -> 0 | AJ30: =SUM(AH30:AI30) -> 0
B31: =SUM(B11:B30) -> 2600000 | C31: =SUM(C11:C30) -> 2600000 | D31: =SUM(D11:D30) -> 2600000 | E31: =SUM(E11:E30) -> 2600000 | F31: =SUM(F11:F30) -> 2600000 | G31: =SUM(G11:G30) -> 4050000 | H31: =SUM(H11:H30) -> 4050000 | I31: =SUM(I11:I30) -> 4050000 | ... AJ31: =SUM(AJ11:AJ30) -> 0
B33: Charges
B34: Année 1 | O34: Année 2 | AB34: Année 3 | AE34: Année 4 | AH34: Année 5
B35: =Config!$C$7 -> 45505 | C35: =DATE(YEAR(B35),MONTH(B35)+1,DAY(B35)) -> 45536 | D35: =DATE(YEAR(C35),MONTH(C35)+1,DAY(C35)) -> 45566 | E35: =DATE(YEAR(D35),MONTH(D35)+1,DAY(D35)) -> 45597 | F35: =DATE(YEAR(E35),MONTH(E35)+1,DAY(E35)) -> 45627 | G35: =DATE(YEAR(F35),MONTH(F35)+1,DAY(F35)) -> 45658 | H35: =DATE(YEAR(G35),MONTH(G35)+1,DAY(G35)) -> 45689 | I35: =DATE(YEAR(H35),MONTH(H35)+1,DAY(H35)) -> 45717 | J35: =DATE(YEAR(I35),MONTH(I35)+1,DAY(I35)) -> 45748 | ... M35: =DATE(YEAR(L35),MONTH(L35)+1,DAY(L35)) -> 45839 | N35: Total | O35: =DATE(YEAR(M35),MONTH(M35)+1,DAY(M35)) -> 45870 | P35: =DATE(YEAR(O35),MONTH(O35)+1,DAY(O35)) -> 45901 | Q35: =DATE(YEAR(P35),MONTH(P35)+1,DAY(P35)) -> 45931 | R35: =DATE(YEAR(Q35),MONTH(Q35)+1,DAY(Q35)) -> 45962 | S35: =DATE(YEAR(R35),MONTH(R35)+1,DAY(R35)) -> 45992 | T35: =DATE(YEAR(S35),MONTH(S35)+1,DAY(S35)) -> 46023 | U35: =DATE(YEAR(T35),MONTH(T35)+1,DAY(T35)) -> 46054 | V35: =DATE(YEAR(U35),MONTH(U35)+1,DAY(U35)) -> 46082 | W35: =DATE(YEAR(V35),MONTH(V35)+1,DAY(V35)) -> 46113 | ... Z35: =DATE(YEAR(Y35),MONTH(Y35)+1,DAY(Y35)) -> 46204 | AA35: Total | AB35: S1 | AC35: S2 | AD35: Total | AE35: S1 | AF35: S2 | AG35: Total | AH35: S1 | AI35: S2 | AJ35: Total
N36: =SUM(B36:M36) -> 0 | AA36: =SUM(O36:Z36) -> 0 | AD36: =SUM(AB36:AC36) -> 0 | AG36: =SUM(AE36:AF36) -> 0 | AJ36: =SUM(AH36:AI36) -> 0
N37: =SUM(B37:M37) -> 0 | AA37: =SUM(O37:Z37) -> 0 | AD37: =SUM(AB37:AC37) -> 0 | AG37: =SUM(AE37:AF37) -> 0 | AJ37: =SUM(AH37:AI37) -> 0
B38: =IF((B13<=Config!$C$72),0,Config!$C$70*B13) -> 247000 | C38: =IF((C13<=Config!$C$72),0,Config!$C$70*C13) -> 247000 | D38: =IF((D13<=Config!$C$72),0,Config!$C$70*D13) -> 247000 | E38: =IF((E13<=Config!$C$72),0,Config!$C$70*E13) -> 247000 | F38: =IF((F13<=Config!$C$72),0,Config!$C$70*F13) -> 247000 | G38: =IF((G13<=Config!$C$72),0,Config!$C$70*G13) -> 247000 | H38: =IF((H13<=Config!$C$72),0,Config!$C$70*H13) -> 247000 | I38: =IF((I13<=Config!$C$72),0,Config!$C$70*I13) -> 247000 | ... M38: =IF((M13<=Config!$C$72),0,Config!$C$70*M13) -> 247000 | N38: =SUM(B38:M38) -> 2964000 | O38: =IF((O13<=Config!$C$72),0,Config!$C$70*O13) -> 497166.67 | P38: =IF((P13<=Config!$C$72),0,Config!$C$70*P13) -> 497166.67 | Q38: =IF((Q13<=Config!$C$72),0,Config!$C$70*Q13) -> 497166.67 | R38: =IF((R13<=Config!$C$72),0,Config!$C$70*R13) -> 497166.67 | S38: =IF((S13<=Config!$C$72),0,Config!$C$70*S13) -> 497166.67 | T38: =IF((T13<=Config!$C$72),0,Config!$C$70*T13) -> 497166.67 | U38: =IF((U13<=Config!$C$72),0,Config!$C$70*U13) -> 497166.67 | V38: =IF((V13<=Config!$C$72),0,Config!$C$70*V13) -> 497166.67 | ... Z38: =IF((Z13<=Config!$C$72),0,Config!$C$70*Z13) -> 497166.67 | AA38: =SUM(O38:Z38) -> 5966000 | AB38: =IF((AB13<=(Config!$C$72*6)),0,Config!$C$70*AB13) -> 4531500 | AC38: =IF((AC13<=(Config!$C$72*6)),0,Config!$C$70*AC13) -> 4531500 | AD38: =SUM(AB38:AC38) -> 9063000 | AE38: =IF((AE13<=(Config!$C$72*6)),0,Config!$C$70*AE13) -> 0 | AF38: =IF((AF13<=(Config!$C$72*6)),0,Config!$C$70*AF13) -> 0 | AG38: =SUM(AE38:AF38) -> 0 | AH38: =IF((AH13<=(Config!$C$72*6)),0,Config!$C$70*AH13) -> 0 | AI38: =IF((AI13<=(Config!$C$72*6)),0,Config!$C$70*AI13) -> 0 | AJ38: =SUM(AH38:AI38) -> 0
B39: =IF((B14<=Config!$C$72),0,Config!$C$70*B14) -> 247000 | C39: =IF((C14<=Config!$C$72),0,Config!$C$70*C14) -> 247000 | D39: =IF((D14<=Config!$C$72),0,Config!$C$70*D14) -> 247000 | E39: =IF((E14<=Config!$C$72),0,Config!$C$70*E14) -> 247000 | F39: =IF((F14<=Config!$C$72),0,Config!$C$70*F14) -> 247000 | G39: =IF((G14<=Config!$C$72),0,Config!$C$70*G14) -> 247000 | H39: =IF((H14<=Config!$C$72),0,Config!$C$70*H14) -> 247000 | I39: =IF((I14<=Config!$C$72),0,Config!$C$70*I14) -> 247000 | ... M39: =IF((M14<=Config!$C$72),0,Config!$C$70*M14) -> 247000 | N39: =SUM(B39:M39) -> 2964000 | O39: =IF((O14<=Config!$C$72),0,Config!$C$70*O14) -> 497166.67 | P39: =IF((P14<=Config!$C$72),0,Config!$C$70*P14) -> 497166.67 | Q39: =IF((Q14<=Config!$C$72),0,Config!$C$70*Q14) -> 497166.67 | R39: =IF((R14<=Config!$C$72),0,Config!$C$70*R14) -> 497166.67 | S39: =IF((S14<=Config!$C$72),0,Config!$C$70*S14) -> 497166.67 | T39: =IF((T14<=Config!$C$72),0,Config!$C$70*T14) -> 497166.67 | U39: =IF((U14<=Config!$C$72),0,Config!$C$70*U14) -> 497166.67 | V39: =IF((V14<=Config!$C$72),0,Config!$C$70*V14) -> 497166.67 | ... Z39: =IF((Z14<=Config!$C$72),0,Config!$C$70*Z14) -> 497166.67 | AA39: =SUM(O39:Z39) -> 5966000 | AB39: =IF((AB14<=(Config!$C$72*6)),0,Config!$C$70*AB14) -> 4531500 | AC39: =IF((AC14<=(Config!$C$72*6)),0,Config!$C$70*AC14) -> 4531500 | AD39: =SUM(AB39:AC39) -> 9063000 | AE39: =IF((AE14<=(Config!$C$72*6)),0,Config!$C$70*AE14) -> 0 | AF39: =IF((AF14<=(Config!$C$72*6)),0,Config!$C$70*AF14) -> 0 | AG39: =SUM(AE39:AF39) -> 0 | AH39: =IF((AH14<=(Config!$C$72*6)),0,Config!$C$70*AH14) -> 0 | AI39: =IF((AI14<=(Config!$C$72*6)),0,Config!$C$70*AI14) -> 0 | AJ39: =SUM(AH39:AI39) -> 0
B40: =IF((B15<=Config!$C$72),0,Config!$C$70*B15) -> 0 | C40: =IF((C15<=Config!$C$72),0,Config!$C$70*C15) -> 0 | D40: =IF((D15<=Config!$C$72),0,Config!$C$70*D15) -> 0 | E40: =IF((E15<=Config!$C$72),0,Config!$C$70*E15) -> 0 | F40: =IF((F15<=Config!$C$72),0,Config!$C$70*F15) -> 0 | G40: =IF((G15<=Config!$C$72),0,Config!$C$70*G15) -> 123500 | H40: =IF((H15<=Config!$C$72),0,Config!$C$70*H15) -> 123500 | I40: =IF((I15<=Config!$C$72),0,Config!$C$70*I15) -> 123500 | ... M40: =IF((M15<=Config!$C$72),0,Config!$C$70*M15) -> 123500 | N40: =SUM(B40:M40) -> 864500 | O40: =IF((O15<=Config!$C$72),0,Config!$C$70*O15) -> 152000 | P40: =IF((P15<=Config!$C$72),0,Config!$C$70*P15) -> 152000 | Q40: =IF((Q15<=Config!$C$72),0,Config!$C$70*Q15) -> 152000 | R40: =IF((R15<=Config!$C$72),0,Config!$C$70*R15) -> 152000 | S40: =IF((S15<=Config!$C$72),0,Config!$C$70*S15) -> 152000 | T40: =IF((T15<=Config!$C$72),0,Config!$C$70*T15) -> 304000 | U40: =IF((U15<=Config!$C$72),0,Config!$C$70*U15) -> 304000 | V40: =IF((V15<=Config!$C$72),0,Config!$C$70*V15) -> 304000 | ... Z40: =IF((Z15<=Config!$C$72),0,Config!$C$70*Z15) -> 304000 | AA40: =SUM(O40:Z40) -> 2888000 | AB40: =IF((AB15<=(Config!$C$72*6)),0,Config!$C$70*AB15) -> 2964000 | AC40: =IF((AC15<=(Config!$C$72*6)),0,Config!$C$70*AC15) -> 4446000 | AD40: =SUM(AB40:AC40) -> 7410000 | AE40: =IF((AE15<=(Config!$C$72*6)),0,Config!$C$70*AE15) -> 0 | AF40: =IF((AF15<=(Config!$C$72*6)),0,Config!$C$70*AF15) -> 0 | AG40: =SUM(AE40:AF40) -> 0 | AH40: =IF((AH15<=(Config!$C$72*6)),0,Config!$C$70*AH15) -> 0 | AI40: =IF((AI15<=(Config!$C$72*6)),0,Config!$C$70*AI15) -> 0 | AJ40: =SUM(AH40:AI40) -> 0
B41: =IF((B16<=Config!$C$72),0,Config!$C$70*B16) -> 0 | C41: =IF((C16<=Config!$C$72),0,Config!$C$70*C16) -> 0 | D41: =IF((D16<=Config!$C$72),0,Config!$C$70*D16) -> 0 | E41: =IF((E16<=Config!$C$72),0,Config!$C$70*E16) -> 0 | F41: =IF((F16<=Config!$C$72),0,Config!$C$70*F16) -> 0 | G41: =IF((G16<=Config!$C$72),0,Config!$C$70*G16) -> 152000 | H41: =IF((H16<=Config!$C$72),0,Config!$C$70*H16) -> 152000 | I41: =IF((I16<=Config!$C$72),0,Config!$C$70*I16) -> 152000 | ... M41: =IF((M16<=Config!$C$72),0,Config!$C$70*M16) -> 152000 | N41: =SUM(B41:M41) -> 1064000 | O41: =IF((O16<=Config!$C$72),0,Config!$C$70*O16) -> 247000 | P41: =IF((P16<=Config!$C$72),0,Config!$C$70*P16) -> 247000 | Q41: =IF((Q16<=Config!$C$72),0,Config!$C$70*Q16) -> 247000 | R41: =IF((R16<=Config!$C$72),0,Config!$C$70*R16) -> 247000 | S41: =IF((S16<=Config!$C$72),0,Config!$C$70*S16) -> 247000 | T41: =IF((T16<=Config!$C$72),0,Config!$C$70*T16) -> 247000 | U41: =IF((U16<=Config!$C$72),0,Config!$C$70*U16) -> 247000 | V41: =IF((V16<=Config!$C$72),0,Config!$C$70*V16) -> 247000 | ... Z41: =IF((Z16<=Config!$C$72),0,Config!$C$70*Z16) -> 247000 | AA41: =SUM(O41:Z41) -> 2964000 | AB41: =IF((AB16<=(Config!$C$72*6)),0,Config!$C$70*AB16) -> 4066000 | AC41: =IF((AC16<=(Config!$C$72*6)),0,Config!$C$70*AC16) -> 4066000 | AD41: =SUM(AB41:AC41) -> 8132000 | AE41: =IF((AE16<=(Config!$C$72*6)),0,Config!$C$70*AE16) -> 0 | AF41: =IF((AF16<=(Config!$C$72*6)),0,Config!$C$70*AF16) -> 0 | AG41: =SUM(AE41:AF41) -> 0 | AH41: =IF((AH16<=(Config!$C$72*6)),0,Config!$C$70*AH16) -> 0 | AI41: =IF((AI16<=(Config!$C$72*6)),0,Config!$C$70*AI16) -> 0 | AJ41: =SUM(AH41:AI41) -> 0
B42: =IF((B17<=Config!$C$72),0,Config!$C$70*B17) -> 0 | C42: =IF((C17<=Config!$C$72),0,Config!$C$70*C17) -> 0 | D42: =IF((D17<=Config!$C$72),0,Config!$C$70*D17) -> 0 | E42: =IF((E17<=Config!$C$72),0,Config!$C$70*E17) -> 0 | F42: =IF((F17<=Config!$C$72),0,Config!$C$70*F17) -> 0 | G42: =IF((G17<=Config!$C$72),0,Config!$C$70*G17) -> 0 | H42: =IF((H17<=Config!$C$72),0,Config!$C$70*H17) -> 0 | I42: =IF((I17<=Config!$C$72),0,Config!$C$70*I17) -> 0 | ... M42: =IF((M17<=Config!$C$72),0,Config!$C$70*M17) -> 0 | N42: =SUM(B42:M42) -> 0 | O42: =IF((O17<=Config!$C$72),0,Config!$C$70*O17) -> 0 | P42: =IF((P17<=Config!$C$72),0,Config!$C$70*P17) -> 0 | Q42: =IF((Q17<=Config!$C$72),0,Config!$C$70*Q17) -> 0 | R42: =IF((R17<=Config!$C$72),0,Config!$C$70*R17) -> 0 | S42: =IF((S17<=Config!$C$72),0,Config!$C$70*S17) -> 0 | T42: =IF((T17<=Config!$C$72),0,Config!$C$70*T17) -> 0 | U42: =IF((U17<=Config!$C$72),0,Config!$C$70*U17) -> 0 | V42: =IF((V17<=Config!$C$72),0,Config!$C$70*V17) -> 0 | ... Z42: =IF((Z17<=Config!$C$72),0,Config!$C$70*Z17) -> 0 | AA42: =SUM(O42:Z42) -> 0 | AB42: =IF((AB17<=(Config!$C$72*6)),0,Config!$C$70*AB17) -> 0 | AC42: =IF((AC17<=(Config!$C$72*6)),0,Config!$C$70*AC17) -> 0 | AD42: =SUM(AB42:AC42) -> 0 | AE42: =IF((AE17<=(Config!$C$72*6)),0,Config!$C$70*AE17) -> 0 | AF42: =IF((AF17<=(Config!$C$72*6)),0,Config!$C$70*AF17) -> 0 | AG42: =SUM(AE42:AF42) -> 0 | AH42: =IF((AH17<=(Config!$C$72*6)),0,Config!$C$70*AH17) -> 0 | AI42: =IF((AI17<=(Config!$C$72*6)),0,Config!$C$70*AI17) -> 0 | AJ42: =SUM(AH42:AI42) -> 0
B43: =IF((B18<=Config!$C$72),0,Config!$C$70*B18) -> 0 | C43: =IF((C18<=Config!$C$72),0,Config!$C$70*C18) -> 0 | D43: =IF((D18<=Config!$C$72),0,Config!$C$70*D18) -> 0 | E43: =IF((E18<=Config!$C$72),0,Config!$C$70*E18) -> 0 | F43: =IF((F18<=Config!$C$72),0,Config!$C$70*F18) -> 0 | G43: =IF((G18<=Config!$C$72),0,Config!$C$70*G18) -> 0 | H43: =IF((H18<=Config!$C$72),0,Config!$C$70*H18) -> 0 | I43: =IF((I18<=Config!$C$72),0,Config!$C$70*I18) -> 0 | ... M43: =IF((M18<=Config!$C$72),0,Config!$C$70*M18) -> 0 | N43: =SUM(B43:M43) -> 0 | O43: =IF((O18<=Config!$C$72),0,Config!$C$70*O18) -> 0 | P43: =IF((P18<=Config!$C$72),0,Config!$C$70*P18) -> 0 | Q43: =IF((Q18<=Config!$C$72),0,Config!$C$70*Q18) -> 0 | R43: =IF((R18<=Config!$C$72),0,Config!$C$70*R18) -> 0 | S43: =IF((S18<=Config!$C$72),0,Config!$C$70*S18) -> 0 | T43: =IF((T18<=Config!$C$72),0,Config!$C$70*T18) -> 0 | U43: =IF((U18<=Config!$C$72),0,Config!$C$70*U18) -> 0 | V43: =IF((V18<=Config!$C$72),0,Config!$C$70*V18) -> 0 | ... Z43: =IF((Z18<=Config!$C$72),0,Config!$C$70*Z18) -> 0 | AA43: =SUM(O43:Z43) -> 0 | AB43: =IF((AB18<=(Config!$C$72*6)),0,Config!$C$70*AB18) -> 0 | AC43: =IF((AC18<=(Config!$C$72*6)),0,Config!$C$70*AC18) -> 0 | AD43: =SUM(AB43:AC43) -> 0 | AE43: =IF((AE18<=(Config!$C$72*6)),0,Config!$C$70*AE18) -> 0 | AF43: =IF((AF18<=(Config!$C$72*6)),0,Config!$C$70*AF18) -> 0 | AG43: =SUM(AE43:AF43) -> 0 | AH43: =IF((AH18<=(Config!$C$72*6)),0,Config!$C$70*AH18) -> 0 | AI43: =IF((AI18<=(Config!$C$72*6)),0,Config!$C$70*AI18) -> 0 | AJ43: =SUM(AH43:AI43) -> 0
B44: =IF((B19<=Config!$C$72),0,Config!$C$70*B19) -> 0 | C44: =IF((C19<=Config!$C$72),0,Config!$C$70*C19) -> 0 | D44: =IF((D19<=Config!$C$72),0,Config!$C$70*D19) -> 0 | E44: =IF((E19<=Config!$C$72),0,Config!$C$70*E19) -> 0 | F44: =IF((F19<=Config!$C$72),0,Config!$C$70*F19) -> 0 | G44: =IF((G19<=Config!$C$72),0,Config!$C$70*G19) -> 0 | H44: =IF((H19<=Config!$C$72),0,Config!$C$70*H19) -> 0 | I44: =IF((I19<=Config!$C$72),0,Config!$C$70*I19) -> 0 | ... M44: =IF((M19<=Config!$C$72),0,Config!$C$70*M19) -> 0 | N44: =SUM(B44:M44) -> 0 | O44: =IF((O19<=Config!$C$72),0,Config!$C$70*O19) -> 0 | P44: =IF((P19<=Config!$C$72),0,Config!$C$70*P19) -> 0 | Q44: =IF((Q19<=Config!$C$72),0,Config!$C$70*Q19) -> 0 | R44: =IF((R19<=Config!$C$72),0,Config!$C$70*R19) -> 0 | S44: =IF((S19<=Config!$C$72),0,Config!$C$70*S19) -> 0 | T44: =IF((T19<=Config!$C$72),0,Config!$C$70*T19) -> 0 | U44: =IF((U19<=Config!$C$72),0,Config!$C$70*U19) -> 0 | V44: =IF((V19<=Config!$C$72),0,Config!$C$70*V19) -> 0 | ... Z44: =IF((Z19<=Config!$C$72),0,Config!$C$70*Z19) -> 0 | AA44: =SUM(O44:Z44) -> 0 | AB44: =IF((AB19<=(Config!$C$72*6)),0,Config!$C$70*AB19) -> 0 | AC44: =IF((AC19<=(Config!$C$72*6)),0,Config!$C$70*AC19) -> 0 | AD44: =SUM(AB44:AC44) -> 0 | AE44: =IF((AE19<=(Config!$C$72*6)),0,Config!$C$70*AE19) -> 0 | AF44: =IF((AF19<=(Config!$C$72*6)),0,Config!$C$70*AF19) -> 0 | AG44: =SUM(AE44:AF44) -> 0 | AH44: =IF((AH19<=(Config!$C$72*6)),0,Config!$C$70*AH19) -> 0 | AI44: =IF((AI19<=(Config!$C$72*6)),0,Config!$C$70*AI19) -> 0 | AJ44: =SUM(AH44:AI44) -> 0
B45: =IF((B20<=Config!$C$72),0,Config!$C$70*B20) -> 0 | C45: =IF((C20<=Config!$C$72),0,Config!$C$70*C20) -> 0 | D45: =IF((D20<=Config!$C$72),0,Config!$C$70*D20) -> 0 | E45: =IF((E20<=Config!$C$72),0,Config!$C$70*E20) -> 0 | F45: =IF((F20<=Config!$C$72),0,Config!$C$70*F20) -> 0 | G45: =IF((G20<=Config!$C$72),0,Config!$C$70*G20) -> 0 | H45: =IF((H20<=Config!$C$72),0,Config!$C$70*H20) -> 0 | I45: =IF((I20<=Config!$C$72),0,Config!$C$70*I20) -> 0 | ... M45: =IF((M20<=Config!$C$72),0,Config!$C$70*M20) -> 0 | N45: =SUM(B45:M45) -> 0 | O45: =IF((O20<=Config!$C$72),0,Config!$C$70*O20) -> 0 | P45: =IF((P20<=Config!$C$72),0,Config!$C$70*P20) -> 0 | Q45: =IF((Q20<=Config!$C$72),0,Config!$C$70*Q20) -> 0 | R45: =IF((R20<=Config!$C$72),0,Config!$C$70*R20) -> 0 | S45: =IF((S20<=Config!$C$72),0,Config!$C$70*S20) -> 0 | T45: =IF((T20<=Config!$C$72),0,Config!$C$70*T20) -> 0 | U45: =IF((U20<=Config!$C$72),0,Config!$C$70*U20) -> 0 | V45: =IF((V20<=Config!$C$72),0,Config!$C$70*V20) -> 0 | ... Z45: =IF((Z20<=Config!$C$72),0,Config!$C$70*Z20) -> 0 | AA45: =SUM(O45:Z45) -> 0 | AB45: =IF((AB20<=(Config!$C$72*6)),0,Config!$C$70*AB20) -> 0 | AC45: =IF((AC20<=(Config!$C$72*6)),0,Config!$C$70*AC20) -> 0 | AD45: =SUM(AB45:AC45) -> 0 | AE45: =IF((AE20<=(Config!$C$72*6)),0,Config!$C$70*AE20) -> 0 | AF45: =IF((AF20<=(Config!$C$72*6)),0,Config!$C$70*AF20) -> 0 | AG45: =SUM(AE45:AF45) -> 0 | AH45: =IF((AH20<=(Config!$C$72*6)),0,Config!$C$70*AH20) -> 0 | AI45: =IF((AI20<=(Config!$C$72*6)),0,Config!$C$70*AI20) -> 0 | AJ45: =SUM(AH45:AI45) -> 0
B46: =IF((B21<=Config!$C$72),0,Config!$C$70*B21) -> 0 | C46: =IF((C21<=Config!$C$72),0,Config!$C$70*C21) -> 0 | D46: =IF((D21<=Config!$C$72),0,Config!$C$70*D21) -> 0 | E46: =IF((E21<=Config!$C$72),0,Config!$C$70*E21) -> 0 | F46: =IF((F21<=Config!$C$72),0,Config!$C$70*F21) -> 0 | G46: =IF((G21<=Config!$C$72),0,Config!$C$70*G21) -> 0 | H46: =IF((H21<=Config!$C$72),0,Config!$C$70*H21) -> 0 | I46: =IF((I21<=Config!$C$72),0,Config!$C$70*I21) -> 0 | ... M46: =IF((M21<=Config!$C$72),0,Config!$C$70*M21) -> 0 | N46: =SUM(B46:M46) -> 0 | O46: =IF((O21<=Config!$C$72),0,Config!$C$70*O21) -> 0 | P46: =IF((P21<=Config!$C$72),0,Config!$C$70*P21) -> 0 | Q46: =IF((Q21<=Config!$C$72),0,Config!$C$70*Q21) -> 0 | R46: =IF((R21<=Config!$C$72),0,Config!$C$70*R21) -> 0 | S46: =IF((S21<=Config!$C$72),0,Config!$C$70*S21) -> 0 | T46: =IF((T21<=Config!$C$72),0,Config!$C$70*T21) -> 0 | U46: =IF((U21<=Config!$C$72),0,Config!$C$70*U21) -> 0 | V46: =IF((V21<=Config!$C$72),0,Config!$C$70*V21) -> 0 | ... Z46: =IF((Z21<=Config!$C$72),0,Config!$C$70*Z21) -> 0 | AA46: =SUM(O46:Z46) -> 0 | AB46: =IF((AB21<=(Config!$C$72*6)),0,Config!$C$70*AB21) -> 0 | AC46: =IF((AC21<=(Config!$C$72*6)),0,Config!$C$70*AC21) -> 0 | AD46: =SUM(AB46:AC46) -> 0 | AE46: =IF((AE21<=(Config!$C$72*6)),0,Config!$C$70*AE21) -> 0 | AF46: =IF((AF21<=(Config!$C$72*6)),0,Config!$C$70*AF21) -> 0 | AG46: =SUM(AE46:AF46) -> 0 | AH46: =IF((AH21<=(Config!$C$72*6)),0,Config!$C$70*AH21) -> 0 | AI46: =IF((AI21<=(Config!$C$72*6)),0,Config!$C$70*AI21) -> 0 | AJ46: =SUM(AH46:AI46) -> 0
B47: =IF((B22<=Config!$C$72),0,Config!$C$70*B22) -> 0 | C47: =IF((C22<=Config!$C$72),0,Config!$C$70*C22) -> 0 | D47: =IF((D22<=Config!$C$72),0,Config!$C$70*D22) -> 0 | E47: =IF((E22<=Config!$C$72),0,Config!$C$70*E22) -> 0 | F47: =IF((F22<=Config!$C$72),0,Config!$C$70*F22) -> 0 | G47: =IF((G22<=Config!$C$72),0,Config!$C$70*G22) -> 0 | H47: =IF((H22<=Config!$C$72),0,Config!$C$70*H22) -> 0 | I47: =IF((I22<=Config!$C$72),0,Config!$C$70*I22) -> 0 | ... M47: =IF((M22<=Config!$C$72),0,Config!$C$70*M22) -> 0 | N47: =SUM(B47:M47) -> 0 | O47: =IF((O22<=Config!$C$72),0,Config!$C$70*O22) -> 0 | P47: =IF((P22<=Config!$C$72),0,Config!$C$70*P22) -> 0 | Q47: =IF((Q22<=Config!$C$72),0,Config!$C$70*Q22) -> 0 | R47: =IF((R22<=Config!$C$72),0,Config!$C$70*R22) -> 0 | S47: =IF((S22<=Config!$C$72),0,Config!$C$70*S22) -> 0 | T47: =IF((T22<=Config!$C$72),0,Config!$C$70*T22) -> 0 | U47: =IF((U22<=Config!$C$72),0,Config!$C$70*U22) -> 0 | V47: =IF((V22<=Config!$C$72),0,Config!$C$70*V22) -> 0 | ... Z47: =IF((Z22<=Config!$C$72),0,Config!$C$70*Z22) -> 0 | AA47: =SUM(O47:Z47) -> 0 | AB47: =IF((AB22<=(Config!$C$72*6)),0,Config!$C$70*AB22) -> 0 | AC47: =IF((AC22<=(Config!$C$72*6)),0,Config!$C$70*AC22) -> 0 | AD47: =SUM(AB47:AC47) -> 0 | AE47: =IF((AE22<=(Config!$C$72*6)),0,Config!$C$70*AE22) -> 0 | AF47: =IF((AF22<=(Config!$C$72*6)),0,Config!$C$70*AF22) -> 0 | AG47: =SUM(AE47:AF47) -> 0 | AH47: =IF((AH22<=(Config!$C$72*6)),0,Config!$C$70*AH22) -> 0 | AI47: =IF((AI22<=(Config!$C$72*6)),0,Config!$C$70*AI22) -> 0 | AJ47: =SUM(AH47:AI47) -> 0
B48: =IF((B23<=Config!$C$72),0,Config!$C$70*B23) -> 0 | C48: =IF((C23<=Config!$C$72),0,Config!$C$70*C23) -> 0 | D48: =IF((D23<=Config!$C$72),0,Config!$C$70*D23) -> 0 | E48: =IF((E23<=Config!$C$72),0,Config!$C$70*E23) -> 0 | F48: =IF((F23<=Config!$C$72),0,Config!$C$70*F23) -> 0 | G48: =IF((G23<=Config!$C$72),0,Config!$C$70*G23) -> 0 | H48: =IF((H23<=Config!$C$72),0,Config!$C$70*H23) -> 0 | I48: =IF((I23<=Config!$C$72),0,Config!$C$70*I23) -> 0 | ... M48: =IF((M23<=Config!$C$72),0,Config!$C$70*M23) -> 0 | N48: =SUM(B48:M48) -> 0 | O48: =IF((O23<=Config!$C$72),0,Config!$C$70*O23) -> 0 | P48: =IF((P23<=Config!$C$72),0,Config!$C$70*P23) -> 0 | Q48: =IF((Q23<=Config!$C$72),0,Config!$C$70*Q23) -> 0 | R48: =IF((R23<=Config!$C$72),0,Config!$C$70*R23) -> 0 | S48: =IF((S23<=Config!$C$72),0,Config!$C$70*S23) -> 0 | T48: =IF((T23<=Config!$C$72),0,Config!$C$70*T23) -> 0 | U48: =IF((U23<=Config!$C$72),0,Config!$C$70*U23) -> 0 | V48: =IF((V23<=Config!$C$72),0,Config!$C$70*V23) -> 0 | ... Z48: =IF((Z23<=Config!$C$72),0,Config!$C$70*Z23) -> 0 | AA48: =SUM(O48:Z48) -> 0 | AB48: =IF((AB23<=(Config!$C$72*6)),0,Config!$C$70*AB23) -> 0 | AC48: =IF((AC23<=(Config!$C$72*6)),0,Config!$C$70*AC23) -> 0 | AD48: =SUM(AB48:AC48) -> 0 | AE48: =IF((AE23<=(Config!$C$72*6)),0,Config!$C$70*AE23) -> 0 | AF48: =IF((AF23<=(Config!$C$72*6)),0,Config!$C$70*AF23) -> 0 | AG48: =SUM(AE48:AF48) -> 0 | AH48: =IF((AH23<=(Config!$C$72*6)),0,Config!$C$70*AH23) -> 0 | AI48: =IF((AI23<=(Config!$C$72*6)),0,Config!$C$70*AI23) -> 0 | AJ48: =SUM(AH48:AI48) -> 0
B49: =IF((B24<=Config!$C$72),0,Config!$C$70*B24) -> 0 | C49: =IF((C24<=Config!$C$72),0,Config!$C$70*C24) -> 0 | D49: =IF((D24<=Config!$C$72),0,Config!$C$70*D24) -> 0 | E49: =IF((E24<=Config!$C$72),0,Config!$C$70*E24) -> 0 | F49: =IF((F24<=Config!$C$72),0,Config!$C$70*F24) -> 0 | G49: =IF((G24<=Config!$C$72),0,Config!$C$70*G24) -> 0 | H49: =IF((H24<=Config!$C$72),0,Config!$C$70*H24) -> 0 | I49: =IF((I24<=Config!$C$72),0,Config!$C$70*I24) -> 0 | ... M49: =IF((M24<=Config!$C$72),0,Config!$C$70*M24) -> 0 | N49: =SUM(B49:M49) -> 0 | O49: =IF((O24<=Config!$C$72),0,Config!$C$70*O24) -> 0 | P49: =IF((P24<=Config!$C$72),0,Config!$C$70*P24) -> 0 | Q49: =IF((Q24<=Config!$C$72),0,Config!$C$70*Q24) -> 0 | R49: =IF((R24<=Config!$C$72),0,Config!$C$70*R24) -> 0 | S49: =IF((S24<=Config!$C$72),0,Config!$C$70*S24) -> 0 | T49: =IF((T24<=Config!$C$72),0,Config!$C$70*T24) -> 0 | U49: =IF((U24<=Config!$C$72),0,Config!$C$70*U24) -> 0 | V49: =IF((V24<=Config!$C$72),0,Config!$C$70*V24) -> 0 | ... Z49: =IF((Z24<=Config!$C$72),0,Config!$C$70*Z24) -> 0 | AA49: =SUM(O49:Z49) -> 0 | AB49: =IF((AB24<=(Config!$C$72*6)),0,Config!$C$70*AB24) -> 0 | AC49: =IF((AC24<=(Config!$C$72*6)),0,Config!$C$70*AC24) -> 0 | AD49: =SUM(AB49:AC49) -> 0 | AE49: =IF((AE24<=(Config!$C$72*6)),0,Config!$C$70*AE24) -> 0 | AF49: =IF((AF24<=(Config!$C$72*6)),0,Config!$C$70*AF24) -> 0 | AG49: =SUM(AE49:AF49) -> 0 | AH49: =IF((AH24<=(Config!$C$72*6)),0,Config!$C$70*AH24) -> 0 | AI49: =IF((AI24<=(Config!$C$72*6)),0,Config!$C$70*AI24) -> 0 | AJ49: =SUM(AH49:AI49) -> 0
... B55: =IF((B30<=Config!$C$72),0,Config!$C$70*B30) -> 0 | C55: =IF((C30<=Config!$C$72),0,Config!$C$70*C30) -> 0 | D55: =IF((D30<=Config!$C$72),0,Config!$C$70*D30) -> 0 | E55: =IF((E30<=Config!$C$72),0,Config!$C$70*E30) -> 0 | F55: =IF((F30<=Config!$C$72),0,Config!$C$70*F30) -> 0 | G55: =IF((G30<=Config!$C$72),0,Config!$C$70*G30) -> 0 | H55: =IF((H30<=Config!$C$72),0,Config!$C$70*H30) -> 0 | I55: =IF((I30<=Config!$C$72),0,Config!$C$70*I30) -> 0 | ... M55: =IF((M30<=Config!$C$72),0,Config!$C$70*M30) -> 0 | N55: =SUM(B55:M55) -> 0 | O55: =IF((O30<=Config!$C$72),0,Config!$C$70*O30) -> 0 | P55: =IF((P30<=Config!$C$72),0,Config!$C$70*P30) -> 0 | Q55: =IF((Q30<=Config!$C$72),0,Config!$C$70*Q30) -> 0 | R55: =IF((R30<=Config!$C$72),0,Config!$C$70*R30) -> 0 | S55: =IF((S30<=Config!$C$72),0,Config!$C$70*S30) -> 0 | T55: =IF((T30<=Config!$C$72),0,Config!$C$70*T30) -> 0 | U55: =IF((U30<=Config!$C$72),0,Config!$C$70*U30) -> 0 | V55: =IF((V30<=Config!$C$72),0,Config!$C$70*V30) -> 0 | ... Z55: =IF((Z30<=Config!$C$72),0,Config!$C$70*Z30) -> 0 | AA55: =SUM(O55:Z55) -> 0 | AB55: =IF((AB30<=(Config!$C$72*6)),0,Config!$C$70*AB30) -> 0 | AC55: =IF((AC30<=(Config!$C$72*6)),0,Config!$C$70*AC30) -> 0 | AD55: =SUM(AB55:AC55) -> 0 | AE55: =IF((AE30<=(Config!$C$72*6)),0,Config!$C$70*AE30) -> 0 | AF55: =IF((AF30<=(Config!$C$72*6)),0,Config!$C$70*AF30) -> 0 | AG55: =SUM(AE55:AF55) -> 0 | AH55: =IF((AH30<=(Config!$C$72*6)),0,Config!$C$70*AH30) -> 0 | AI55: =IF((AI30<=(Config!$C$72*6)),0,Config!$C$70*AI30) -> 0 | AJ55: =SUM(AH55:AI55) -> 0
B56: =SUM(B36:B55) -> 494000 | C56: =SUM(C36:C55) -> 494000 | D56: =SUM(D36:D55) -> 494000 | E56: =SUM(E36:E55) -> 494000 | F56: =SUM(F36:F55) -> 494000 | G56: =SUM(G36:G55) -> 769500 | H56: =SUM(H36:H55) -> 769500 | I56: =SUM(I36:I55) -> 769500 | ... AJ56: =SUM(AJ36:AJ55) -> 0
B58: Charges de personnel totale
B59: Année 1 | O59: Année 2 | AB59: Année 3 | AE59: Année 4 | AH59: Année 5
B60: =Config!$C$7 -> 45505 | C60: =DATE(YEAR(B60),MONTH(B60)+1,DAY(B60)) -> 45536 | D60: =DATE(YEAR(C60),MONTH(C60)+1,DAY(C60)) -> 45566 | E60: =DATE(YEAR(D60),MONTH(D60)+1,DAY(D60)) -> 45597 | F60: =DATE(YEAR(E60),MONTH(E60)+1,DAY(E60)) -> 45627 | G60: =DATE(YEAR(F60),MONTH(F60)+1,DAY(F60)) -> 45658 | H60: =DATE(YEAR(G60),MONTH(G60)+1,DAY(G60)) -> 45689 | I60: =DATE(YEAR(H60),MONTH(H60)+1,DAY(H60)) -> 45717 | J60: =DATE(YEAR(I60),MONTH(I60)+1,DAY(I60)) -> 45748 | ... M60: =DATE(YEAR(L60),MONTH(L60)+1,DAY(L60)) -> 45839 | N60: Total | O60: =DATE(YEAR(M60),MONTH(M60)+1,DAY(M60)) -> 45870 | P60: =DATE(YEAR(O60),MONTH(O60)+1,DAY(O60)) -> 45901 | Q60: =DATE(YEAR(P60),MONTH(P60)+1,DAY(P60)) -> 45931 | R60: =DATE(YEAR(Q60),MONTH(Q60)+1,DAY(Q60)) -> 45962 | S60: =DATE(YEAR(R60),MONTH(R60)+1,DAY(R60)) -> 45992 | T60: =DATE(YEAR(S60),MONTH(S60)+1,DAY(S60)) -> 46023 | U60: =DATE(YEAR(T60),MONTH(T60)+1,DAY(T60)) -> 46054 | V60: =DATE(YEAR(U60),MONTH(U60)+1,DAY(U60)) -> 46082 | W60: =DATE(YEAR(V60),MONTH(V60)+1,DAY(V60)) -> 46113 | ... Z60: =DATE(YEAR(Y60),MONTH(Y60)+1,DAY(Y60)) -> 46204 | AA60: Total | AB60: S1 | AC60: S2 | AD60: Total | AE60: S1 | AF60: S2 | AG60: Total | AH60: S1 | AI60: S2 | AJ60: Total
B61: =B11+B36 -> 0 | C61: =C11+C36 -> 0 | D61: =D11+D36 -> 0 | E61: =E11+E36 -> 0 | F61: =F11+F36 -> 0 | G61: =G11+G36 -> 0 | H61: =H11+H36 -> 0 | I61: =I11+I36 -> 0 | ... M61: =M11+M36 -> 0 | N61: =SUM(B61:M61) -> 0 | O61: =O11+O36 -> 0 | P61: =P11+P36 -> 0 | Q61: =Q11+Q36 -> 0 | R61: =R11+R36 -> 0 | S61: =S11+S36 -> 0 | T61: =T11+T36 -> 0 | U61: =U11+U36 -> 0 | V61: =V11+V36 -> 0 | ... Z61: =Z11+Z36 -> 0 | AA61: =SUM(O61:Z61) -> 0 | AB61: =AB11+AB36 -> 0 | AC61: =AC11+AC36 -> 0 | AD61: =SUM(AB61:AC61) -> 0 | AE61: =AE11+AE36 -> 0 | AF61: =AF11+AF36 -> 0 | AG61: =SUM(AE61:AF61) -> 0 | AH61: =AH11+AH36 -> 0 | AI61: =AI11+AI36 -> 0 | AJ61: =SUM(AH61:AI61) -> 0
B62: =B12+B37 -> 0 | C62: =C12+C37 -> 0 | D62: =D12+D37 -> 0 | E62: =E12+E37 -> 0 | F62: =F12+F37 -> 0 | G62: =G12+G37 -> 0 | H62: =H12+H37 -> 0 | I62: =I12+I37 -> 0 | ... M62: =M12+M37 -> 0 | N62: =SUM(B62:M62) -> 0 | O62: =O12+O37 -> 0 | P62: =P12+P37 -> 0 | Q62: =Q12+Q37 -> 0 | R62: =R12+R37 -> 0 | S62: =S12+S37 -> 0 | T62: =T12+T37 -> 0 | U62: =U12+U37 -> 0 | V62: =V12+V37 -> 0 | ... Z62: =Z12+Z37 -> 0 | AA62: =SUM(O62:Z62) -> 0 | AB62: =AB12+AB37 -> 0 | AC62: =AC12+AC37 -> 0 | AD62: =SUM(AB62:AC62) -> 0 | AE62: =AE12+AE37 -> 0 | AF62: =AF12+AF37 -> 0 | AG62: =SUM(AE62:AF62) -> 0 | AH62: =AH12+AH37 -> 0 | AI62: =AI12+AI37 -> 0 | AJ62: =SUM(AH62:AI62) -> 0
B63: =B13+B38 -> 1547000 | C63: =C13+C38 -> 1547000 | D63: =D13+D38 -> 1547000 | E63: =E13+E38 -> 1547000 | F63: =F13+F38 -> 1547000 | G63: =G13+G38 -> 1547000 | H63: =H13+H38 -> 1547000 | I63: =I13+I38 -> 1547000 | ... M63: =M13+M38 -> 1547000 | N63: =SUM(B63:M63) -> 18564000 | O63: =O13+O38 -> 3113833.3 | P63: =P13+P38 -> 3113833.3 | Q63: =Q13+Q38 -> 3113833.3 | R63: =R13+R38 -> 3113833.3 | S63: =S13+S38 -> 3113833.3 | T63: =T13+T38 -> 3113833.3 | U63: =U13+U38 -> 3113833.3 | V63: =V13+V38 -> 3113833.3 | ... Z63: =Z13+Z38 -> 3113833.3 | AA63: =SUM(O63:Z63) -> 37366000 | AB63: =AB13+AB38 -> 28381500 | AC63: =AC13+AC38 -> 28381500 | AD63: =SUM(AB63:AC63) -> 56763000 | AE63: =AE13+AE38 -> 0 | AF63: =AF13+AF38 -> 0 | AG63: =SUM(AE63:AF63) -> 0 | AH63: =AH13+AH38 -> 0 | AI63: =AI13+AI38 -> 0 | AJ63: =SUM(AH63:AI63) -> 0
B64: =B14+B39 -> 1547000 | C64: =C14+C39 -> 1547000 | D64: =D14+D39 -> 1547000 | E64: =E14+E39 -> 1547000 | F64: =F14+F39 -> 1547000 | G64: =G14+G39 -> 1547000 | H64: =H14+H39 -> 1547000 | I64: =I14+I39 -> 1547000 | ... M64: =M14+M39 -> 1547000 | N64: =SUM(B64:M64) -> 18564000 | O64: =O14+O39 -> 3113833.3 | P64: =P14+P39 -> 3113833.3 | Q64: =Q14+Q39 -> 3113833.3 | R64: =R14+R39 -> 3113833.3 | S64: =S14+S39 -> 3113833.3 | T64: =T14+T39 -> 3113833.3 | U64: =U14+U39 -> 3113833.3 | V64: =V14+V39 -> 3113833.3 | ... Z64: =Z14+Z39 -> 3113833.3 | AA64: =SUM(O64:Z64) -> 37366000 | AB64: =AB14+AB39 -> 28381500 | AC64: =AC14+AC39 -> 28381500 | AD64: =SUM(AB64:AC64) -> 56763000 | AE64: =AE14+AE39 -> 0 | AF64: =AF14+AF39 -> 0 | AG64: =SUM(AE64:AF64) -> 0 | AH64: =AH14+AH39 -> 0 | AI64: =AI14+AI39 -> 0 | AJ64: =SUM(AH64:AI64) -> 0
B65: =B15+B40 -> 0 | C65: =C15+C40 -> 0 | D65: =D15+D40 -> 0 | E65: =E15+E40 -> 0 | F65: =F15+F40 -> 0 | G65: =G15+G40 -> 773500 | H65: =H15+H40 -> 773500 | I65: =I15+I40 -> 773500 | ... M65: =M15+M40 -> 773500 | N65: =SUM(B65:M65) -> 5414500 | O65: =O15+O40 -> 952000 | P65: =P15+P40 -> 952000 | Q65: =Q15+Q40 -> 952000 | R65: =R15+R40 -> 952000 | S65: =S15+S40 -> 952000 | T65: =T15+T40 -> 1904000 | U65: =U15+U40 -> 1904000 | V65: =V15+V40 -> 1904000 | ... Z65: =Z15+Z40 -> 1904000 | AA65: =SUM(O65:Z65) -> 18088000 | AB65: =AB15+AB40 -> 18564000 | AC65: =AC15+AC40 -> 27846000 | AD65: =SUM(AB65:AC65) -> 46410000 | AE65: =AE15+AE40 -> 0 | AF65: =AF15+AF40 -> 0 | AG65: =SUM(AE65:AF65) -> 0 | AH65: =AH15+AH40 -> 0 | AI65: =AI15+AI40 -> 0 | AJ65: =SUM(AH65:AI65) -> 0
B66: =B16+B41 -> 0 | C66: =C16+C41 -> 0 | D66: =D16+D41 -> 0 | E66: =E16+E41 -> 0 | F66: =F16+F41 -> 0 | G66: =G16+G41 -> 952000 | H66: =H16+H41 -> 952000 | I66: =I16+I41 -> 952000 | ... M66: =M16+M41 -> 952000 | N66: =SUM(B66:M66) -> 6664000 | O66: =O16+O41 -> 1547000 | P66: =P16+P41 -> 1547000 | Q66: =Q16+Q41 -> 1547000 | R66: =R16+R41 -> 1547000 | S66: =S16+S41 -> 1547000 | T66: =T16+T41 -> 1547000 | U66: =U16+U41 -> 1547000 | V66: =V16+V41 -> 1547000 | ... Z66: =Z16+Z41 -> 1547000 | AA66: =SUM(O66:Z66) -> 18564000 | AB66: =AB16+AB41 -> 25466000 | AC66: =AC16+AC41 -> 25466000 | AD66: =SUM(AB66:AC66) -> 50932000 | AE66: =AE16+AE41 -> 0 | AF66: =AF16+AF41 -> 0 | AG66: =SUM(AE66:AF66) -> 0 | AH66: =AH16+AH41 -> 0 | AI66: =AI16+AI41 -> 0 | AJ66: =SUM(AH66:AI66) -> 0
B67: =B17+B42 -> 0 | C67: =C17+C42 -> 0 | D67: =D17+D42 -> 0 | E67: =E17+E42 -> 0 | F67: =F17+F42 -> 0 | G67: =G17+G42 -> 0 | H67: =H17+H42 -> 0 | I67: =I17+I42 -> 0 | ... M67: =M17+M42 -> 0 | N67: =SUM(B67:M67) -> 0 | O67: =O17+O42 -> 0 | P67: =P17+P42 -> 0 | Q67: =Q17+Q42 -> 0 | R67: =R17+R42 -> 0 | S67: =S17+S42 -> 0 | T67: =T17+T42 -> 0 | U67: =U17+U42 -> 0 | V67: =V17+V42 -> 0 | ... Z67: =Z17+Z42 -> 0 | AA67: =SUM(O67:Z67) -> 0 | AB67: =AB17+AB42 -> 0 | AC67: =AC17+AC42 -> 0 | AD67: =SUM(AB67:AC67) -> 0 | AE67: =AE17+AE42 -> 0 | AF67: =AF17+AF42 -> 0 | AG67: =SUM(AE67:AF67) -> 0 | AH67: =AH17+AH42 -> 0 | AI67: =AI17+AI42 -> 0 | AJ67: =SUM(AH67:AI67) -> 0
B68: =B18+B43 -> 0 | C68: =C18+C43 -> 0 | D68: =D18+D43 -> 0 | E68: =E18+E43 -> 0 | F68: =F18+F43 -> 0 | G68: =G18+G43 -> 0 | H68: =H18+H43 -> 0 | I68: =I18+I43 -> 0 | ... M68: =M18+M43 -> 0 | N68: =SUM(B68:M68) -> 0 | O68: =O18+O43 -> 0 | P68: =P18+P43 -> 0 | Q68: =Q18+Q43 -> 0 | R68: =R18+R43 -> 0 | S68: =S18+S43 -> 0 | T68: =T18+T43 -> 0 | U68: =U18+U43 -> 0 | V68: =V18+V43 -> 0 | ... Z68: =Z18+Z43 -> 0 | AA68: =SUM(O68:Z68) -> 0 | AB68: =AB18+AB43 -> 0 | AC68: =AC18+AC43 -> 0 | AD68: =SUM(AB68:AC68) -> 0 | AE68: =AE18+AE43 -> 0 | AF68: =AF18+AF43 -> 0 | AG68: =SUM(AE68:AF68) -> 0 | AH68: =AH18+AH43 -> 0 | AI68: =AI18+AI43 -> 0 | AJ68: =SUM(AH68:AI68) -> 0
B69: =B19+B44 -> 0 | C69: =C19+C44 -> 0 | D69: =D19+D44 -> 0 | E69: =E19+E44 -> 0 | F69: =F19+F44 -> 0 | G69: =G19+G44 -> 0 | H69: =H19+H44 -> 0 | I69: =I19+I44 -> 0 | ... M69: =M19+M44 -> 0 | N69: =SUM(B69:M69) -> 0 | O69: =O19+O44 -> 0 | P69: =P19+P44 -> 0 | Q69: =Q19+Q44 -> 0 | R69: =R19+R44 -> 0 | S69: =S19+S44 -> 0 | T69: =T19+T44 -> 0 | U69: =U19+U44 -> 0 | V69: =V19+V44 -> 0 | ... Z69: =Z19+Z44 -> 0 | AA69: =SUM(O69:Z69) -> 0 | AB69: =AB19+AB44 -> 0 | AC69: =AC19+AC44 -> 0 | AD69: =SUM(AB69:AC69) -> 0 | AE69: =AE19+AE44 -> 0 | AF69: =AF19+AF44 -> 0 | AG69: =SUM(AE69:AF69) -> 0 | AH69: =AH19+AH44 -> 0 | AI69: =AI19+AI44 -> 0 | AJ69: =SUM(AH69:AI69) -> 0
B70: =B20+B45 -> 0 | C70: =C20+C45 -> 0 | D70: =D20+D45 -> 0 | E70: =E20+E45 -> 0 | F70: =F20+F45 -> 0 | G70: =G20+G45 -> 0 | H70: =H20+H45 -> 0 | I70: =I20+I45 -> 0 | ... M70: =M20+M45 -> 0 | N70: =SUM(B70:M70) -> 0 | O70: =O20+O45 -> 0 | P70: =P20+P45 -> 0 | Q70: =Q20+Q45 -> 0 | R70: =R20+R45 -> 0 | S70: =S20+S45 -> 0 | T70: =T20+T45 -> 0 | U70: =U20+U45 -> 0 | V70: =V20+V45 -> 0 | ... Z70: =Z20+Z45 -> 0 | AA70: =SUM(O70:Z70) -> 0 | AB70: =AB20+AB45 -> 0 | AC70: =AC20+AC45 -> 0 | AD70: =SUM(AB70:AC70) -> 0 | AE70: =AE20+AE45 -> 0 | AF70: =AF20+AF45 -> 0 | AG70: =SUM(AE70:AF70) -> 0 | AH70: =AH20+AH45 -> 0 | AI70: =AI20+AI45 -> 0 | AJ70: =SUM(AH70:AI70) -> 0
B71: =B21+B46 -> 0 | C71: =C21+C46 -> 0 | D71: =D21+D46 -> 0 | E71: =E21+E46 -> 0 | F71: =F21+F46 -> 0 | G71: =G21+G46 -> 0 | H71: =H21+H46 -> 0 | I71: =I21+I46 -> 0 | ... M71: =M21+M46 -> 0 | N71: =SUM(B71:M71) -> 0 | O71: =O21+O46 -> 0 | P71: =P21+P46 -> 0 | Q71: =Q21+Q46 -> 0 | R71: =R21+R46 -> 0 | S71: =S21+S46 -> 0 | T71: =T21+T46 -> 0 | U71: =U21+U46 -> 0 | V71: =V21+V46 -> 0 | ... Z71: =Z21+Z46 -> 0 | AA71: =SUM(O71:Z71) -> 0 | AB71: =AB21+AB46 -> 0 | AC71: =AC21+AC46 -> 0 | AD71: =SUM(AB71:AC71) -> 0 | AE71: =AE21+AE46 -> 0 | AF71: =AF21+AF46 -> 0 | AG71: =SUM(AE71:AF71) -> 0 | AH71: =AH21+AH46 -> 0 | AI71: =AI21+AI46 -> 0 | AJ71: =SUM(AH71:AI71) -> 0
B72: =B22+B47 -> 0 | C72: =C22+C47 -> 0 | D72: =D22+D47 -> 0 | E72: =E22+E47 -> 0 | F72: =F22+F47 -> 0 | G72: =G22+G47 -> 0 | H72: =H22+H47 -> 0 | I72: =I22+I47 -> 0 | ... M72: =M22+M47 -> 0 | N72: =SUM(B72:M72) -> 0 | O72: =O22+O47 -> 0 | P72: =P22+P47 -> 0 | Q72: =Q22+Q47 -> 0 | R72: =R22+R47 -> 0 | S72: =S22+S47 -> 0 | T72: =T22+T47 -> 0 | U72: =U22+U47 -> 0 | V72: =V22+V47 -> 0 | ... Z72: =Z22+Z47 -> 0 | AA72: =SUM(O72:Z72) -> 0 | AB72: =AB22+AB47 -> 0 | AC72: =AC22+AC47 -> 0 | AD72: =SUM(AB72:AC72) -> 0 | AE72: =AE22+AE47 -> 0 | AF72: =AF22+AF47 -> 0 | AG72: =SUM(AE72:AF72) -> 0 | AH72: =AH22+AH47 -> 0 | AI72: =AI22+AI47 -> 0 | AJ72: =SUM(AH72:AI72) -> 0
... B80: =B30+B55 -> 0 | C80: =C30+C55 -> 0 | D80: =D30+D55 -> 0 | E80: =E30+E55 -> 0 | F80: =F30+F55 -> 0 | G80: =G30+G55 -> 0 | H80: =H30+H55 -> 0 | I80: =I30+I55 -> 0 | ... M80: =M30+M55 -> 0 | N80: =SUM(B80:M80) -> 0 | O80: =O30+O55 -> 0 | P80: =P30+P55 -> 0 | Q80: =Q30+Q55 -> 0 | R80: =R30+R55 -> 0 | S80: =S30+S55 -> 0 | T80: =T30+T55 -> 0 | U80: =U30+U55 -> 0 | V80: =V30+V55 -> 0 | ... Z80: =Z30+Z55 -> 0 | AA80: =SUM(O80:Z80) -> 0 | AB80: =AB30+AB55 -> 0 | AC80: =AC30+AC55 -> 0 | AD80: =SUM(AB80:AC80) -> 0 | AE80: =AE30+AE55 -> 0 | AF80: =AF30+AF55 -> 0 | AG80: =SUM(AE80:AF80) -> 0 | AH80: =AH30+AH55 -> 0 | AI80: =AI30+AI55 -> 0 | AJ80: =SUM(AH80:AI80) -> 0
B81: =SUM(B61:B80) -> 3094000 | C81: =SUM(C61:C80) -> 3094000 | D81: =SUM(D61:D80) -> 3094000 | E81: =SUM(E61:E80) -> 3094000 | F81: =SUM(F61:F80) -> 3094000 | G81: =SUM(G61:G80) -> 4819500 | H81: =SUM(H61:H80) -> 4819500 | I81: =SUM(I61:I80) -> 4819500 | ... AJ81: =SUM(AJ61:AJ80) -> 0

Sheet Charges externes
B2: CHARGES EXTERNES (en € HT)
B5: Note sur les charges externes : Les charges externes grisées, dont les décaissements sont lissés mensuellement, sont calculées automatiquement à partir des informations indiquées dans la section "Charges externes" de l'onglet "CONFIG" (information de "Configuration avancée") et du chiffre d'affaires calculé et des informations de personnel renseignées. D'autres charges externes personnalisables pourront être renseignées si besoin dans les cases marrons. Renseignez dans ce cas le nom du poste de charges dans le tableau de gauche et les décaissements mensuels associés dans le tableau de droite.
C7: Charges annuelles consolidées | I7: Année 1 | U7: Année 2 | AG7: Année 3 | AS7: Année 4 | BE7: Année 5
B8: Poste | C8: Année 1 | D8: Année 2 | E8: Année 3 | F8: Année 4 | G8: Année 5 | I8: =Config!$C$7 -> 45505 | J8: =DATE(YEAR(I8),MONTH(I8)+1,DAY(I8)) -> 45536 | K8: =DATE(YEAR(J8),MONTH(J8)+1,DAY(J8)) -> 45566 | L8: =DATE(YEAR(K8),MONTH(K8)+1,DAY(K8)) -> 45597 | M8: =DATE(YEAR(L8),MONTH(L8)+1,DAY(L8)) -> 45627 | N8: =DATE(YEAR(M8),MONTH(M8)+1,DAY(M8)) -> 45658 | O8: =DATE(YEAR(N8),MONTH(N8)+1,DAY(N8)) -> 45689 | P8: =DATE(YEAR(O8),MONTH(O8)+1,DAY(O8)) -> 45717 | Q8: =DATE(YEAR(P8),MONTH(P8)+1,DAY(P8)) -> 45748 | ... BP8: =DATE(YEAR(BO8),MONTH(BO8)+1,DAY(BO8)) -> 47300
B9: Frais de déplacement | C9: =Config!$C$55+Config!$D$55*'Commandes - Calculs auto'!N23 -> 3132057.6 | D9: =Config!$C$55+Config!$D$55*'Commandes - Calculs auto'!Z23 -> 12168031 | E9: =Config!$C$55+Config!$D$55*'Commandes - Calculs auto'!AL23 -> 34191077 | F9: =Config!$C$55+Config!$D$55*'Commandes - Calculs auto'!AX23 -> 56910000 | G9: =Config!$C$55+Config!$D$55*'Commandes - Calculs auto'!BJ23 -> 104610000 | I9: =$C9/12 -> 261004.8 | J9: =$C9/12 -> 261004.8 | K9: =$C9/12 -> 261004.8 | L9: =$C9/12 -> 261004.8 | M9: =$C9/12 -> 261004.8 | N9: =$C9/12 -> 261004.8 | O9: =$C9/12 -> 261004.8 | P9: =$C9/12 -> 261004.8 | ... T9: =$C9/12 -> 261004.8 | U9: =$D9/12 -> 1014002.6 | V9: =$D9/12 -> 1014002.6 | W9: =$D9/12 -> 1014002.6 | X9: =$D9/12 -> 1014002.6 | Y9: =$D9/12 -> 1014002.6 | Z9: =$D9/12 -> 1014002.6 | AA9: =$D9/12 -> 1014002.6 | AB9: =$D9/12 -> 1014002.6 | ... AF9: =$D9/12 -> 1014002.6 | AG9: =$E9/12 -> 2849256.4 | AH9: =$E9/12 -> 2849256.4 | AI9: =$E9/12 -> 2849256.4 | AJ9: =$E9/12 -> 2849256.4 | AK9: =$E9/12 -> 2849256.4 | AL9: =$E9/12 -> 2849256.4 | AM9: =$E9/12 -> 2849256.4 | AN9: =$E9/12 -> 2849256.4 | ... AR9: =$E9/12 -> 2849256.4 | AS9: =$F9/12 -> 4742500 | AT9: =$F9/12 -> 4742500 | AU9: =$F9/12 -> 4742500 | AV9: =$F9/12 -> 4742500 | AW9: =$F9/12 -> 4742500 | AX9: =$F9/12 -> 4742500 | AY9: =$F9/12 -> 4742500 | AZ9: =$F9/12 -> 4742500 | ... BD9: =$F9/12 -> 4742500 | BE9: =$G9/12 -> 8717500 | BF9: =$G9/12 -> 8717500 | BG9: =$G9/12 -> 8717500 | BH9: =$G9/12 -> 8717500 | BI9: =$G9/12 -> 8717500 | BJ9: =$G9/12 -> 8717500 | BK9: =$G9/12 -> 8717500 | BL9: =$G9/12 -> 8717500 | ... BP9: =$G9/12 -> 8717500
B10: Honoraires | C10: =Config!$C$56+Config!$D$56*'Personnel - Calculs auto'!C$6 -> 4800000 | D10: =Config!$C$56+Config!$D$56*'Personnel - Calculs auto'!D$6 -> 4800000 | E10: =Config!$C$56+Config!$D$56*'Personnel - Calculs auto'!E$6 -> 4800000 | F10: =Config!$C$56+Config!$D$56*'Personnel - Calculs auto'!F$6 -> 4800000 | G10: =Config!$C$56+Config!$D$56*'Personnel - Calculs auto'!G$6 -> 4800000 | I10: =$C10/12 -> 400000 | J10: =$C10/12 -> 400000 | K10: =$C10/12 -> 400000 | L10: =$C10/12 -> 400000 | M10: =$C10/12 -> 400000 | N10: =$C10/12 -> 400000 | O10: =$C10/12 -> 400000 | P10: =$C10/12 -> 400000 | ... T10: =$C10/12 -> 400000 | U10: =$D10/12 -> 400000 | V10: =$D10/12 -> 400000 | W10: =$D10/12 -> 400000 | X10: =$D10/12 -> 400000 | Y10: =$D10/12 -> 400000 | Z10: =$D10/12 -> 400000 | AA10: =$D10/12 -> 400000 | AB10: =$D10/12 -> 400000 | ... AF10: =$D10/12 -> 400000 | AG10: =$E10/12 -> 400000 | AH10: =$E10/12 -> 400000 | AI10: =$E10/12 -> 400000 | AJ10: =$E10/12 -> 400000 | AK10: =$E10/12 -> 400000 | AL10: =$E10/12 -> 400000 | AM10: =$E10/12 -> 400000 | AN10: =$E10/12 -> 400000 | ... AR10: =$E10/12 -> 400000 | AS10: =$F10/12 -> 400000 | AT10: =$F10/12 -> 400000 | AU10: =$F10/12 -> 400000 | AV10: =$F10/12 -> 400000 | AW10: =$F10/12 -> 400000 | AX10: =$F10/12 -> 400000 | AY10: =$F10/12 -> 400000 | AZ10: =$F10/12 -> 400000 | ... BD10: =$F10/12 -> 400000 | BE10: =$G10/12 -> 400000 | BF10: =$G10/12 -> 400000 | BG10: =$G10/12 -> 400000 | BH10: =$G10/12 -> 400000 | BI10: =$G10/12 -> 400000 | BJ10: =$G10/12 -> 400000 | BK10: =$G10/12 -> 400000 | BL10: =$G10/12 -> 400000 | ... BP10: =$G10/12 -> 400000
B11: Marketing | C11: =Config!$C$57+Config!$D$57*'Commandes - Calculs auto'!N23 -> 8964115.1 | D11: =Config!$C$57+Config!$D$57*'Commandes - Calculs auto'!Z23 -> 27036062 | E11: =Config!$C$57+Config!$D$57*'Commandes - Calculs auto'!AL23 -> 71082154 | F11: =Config!$C$57+Config!$D$57*'Commandes - Calculs auto'!AX23 -> 116520000 | G11: =Config!$C$57+Config!$D$57*'Commandes - Calculs auto'!BJ23 -> 211920000 | I11: =$C11/12 -> 747009.59 | J11: =$C11/12 -> 747009.59 | K11: =$C11/12 -> 747009.59 | L11: =$C11/12 -> 747009.59 | M11: =$C11/12 -> 747009.59 | N11: =$C11/12 -> 747009.59 | O11: =$C11/12 -> 747009.59 | P11: =$C11/12 -> 747009.59 | ... T11: =$C11/12 -> 747009.59 | U11: =$D11/12 -> 2253005.2 | V11: =$D11/12 -> 2253005.2 | W11: =$D11/12 -> 2253005.2 | X11: =$D11/12 -> 2253005.2 | Y11: =$D11/12 -> 2253005.2 | Z11: =$D11/12 -> 2253005.2 | AA11: =$D11/12 -> 2253005.2 | AB11: =$D11/12 -> 2253005.2 | ... AF11: =$D11/12 -> 2253005.2 | AG11: =$E11/12 -> 5923512.8 | AH11: =$E11/12 -> 5923512.8 | AI11: =$E11/12 -> 5923512.8 | AJ11: =$E11/12 -> 5923512.8 | AK11: =$E11/12 -> 5923512.8 | AL11: =$E11/12 -> 5923512.8 | AM11: =$E11/12 -> 5923512.8 | AN11: =$E11/12 -> 5923512.8 | ... AR11: =$E11/12 -> 5923512.8 | AS11: =$F11/12 -> 9710000 | AT11: =$F11/12 -> 9710000 | AU11: =$F11/12 -> 9710000 | AV11: =$F11/12 -> 9710000 | AW11: =$F11/12 -> 9710000 | AX11: =$F11/12 -> 9710000 | AY11: =$F11/12 -> 9710000 | AZ11: =$F11/12 -> 9710000 | ... BD11: =$F11/12 -> 9710000 | BE11: =$G11/12 -> 17660000 | BF11: =$G11/12 -> 17660000 | BG11: =$G11/12 -> 17660000 | BH11: =$G11/12 -> 17660000 | BI11: =$G11/12 -> 17660000 | BJ11: =$G11/12 -> 17660000 | BK11: =$G11/12 -> 17660000 | BL11: =$G11/12 -> 17660000 | ... BP11: =$G11/12 -> 17660000
B12: Locaux | C12: =Config!$C$58+Config!$D$58*'Personnel - Calculs auto'!C$6 -> 1593333.3 | D12: =Config!$C$58+Config!$D$58*'Personnel - Calculs auto'!D$6 -> 1876666.7 | E12: =Config!$C$58+Config!$D$58*'Personnel - Calculs auto'!E$6 -> 2260000 | F12: =Config!$C$58+Config!$D$58*'Personnel - Calculs auto'!F$6 -> 960000 | G12: =Config!$C$58+Config!$D$58*'Personnel - Calculs auto'!G$6 -> 960000 | I12: =$C12/12 -> 132777.78 | J12: =$C12/12 -> 132777.78 | K12: =$C12/12 -> 132777.78 | L12: =$C12/12 -> 132777.78 | M12: =$C12/12 -> 132777.78 | N12: =$C12/12 -> 132777.78 | O12: =$C12/12 -> 132777.78 | P12: =$C12/12 -> 132777.78 | ... T12: =$C12/12 -> 132777.78 | U12: =$D12/12 -> 156388.89 | V12: =$D12/12 -> 156388.89 | W12: =$D12/12 -> 156388.89 | X12: =$D12/12 -> 156388.89 | Y12: =$D12/12 -> 156388.89 | Z12: =$D12/12 -> 156388.89 | AA12: =$D12/12 -> 156388.89 | AB12: =$D12/12 -> 156388.89 | ... AF12: =$D12/12 -> 156388.89 | AG12: =$E12/12 -> 188333.33 | AH12: =$E12/12 -> 188333.33 | AI12: =$E12/12 -> 188333.33 | AJ12: =$E12/12 -> 188333.33 | AK12: =$E12/12 -> 188333.33 | AL12: =$E12/12 -> 188333.33 | AM12: =$E12/12 -> 188333.33 | AN12: =$E12/12 -> 188333.33 | ... AR12: =$E12/12 -> 188333.33 | AS12: =$F12/12 -> 80000 | AT12: =$F12/12 -> 80000 | AU12: =$F12/12 -> 80000 | AV12: =$F12/12 -> 80000 | AW12: =$F12/12 -> 80000 | AX12: =$F12/12 -> 80000 | AY12: =$F12/12 -> 80000 | AZ12: =$F12/12 -> 80000 | ... BD12: =$F12/12 -> 80000 | BE12: =$G12/12 -> 80000 | BF12: =$G12/12 -> 80000 | BG12: =$G12/12 -> 80000 | BH12: =$G12/12 -> 80000 | BI12: =$G12/12 -> 80000 | BJ12: =$G12/12 -> 80000 | BK12: =$G12/12 -> 80000 | BL12: =$G12/12 -> 80000 | ... BP12: =$G12/12 -> 80000
B13: Téléphonie | C13: =Config!$C$59+Config!$D$59*'Personnel - Calculs auto'!C$6 -> 2400000 | D13: =Config!$C$59+Config!$D$59*'Personnel - Calculs auto'!D$6 -> 2400000 | E13: =Config!$C$59+Config!$D$59*'Personnel - Calculs auto'!E$6 -> 2400000 | F13: =Config!$C$59+Config!$D$59*'Personnel - Calculs auto'!F$6 -> 2400000 | G13: =Config!$C$59+Config!$D$59*'Personnel - Calculs auto'!G$6 -> 2400000 | I13: =$C13/12 -> 200000 | J13: =$C13/12 -> 200000 | K13: =$C13/12 -> 200000 | L13: =$C13/12 -> 200000 | M13: =$C13/12 -> 200000 | N13: =$C13/12 -> 200000 | O13: =$C13/12 -> 200000 | P13: =$C13/12 -> 200000 | ... T13: =$C13/12 -> 200000 | U13: =$D13/12 -> 200000 | V13: =$D13/12 -> 200000 | W13: =$D13/12 -> 200000 | X13: =$D13/12 -> 200000 | Y13: =$D13/12 -> 200000 | Z13: =$D13/12 -> 200000 | AA13: =$D13/12 -> 200000 | AB13: =$D13/12 -> 200000 | ... AF13: =$D13/12 -> 200000 | AG13: =$E13/12 -> 200000 | AH13: =$E13/12 -> 200000 | AI13: =$E13/12 -> 200000 | AJ13: =$E13/12 -> 200000 | AK13: =$E13/12 -> 200000 | AL13: =$E13/12 -> 200000 | AM13: =$E13/12 -> 200000 | AN13: =$E13/12 -> 200000 | ... AR13: =$E13/12 -> 200000 | AS13: =$F13/12 -> 200000 | AT13: =$F13/12 -> 200000 | AU13: =$F13/12 -> 200000 | AV13: =$F13/12 -> 200000 | AW13: =$F13/12 -> 200000 | AX13: =$F13/12 -> 200000 | AY13: =$F13/12 -> 200000 | AZ13: =$F13/12 -> 200000 | ... BD13: =$F13/12 -> 200000 | BE13: =$G13/12 -> 200000 | BF13: =$G13/12 -> 200000 | BG13: =$G13/12 -> 200000 | BH13: =$G13/12 -> 200000 | BI13: =$G13/12 -> 200000 | BJ13: =$G13/12 -> 200000 | BK13: =$G13/12 -> 200000 | BL13: =$G13/12 -> 200000 | ... BP13: =$G13/12 -> 200000
B14: Assurance | C14: =Config!$C$60+Config!$D$60*'Commandes - Calculs auto'!N23 -> 3282057.6 | D14: =Config!$C$60+Config!$D$60*'Commandes - Calculs auto'!Z23 -> 12318031 | E14: =Config!$C$60+Config!$D$60*'Commandes - Calculs auto'!AL23 -> 34341077 | F14: =Config!$C$60+Config!$D$60*'Commandes - Calculs auto'!AX23 -> 57060000 | G14: =Config!$C$60+Config!$D$60*'Commandes - Calculs auto'!BJ23 -> 104760000 | I14: =$C14/12 -> 273504.8 | J14: =$C14/12 -> 273504.8 | K14: =$C14/12 -> 273504.8 | L14: =$C14/12 -> 273504.8 | M14: =$C14/12 -> 273504.8 | N14: =$C14/12 -> 273504.8 | O14: =$C14/12 -> 273504.8 | P14: =$C14/12 -> 273504.8 | ... T14: =$C14/12 -> 273504.8 | U14: =$D14/12 -> 1026502.6 | V14: =$D14/12 -> 1026502.6 | W14: =$D14/12 -> 1026502.6 | X14: =$D14/12 -> 1026502.6 | Y14: =$D14/12 -> 1026502.6 | Z14: =$D14/12 -> 1026502.6 | AA14: =$D14/12 -> 1026502.6 | AB14: =$D14/12 -> 1026502.6 | ... AF14: =$D14/12 -> 1026502.6 | AG14: =$E14/12 -> 2861756.4 | AH14: =$E14/12 -> 2861756.4 | AI14: =$E14/12 -> 2861756.4 | AJ14: =$E14/12 -> 2861756.4 | AK14: =$E14/12 -> 2861756.4 | AL14: =$E14/12 -> 2861756.4 | AM14: =$E14/12 -> 2861756.4 | AN14: =$E14/12 -> 2861756.4 | ... AR14: =$E14/12 -> 2861756.4 | AS14: =$F14/12 -> 4755000 | AT14: =$F14/12 -> 4755000 | AU14: =$F14/12 -> 4755000 | AV14: =$F14/12 -> 4755000 | AW14: =$F14/12 -> 4755000 | AX14: =$F14/12 -> 4755000 | AY14: =$F14/12 -> 4755000 | AZ14: =$F14/12 -> 4755000 | ... BD14: =$F14/12 -> 4755000 | BE14: =$G14/12 -> 8730000 | BF14: =$G14/12 -> 8730000 | BG14: =$G14/12 -> 8730000 | BH14: =$G14/12 -> 8730000 | BI14: =$G14/12 -> 8730000 | BJ14: =$G14/12 -> 8730000 | BK14: =$G14/12 -> 8730000 | BL14: =$G14/12 -> 8730000 | ... BP14: =$G14/12 -> 8730000
B15: Fournitures | C15: =Config!$C$61+Config!$D$61*'Personnel - Calculs auto'!C$6 -> 12000000 | D15: =Config!$C$61+Config!$D$61*'Personnel - Calculs auto'!D$6 -> 12000000 | E15: =Config!$C$61+Config!$D$61*'Personnel - Calculs auto'!E$6 -> 12000000 | F15: =Config!$C$61+Config!$D$61*'Personnel - Calculs auto'!F$6 -> 12000000 | G15: =Config!$C$61+Config!$D$61*'Personnel - Calculs auto'!G$6 -> 12000000 | I15: =$C15/12 -> 1000000 | J15: =$C15/12 -> 1000000 | K15: =$C15/12 -> 1000000 | L15: =$C15/12 -> 1000000 | M15: =$C15/12 -> 1000000 | N15: =$C15/12 -> 1000000 | O15: =$C15/12 -> 1000000 | P15: =$C15/12 -> 1000000 | ... T15: =$C15/12 -> 1000000 | U15: =$D15/12 -> 1000000 | V15: =$D15/12 -> 1000000 | W15: =$D15/12 -> 1000000 | X15: =$D15/12 -> 1000000 | Y15: =$D15/12 -> 1000000 | Z15: =$D15/12 -> 1000000 | AA15: =$D15/12 -> 1000000 | AB15: =$D15/12 -> 1000000 | ... AF15: =$D15/12 -> 1000000 | AG15: =$E15/12 -> 1000000 | AH15: =$E15/12 -> 1000000 | AI15: =$E15/12 -> 1000000 | AJ15: =$E15/12 -> 1000000 | AK15: =$E15/12 -> 1000000 | AL15: =$E15/12 -> 1000000 | AM15: =$E15/12 -> 1000000 | AN15: =$E15/12 -> 1000000 | ... AR15: =$E15/12 -> 1000000 | AS15: =$F15/12 -> 1000000 | AT15: =$F15/12 -> 1000000 | AU15: =$F15/12 -> 1000000 | AV15: =$F15/12 -> 1000000 | AW15: =$F15/12 -> 1000000 | AX15: =$F15/12 -> 1000000 | AY15: =$F15/12 -> 1000000 | AZ15: =$F15/12 -> 1000000 | ... BD15: =$F15/12 -> 1000000 | BE15: =$G15/12 -> 1000000 | BF15: =$G15/12 -> 1000000 | BG15: =$G15/12 -> 1000000 | BH15: =$G15/12 -> 1000000 | BI15: =$G15/12 -> 1000000 | BJ15: =$G15/12 -> 1000000 | BK15: =$G15/12 -> 1000000 | BL15: =$G15/12 -> 1000000 | ... BP15: =$G15/12 -> 1000000
B16: Informatique | C16: =Config!$C$62+Config!$D$62*'Personnel - Calculs auto'!C$6 -> 6000000 | D16: =Config!$C$62+Config!$D$62*'Personnel - Calculs auto'!D$6 -> 6000000 | E16: =Config!$C$62+Config!$D$62*'Personnel - Calculs auto'!E$6 -> 6000000 | F16: =Config!$C$62+Config!$D$62*'Personnel - Calculs auto'!F$6 -> 6000000 | G16: =Config!$C$62+Config!$D$62*'Personnel - Calculs auto'!G$6 -> 6000000 | I16: =$C16/12 -> 500000 | J16: =$C16/12 -> 500000 | K16: =$C16/12 -> 500000 | L16: =$C16/12 -> 500000 | M16: =$C16/12 -> 500000 | N16: =$C16/12 -> 500000 | O16: =$C16/12 -> 500000 | P16: =$C16/12 -> 500000 | ... T16: =$C16/12 -> 500000 | U16: =$D16/12 -> 500000 | V16: =$D16/12 -> 500000 | W16: =$D16/12 -> 500000 | X16: =$D16/12 -> 500000 | Y16: =$D16/12 -> 500000 | Z16: =$D16/12 -> 500000 | AA16: =$D16/12 -> 500000 | AB16: =$D16/12 -> 500000 | ... AF16: =$D16/12 -> 500000 | AG16: =$E16/12 -> 500000 | AH16: =$E16/12 -> 500000 | AI16: =$E16/12 -> 500000 | AJ16: =$E16/12 -> 500000 | AK16: =$E16/12 -> 500000 | AL16: =$E16/12 -> 500000 | AM16: =$E16/12 -> 500000 | AN16: =$E16/12 -> 500000 | ... AR16: =$E16/12 -> 500000 | AS16: =$F16/12 -> 500000 | AT16: =$F16/12 -> 500000 | AU16: =$F16/12 -> 500000 | AV16: =$F16/12 -> 500000 | AW16: =$F16/12 -> 500000 | AX16: =$F16/12 -> 500000 | AY16: =$F16/12 -> 500000 | AZ16: =$F16/12 -> 500000 | ... BD16: =$F16/12 -> 500000 | BE16: =$G16/12 -> 500000 | BF16: =$G16/12 -> 500000 | BG16: =$G16/12 -> 500000 | BH16: =$G16/12 -> 500000 | BI16: =$G16/12 -> 500000 | BJ16: =$G16/12 -> 500000 | BK16: =$G16/12 -> 500000 | BL16: =$G16/12 -> 500000 | ... BP16: =$G16/12 -> 500000
B17: Frais bancaires | C17: =Config!$C$63+Config!$D$63*'Commandes - Calculs auto'!N23 -> 1591028.8 | D17: =Config!$C$63+Config!$D$63*'Commandes - Calculs auto'!Z23 -> 6109015.5 | E17: =Config!$C$63+Config!$D$63*'Commandes - Calculs auto'!AL23 -> 17120539 | F17: =Config!$C$63+Config!$D$63*'Commandes - Calculs auto'!AX23 -> 28480000 | G17: =Config!$C$63+Config!$D$63*'Commandes - Calculs auto'!BJ23 -> 52330000 | I17: =$C17/12 -> 132585.73 | J17: =$C17/12 -> 132585.73 | K17: =$C17/12 -> 132585.73 | L17: =$C17/12 -> 132585.73 | M17: =$C17/12 -> 132585.73 | N17: =$C17/12 -> 132585.73 | O17: =$C17/12 -> 132585.73 | P17: =$C17/12 -> 132585.73 | ... T17: =$C17/12 -> 132585.73 | U17: =$D17/12 -> 509084.62 | V17: =$D17/12 -> 509084.62 | W17: =$D17/12 -> 509084.62 | X17: =$D17/12 -> 509084.62 | Y17: =$D17/12 -> 509084.62 | Z17: =$D17/12 -> 509084.62 | AA17: =$D17/12 -> 509084.62 | AB17: =$D17/12 -> 509084.62 | ... AF17: =$D17/12 -> 509084.62 | AG17: =$E17/12 -> 1426711.5 | AH17: =$E17/12 -> 1426711.5 | AI17: =$E17/12 -> 1426711.5 | AJ17: =$E17/12 -> 1426711.5 | AK17: =$E17/12 -> 1426711.5 | AL17: =$E17/12 -> 1426711.5 | AM17: =$E17/12 -> 1426711.5 | AN17: =$E17/12 -> 1426711.5 | ... AR17: =$E17/12 -> 1426711.5 | AS17: =$F17/12 -> 2373333.3 | AT17: =$F17/12 -> 2373333.3 | AU17: =$F17/12 -> 2373333.3 | AV17: =$F17/12 -> 2373333.3 | AW17: =$F17/12 -> 2373333.3 | AX17: =$F17/12 -> 2373333.3 | AY17: =$F17/12 -> 2373333.3 | AZ17: =$F17/12 -> 2373333.3 | ... BD17: =$F17/12 -> 2373333.3 | BE17: =$G17/12 -> 4360833.3 | BF17: =$G17/12 -> 4360833.3 | BG17: =$G17/12 -> 4360833.3 | BH17: =$G17/12 -> 4360833.3 | BI17: =$G17/12 -> 4360833.3 | BJ17: =$G17/12 -> 4360833.3 | BK17: =$G17/12 -> 4360833.3 | BL17: =$G17/12 -> 4360833.3 | ... BP17: =$G17/12 -> 4360833.3
B18: Divers | C18: =Config!$C$64+Config!$D$64*'Commandes - Calculs auto'!N23 -> 120000 | D18: =Config!$C$64+Config!$D$64*'Commandes - Calculs auto'!Z23 -> 120000 | E18: =Config!$C$64+Config!$D$64*'Commandes - Calculs auto'!AL23 -> 120000 | F18: =Config!$C$64+Config!$D$64*'Commandes - Calculs auto'!AX23 -> 120000 | G18: =Config!$C$64+Config!$D$64*'Commandes - Calculs auto'!BJ23 -> 120000 | I18: =$C18/12 -> 10000 | J18: =$C18/12 -> 10000 | K18: =$C18/12 -> 10000 | L18: =$C18/12 -> 10000 | M18: =$C18/12 -> 10000 | N18: =$C18/12 -> 10000 | O18: =$C18/12 -> 10000 | P18: =$C18/12 -> 10000 | ... T18: =$C18/12 -> 10000 | U18: =$D18/12 -> 10000 | V18: =$D18/12 -> 10000 | W18: =$D18/12 -> 10000 | X18: =$D18/12 -> 10000 | Y18: =$D18/12 -> 10000 | Z18: =$D18/12 -> 10000 | AA18: =$D18/12 -> 10000 | AB18: =$D18/12 -> 10000 | ... AF18: =$D18/12 -> 10000 | AG18: =$E18/12 -> 10000 | AH18: =$E18/12 -> 10000 | AI18: =$E18/12 -> 10000 | AJ18: =$E18/12 -> 10000 | AK18: =$E18/12 -> 10000 | AL18: =$E18/12 -> 10000 | AM18: =$E18/12 -> 10000 | AN18: =$E18/12 -> 10000 | ... AR18: =$E18/12 -> 10000 | AS18: =$F18/12 -> 10000 | AT18: =$F18/12 -> 10000 | AU18: =$F18/12 -> 10000 | AV18: =$F18/12 -> 10000 | AW18: =$F18/12 -> 10000 | AX18: =$F18/12 -> 10000 | AY18: =$F18/12 -> 10000 | AZ18: =$F18/12 -> 10000 | ... BD18: =$F18/12 -> 10000 | BE18: =$G18/12 -> 10000 | BF18: =$G18/12 -> 10000 | BG18: =$G18/12 -> 10000 | BH18: =$G18/12 -> 10000 | BI18: =$G18/12 -> 10000 | BJ18: =$G18/12 -> 10000 | BK18: =$G18/12 -> 10000 | BL18: =$G18/12 -> 10000 | ... BP18: =$G18/12 -> 10000
C19: =SUM(I19:T19) -> 0 | D19: =SUM(U19:AF19) -> 0 | E19: =SUM(AG19:AR19) -> 0 | F19: =SUM(AS19:BD19) -> 0 | G19: =SUM(BE19:BP19) -> 0
C20: =SUM(I20:T20) -> 0 | D20: =SUM(U20:AF20) -> 0 | E20: =SUM(AG20:AR20) -> 0 | F20: =SUM(AS20:BD20) -> 0 | G20: =SUM(BE20:BP20) -> 0
C21: =SUM(I21:T21) -> 0 | D21: =SUM(U21:AF21) -> 0 | E21: =SUM(AG21:AR21) -> 0 | F21: =SUM(AS21:BD21) -> 0 | G21: =SUM(BE21:BP21) -> 0
C22: =SUM(I22:T22) -> 0 | D22: =SUM(U22:AF22) -> 0 | E22: =SUM(AG22:AR22) -> 0 | F22: =SUM(AS22:BD22) -> 0 | G22: =SUM(BE22:BP22) -> 0
C23: =SUM(I23:T23) -> 0 | D23: =SUM(U23:AF23) -> 0 | E23: =SUM(AG23:AR23) -> 0 | F23: =SUM(AS23:BD23) -> 0 | G23: =SUM(BE23:BP23) -> 0
C24: =SUM(I24:T24) -> 0 | D24: =SUM(U24:AF24) -> 0 | E24: =SUM(AG24:AR24) -> 0 | F24: =SUM(AS24:BD24) -> 0 | G24: =SUM(BE24:BP24) -> 0
C25: =SUM(I25:T25) -> 0 | D25: =SUM(U25:AF25) -> 0 | E25: =SUM(AG25:AR25) -> 0 | F25: =SUM(AS25:BD25) -> 0 | G25: =SUM(BE25:BP25) -> 0
C26: =SUM(I26:T26) -> 0 | D26: =SUM(U26:AF26) -> 0 | E26: =SUM(AG26:AR26) -> 0 | F26: =SUM(AS26:BD26) -> 0 | G26: =SUM(BE26:BP26) -> 0
C27: =SUM(I27:T27) -> 0 | D27: =SUM(U27:AF27) -> 0 | E27: =SUM(AG27:AR27) -> 0 | F27: =SUM(AS27:BD27) -> 0 | G27: =SUM(BE27:BP27) -> 0
C28: =SUM(I28:T28) -> 0 | D28: =SUM(U28:AF28) -> 0 | E28: =SUM(AG28:AR28) -> 0 | F28: =SUM(AS28:BD28) -> 0 | G28: =SUM(BE28:BP28) -> 0
B29: TOTAL | C29: =SUM(C9:C28) -> 43882592 | D29: =SUM(D9:D28) -> 84827806 | E29: =SUM(E9:E28) -> 184314847 | F29: =SUM(F9:F28) -> 285250000 | G29: =SUM(G9:G28) -> 499900000 | I29: =SUM(I9:I28) -> 3656882.7 | J29: =SUM(J9:J28) -> 3656882.7 | K29: =SUM(K9:K28) -> 3656882.7 | L29: =SUM(L9:L28) -> 3656882.7 | M29: =SUM(M9:M28) -> 3656882.7 | N29: =SUM(N9:N28) -> 3656882.7 | O29: =SUM(O9:O28) -> 3656882.7 | P29: =SUM(P9:P28) -> 3656882.7 | ... BP29: =SUM(BP9:BP28) -> 41658333

Sheet Investissements
B2: INVESTISSEMENTS (HT)
B5: Note : Définissez vos investissements et apports en nature en précisant les intitulés et sommes des investissements, ainsi que les durées d'amortissement (à droite du tableau). Pour un investissement en crédit-bail, spécifiez les loyers mensuels à payer et renseignez la mention "VRAI" dans la colonne "Financements en crédit-bail". Dans le cas d'un financement par crédit-bail, la durée d'amortissement n'a pas d'effet.
C7: Année 1 | P7: Année 2 | AC7: Année 3 | AF7: Année 4 | AI7: Année 5 | AM7: Amortissement (en années) 0 si non amortissable | AN7: Année 1 | AO7: Année 2 | AP7: Année 3 | AQ7: Année 4 | AR7: Année 5 | AS7: Financement en crédit-bail (VRAI/FAUX)
B8: Intitulés | C8: =Config!$C$7 -> 45505 | D8: =DATE(YEAR(C8),MONTH(C8)+1,DAY(C8)) -> 45536 | E8: =DATE(YEAR(D8),MONTH(D8)+1,DAY(D8)) -> 45566 | F8: =DATE(YEAR(E8),MONTH(E8)+1,DAY(E8)) -> 45597 | G8: =DATE(YEAR(F8),MONTH(F8)+1,DAY(F8)) -> 45627 | H8: =DATE(YEAR(G8),MONTH(G8)+1,DAY(G8)) -> 45658 | I8: =DATE(YEAR(H8),MONTH(H8)+1,DAY(H8)) -> 45689 | J8: =DATE(YEAR(I8),MONTH(I8)+1,DAY(I8)) -> 45717 | K8: =DATE(YEAR(J8),MONTH(J8)+1,DAY(J8)) -> 45748 | ... N8: =DATE(YEAR(M8),MONTH(M8)+1,DAY(M8)) -> 45839 | O8: TOTAL | P8: =DATE(YEAR(N8),MONTH(N8)+1,DAY(N8)) -> 45870 | Q8: =DATE(YEAR(P8),MONTH(P8)+1,DAY(P8)) -> 45901 | R8: =DATE(YEAR(Q8),MONTH(Q8)+1,DAY(Q8)) -> 45931 | S8: =DATE(YEAR(R8),MONTH(R8)+1,DAY(R8)) -> 45962 | T8: =DATE(YEAR(S8),MONTH(S8)+1,DAY(S8)) -> 45992 | U8: =DATE(YEAR(T8),MONTH(T8)+1,DAY(T8)) -> 46023 | V8: =DATE(YEAR(U8),MONTH(U8)+1,DAY(U8)) -> 46054 | W8: =DATE(YEAR(V8),MONTH(V8)+1,DAY(V8)) -> 46082 | X8: =DATE(YEAR(W8),MONTH(W8)+1,DAY(W8)) -> 46113 | ... AA8: =DATE(YEAR(Z8),MONTH(Z8)+1,DAY(Z8)) -> 46204 | AB8: TOTAL | AC8: S1 | AD8: S2 | AE8: TOTAL | AF8: S1 | AG8: S2 | AH8: TOTAL | AI8: S1 | AJ8: S2 | AK8: TOTAL
B9: Apports en nature | O9: =SUM(C9:N9) -> 0 | AB9: =SUM(P9:AA9) -> 0 | AE9: =SUM(AC9:AD9) -> 0 | AH9: =SUM(AF9:AG9) -> 0 | AK9: =SUM(AI9:AJ9) -> 0 | AM9: 0 | AN9: =IF(OR($AM9=0,AS9),0,O9/$AM9) -> 0 | AO9: =IF(OR($AM9=0,AS9),0,AB9/$AM9+IF($AM9>=2,O9/$AM9,0)) -> 0 | AP9: =IF(OR($AM9=0,AS9),0,AE9/$AM9+IF($AM9>=2,AB9/$AM9,0)+IF($AM9>=3,O9/$AM9,0)) -> 0 | AQ9: =IF(OR($AM9=0,AS9),0,AH9/$AM9+IF($AM9>=2,AE9/$AM9,0)+IF($AM9>=3,AB9/$AM9,0)+IF($AM9>=4,O9/$AM9,0)) -> 0 | AR9: =IF(OR($AM9=0,AS9),0,AK9/$AM9+IF($AM9>=2,AH9/$AM9,0)+IF($AM9>=3,AE9/$AM9,0)+IF($AM9>=4,AB9/$AM9,0)+IF($AM9>=5,O9/$AM9,0)) -> 0 | AS9: FALSE
B10: Visio conference | H10: 6000000 | O10: =SUM(C10:N10) -> 6000000 | P10: 6000000 | AB10: =SUM(P10:AA10) -> 6000000 | AC10: 8000000 | AE10: =SUM(AC10:AD10) -> 8000000 | AH10: =SUM(AF10:AG10) -> 0 | AK10: =SUM(AI10:AJ10) -> 0 | AM10: 3 | AN10: =IF(OR($AM10=0,AS10),0,O10/$AM10) -> 2000000 | AO10: =IF(OR($AM10=0,AS10),0,AB10/$AM10+IF($AM10>=2,O10/$AM10,0)) -> 4000000 | AP10: =IF(OR($AM10=0,AS10),0,AE10/$AM10+IF($AM10>=2,AB10/$AM10,0)+IF($AM10>=3,O10/$AM10,0)) -> 6666666.7 | AQ10: =IF(OR($AM10=0,AS10),0,AH10/$AM10+IF($AM10>=2,AE10/$AM10,0)+IF($AM10>=3,AB10/$AM10,0)+IF($AM10>=4,O10/$AM10,0)) -> 4666666.7 | AR10: =IF(OR($AM10=0,AS10),0,AK10/$AM10+IF($AM10>=2,AH10/$AM10,0)+IF($AM10>=3,AE10/$AM10,0)+IF($AM10>=4,AB10/$AM10,0)+IF($AM10>=5,O10/$AM10,0)) -> 2666666.7
AK12: =SUM(AI12:AJ12) -> 0 | AM12: 3 | AN12: =IF(OR($AM12=0,AS12),0,O12/$AM12) -> 0 | AO12: =IF(OR($AM12=0,AS12),0,AB12/$AM12+IF($AM12>=2,O12/$AM12,0)) -> 0 | AP12: =IF(OR($AM12=0,AS12),0,AE12/$AM12+IF($AM12>=2,AB12/$AM12,0)+IF($AM12>=3,O12/$AM12,0)) -> 0 | AQ12: =IF(OR($AM12=0,AS12),0,AH12/$AM12+IF($AM12>=2,AE12/$AM12,0)+IF($AM12>=3,AB12/$AM12,0)+IF($AM12>=4,O12/$AM12,0)) -> 0 | AR12: =IF(OR($AM12=0,AS12),0,AK12/$AM12+IF($AM12>=2,AH12/$AM12,0)+IF($AM12>=3,AE12/$AM12,0)+IF($AM12>=4,AB12/$AM12,0)+IF($AM12>=5,O12/$AM12,0)) -> 0
AK13: =SUM(AI13:AJ13) -> 0 | AM13: 3 | AN13: =IF(OR($AM13=0,AS13),0,O13/$AM13) -> 0 | AO13: =IF(OR($AM13=0,AS13),0,AB13/$AM13+IF($AM13>=2,O13/$AM13,0)) -> 0 | AP13: =IF(OR($AM13=0,AS13),0,AE13/$AM13+IF($AM13>=2,AB13/$AM13,0)+IF($AM13>=3,O13/$AM13,0)) -> 0 | AQ13: =IF(OR($AM13=0,AS13),0,AH13/$AM13+IF($AM13>=2,AE13/$AM13,0)+IF($AM13>=3,AB13/$AM13,0)+IF($AM13>=4,O13/$AM13,0)) -> 0 | AR13: =IF(OR($AM13=0,AS13),0,AK13/$AM13+IF($AM13>=2,AH13/$AM13,0)+IF($AM13>=3,AE13/$AM13,0)+IF($AM13>=4,AB13/$AM13,0)+IF($AM13>=5,O13/$AM13,0)) -> 0
AK14: =SUM(AI14:AJ14) -> 0 | AM14: 3 | AN14: =IF(OR($AM14=0,AS14),0,O14/$AM14) -> 0 | AO14: =IF(OR($AM14=0,AS14),0,AB14/$AM14+IF($AM14>=2,O14/$AM14,0)) -> 0 | AP14: =IF(OR($AM14=0,AS14),0,AE14/$AM14+IF($AM14>=2,AB14/$AM14,0)+IF($AM14>=3,O14/$AM14,0)) -> 0 | AQ14: =IF(OR($AM14=0,AS14),0,AH14/$AM14+IF($AM14>=2,AE14/$AM14,0)+IF($AM14>=3,AB14/$AM14,0)+IF($AM14>=4,O14/$AM14,0)) -> 0 | AR14: =IF(OR($AM14=0,AS14),0,AK14/$AM14+IF($AM14>=2,AH14/$AM14,0)+IF($AM14>=3,AE14/$AM14,0)+IF($AM14>=4,AB14/$AM14,0)+IF($AM14>=5,O14/$AM14,0)) -> 0
AK15: =SUM(AI15:AJ15) -> 0 | AM15: 3 | AN15: =IF(OR($AM15=0,AS15),0,O15/$AM15) -> 0 | AO15: =IF(OR($AM15=0,AS15),0,AB15/$AM15+IF($AM15>=2,O15/$AM15,0)) -> 0 | AP15: =IF(OR($AM15=0,AS15),0,AE15/$AM15+IF($AM15>=2,AB15/$AM15,0)+IF($AM15>=3,O15/$AM15,0)) -> 0 | AQ15: =IF(OR($AM15=0,AS15),0,AH15/$AM15+IF($AM15>=2,AE15/$AM15,0)+IF($AM15>=3,AB15/$AM15,0)+IF($AM15>=4,O15/$AM15,0)) -> 0 | AR15: =IF(OR($AM15=0,AS15),0,AK15/$AM15+IF($AM15>=2,AH15/$AM15,0)+IF($AM15>=3,AE15/$AM15,0)+IF($AM15>=4,AB15/$AM15,0)+IF($AM15>=5,O15/$AM15,0)) -> 0
AK16: =SUM(AI16:AJ16) -> 0 | AM16: 3 | AN16: =IF(OR($AM16=0,AS16),0,O16/$AM16) -> 0 | AO16: =IF(OR($AM16=0,AS16),0,AB16/$AM16+IF($AM16>=2,O16/$AM16,0)) -> 0 | AP16: =IF(OR($AM16=0,AS16),0,AE16/$AM16+IF($AM16>=2,AB16/$AM16,0)+IF($AM16>=3,O16/$AM16,0)) -> 0 | AQ16: =IF(OR($AM16=0,AS16),0,AH16/$AM16+IF($AM16>=2,AE16/$AM16,0)+IF($AM16>=3,AB16/$AM16,0)+IF($AM16>=4,O16/$AM16,0)) -> 0 | AR16: =IF(OR($AM16=0,AS16),0,AK16/$AM16+IF($AM16>=2,AH16/$AM16,0)+IF($AM16>=3,AE16/$AM16,0)+IF($AM16>=4,AB16/$AM16,0)+IF($AM16>=5,O16/$AM16,0)) -> 0
AK17: =SUM(AI17:AJ17) -> 0 | AM17: 3 | AN17: =IF(OR($AM17=0,AS17),0,O17/$AM17) -> 0 | AO17: =IF(OR($AM17=0,AS17),0,AB17/$AM17+IF($AM17>=2,O17/$AM17,0)) -> 0 | AP17: =IF(OR($AM17=0,AS17),0,AE17/$AM17+IF($AM17>=2,AB17/$AM17,0)+IF($AM17>=3,O17/$AM17,0)) -> 0 | AQ17: =IF(OR($AM17=0,AS17),0,AH17/$AM17+IF($AM17>=2,AE17/$AM17,0)+IF($AM17>=3,AB17/$AM17,0)+IF($AM17>=4,O17/$AM17,0)) -> 0 | AR17: =IF(OR($AM17=0,AS17),0,AK17/$AM17+IF($AM17>=2,AH17/$AM17,0)+IF($AM17>=3,AE17/$AM17,0)+IF($AM17>=4,AB17/$AM17,0)+IF($AM17>=5,O17/$AM17,0)) -> 0
AK18: =SUM(AI18:AJ18) -> 0 | AM18: 3 | AN18: =IF(OR($AM18=0,AS18),0,O18/$AM18) -> 0 | AO18: =IF(OR($AM18=0,AS18),0,AB18/$AM18+IF($AM18>=2,O18/$AM18,0)) -> 0 | AP18: =IF(OR($AM18=0,AS18),0,AE18/$AM18+IF($AM18>=2,AB18/$AM18,0)+IF($AM18>=3,O18/$AM18,0)) -> 0 | AQ18: =IF(OR($AM18=0,AS18),0,AH18/$AM18+IF($AM18>=2,AE18/$AM18,0)+IF($AM18>=3,AB18/$AM18,0)+IF($AM18>=4,O18/$AM18,0)) -> 0 | AR18: =IF(OR($AM18=0,AS18),0,AK18/$AM18+IF($AM18>=2,AH18/$AM18,0)+IF($AM18>=3,AE18/$AM18,0)+IF($AM18>=4,AB18/$AM18,0)+IF($AM18>=5,O18/$AM18,0)) -> 0
AK19: =SUM(AI19:AJ19) -> 0 | AM19: 3 | AN19: =IF(OR($AM19=0,AS19),0,O19/$AM19) -> 0 | AO19: =IF(OR($AM19=0,AS19),0,AB19/$AM19+IF($AM19>=2,O19/$AM19,0)) -> 0 | AP19: =IF(OR($AM19=0,AS19),0,AE19/$AM19+IF($AM19>=2,AB19/$AM19,0)+IF($AM19>=3,O19/$AM19,0)) -> 0 | AQ19: =IF(OR($AM19=0,AS19),0,AH19/$AM19+IF($AM19>=2,AE19/$AM19,0)+IF($AM19>=3,AB19/$AM19,0)+IF($AM19>=4,O19/$AM19,0)) -> 0 | AR19: =IF(OR($AM19=0,AS19),0,AK19/$AM19+IF($AM19>=2,AH19/$AM19,0)+IF($AM19>=3,AE19/$AM19,0)+IF($AM19>=4,AB19/$AM19,0)+IF($AM19>=5,O19/$AM19,0)) -> 0
AK20: =SUM(AI20:AJ20) -> 0 | AM20: 3 | AN20: =IF(OR($AM20=0,AS20),0,O20/$AM20) -> 0 | AO20: =IF(OR($AM20=0,AS20),0,AB20/$AM20+IF($AM20>=2,O20/$AM20,0)) -> 0 | AP20: =IF(OR($AM20=0,AS20),0,AE20/$AM20+IF($AM20>=2,AB20/$AM20,0)+IF($AM20>=3,O20/$AM20,0)) -> 0 | AQ20: =IF(OR($AM20=0,AS20),0,AH20/$AM20+IF($AM20>=2,AE20/$AM20,0)+IF($AM20>=3,AB20/$AM20,0)+IF($AM20>=4,O20/$AM20,0)) -> 0 | AR20: =IF(OR($AM20=0,AS20),0,AK20/$AM20+IF($AM20>=2,AH20/$AM20,0)+IF($AM20>=3,AE20/$AM20,0)+IF($AM20>=4,AB20/$AM20,0)+IF($AM20>=5,O20/$AM20,0)) -> 0
AK21: =SUM(AI21:AJ21) -> 0 | AM21: 3 | AN21: =IF(OR($AM21=0,AS21),0,O21/$AM21) -> 0 | AO21: =IF(OR($AM21=0,AS21),0,AB21/$AM21+IF($AM21>=2,O21/$AM21,0)) -> 0 | AP21: =IF(OR($AM21=0,AS21),0,AE21/$AM21+IF($AM21>=2,AB21/$AM21,0)+IF($AM21>=3,O21/$AM21,0)) -> 0 | AQ21: =IF(OR($AM21=0,AS21),0,AH21/$AM21+IF($AM21>=2,AE21/$AM21,0)+IF($AM21>=3,AB21/$AM21,0)+IF($AM21>=4,O21/$AM21,0)) -> 0 | AR21: =IF(OR($AM21=0,AS21),0,AK21/$AM21+IF($AM21>=2,AH21/$AM21,0)+IF($AM21>=3,AE21/$AM21,0)+IF($AM21>=4,AB21/$AM21,0)+IF($AM21>=5,O21/$AM21,0)) -> 0
AK22: =SUM(AI22:AJ22) -> 0 | AM22: 3 | AN22: =IF(OR($AM22=0,AS22),0,O22/$AM22) -> 0 | AO22: =IF(OR($AM22=0,AS22),0,AB22/$AM22+IF($AM22>=2,O22/$AM22,0)) -> 0 | AP22: =IF(OR($AM22=0,AS22),0,AE22/$AM22+IF($AM22>=2,AB22/$AM22,0)+IF($AM22>=3,O22/$AM22,0)) -> 0 | AQ22: =IF(OR($AM22=0,AS22),0,AH22/$AM22+IF($AM22>=2,AE22/$AM22,0)+IF($AM22>=3,AB22/$AM22,0)+IF($AM22>=4,O22/$AM22,0)) -> 0 | AR22: =IF(OR($AM22=0,AS22),0,AK22/$AM22+IF($AM22>=2,AH22/$AM22,0)+IF($AM22>=3,AE22/$AM22,0)+IF($AM22>=4,AB22/$AM22,0)+IF($AM22>=5,O22/$AM22,0)) -> 0
AK23: =SUM(AI23:AJ23) -> 0 | AM23: 3 | AN23: =IF(OR($AM23=0,AS23),0,O23/$AM23) -> 0 | AO23: =IF(OR($AM23=0,AS23),0,AB23/$AM23+IF($AM23>=2,O23/$AM23,0)) -> 0 | AP23: =IF(OR($AM23=0,AS23),0,AE23/$AM23+IF($AM23>=2,AB23/$AM23,0)+IF($AM23>=3,O23/$AM23,0)) -> 0 | AQ23: =IF(OR($AM23=0,AS23),0,AH23/$AM23+IF($AM23>=2,AE23/$AM23,0)+IF($AM23>=3,AB23/$AM23,0)+IF($AM23>=4,O23/$AM23,0)) -> 0 | AR23: =IF(OR($AM23=0,AS23),0,AK23/$AM23+IF($AM23>=2,AH23/$AM23,0)+IF($AM23>=3,AE23/$AM23,0)+IF($AM23>=4,AB23/$AM23,0)+IF($AM23>=5,O23/$AM23,0)) -> 0
O24: =SUM(C24:N24) -> 0 | AB24: =SUM(P24:AA24) -> 0 | AE24: =SUM(AC24:AD24) -> 0 | AH24: =SUM(AF24:AG24) -> 0 | AK24: =SUM(AI24:AJ24) -> 0 | AM24: 3 | AN24: =IF(OR($AM24=0,AS24),0,O24/$AM24) -> 0 | AO24: =IF(OR($AM24=0,AS24),0,AB24/$AM24+IF($AM24>=2,O24/$AM24,0)) -> 0 | AP24: =IF(OR($AM24=0,AS24),0,AE24/$AM24+IF($AM24>=2,AB24/$AM24,0)+IF($AM24>=3,O24/$AM24,0)) -> 0 | AQ24: =IF(OR($AM24=0,AS24),0,AH24/$AM24+IF($AM24>=2,AE24/$AM24,0)+IF($AM24>=3,AB24/$AM24,0)+IF($AM24>=4,O24/$AM24,0)) -> 0 | AR24: =IF(OR($AM24=0,AS24),0,AK24/$AM24+IF($AM24>=2,AH24/$AM24,0)+IF($AM24>=3,AE24/$AM24,0)+IF($AM24>=4,AB24/$AM24,0)+IF($AM24>=5,O24/$AM24,0)) -> 0
O25: =SUM(C25:N25) -> 0 | AB25: =SUM(P25:AA25) -> 0 | AE25: =SUM(AC25:AD25) -> 0 | AH25: =SUM(AF25:AG25) -> 0 | AK25: =SUM(AI25:AJ25) -> 0 | AM25: 3 | AN25: =IF(OR($AM25=0,AS25),0,O25/$AM25) -> 0 | AO25: =IF(OR($AM25=0,AS25),0,AB25/$AM25+IF($AM25>=2,O25/$AM25,0)) -> 0 | AP25: =IF(OR($AM25=0,AS25),0,AE25/$AM25+IF($AM25>=2,AB25/$AM25,0)+IF($AM25>=3,O25/$AM25,0)) -> 0 | AQ25: =IF(OR($AM25=0,AS25),0,AH25/$AM25+IF($AM25>=2,AE25/$AM25,0)+IF($AM25>=3,AB25/$AM25,0)+IF($AM25>=4,O25/$AM25,0)) -> 0 | AR25: =IF(OR($AM25=0,AS25),0,AK25/$AM25+IF($AM25>=2,AH25/$AM25,0)+IF($AM25>=3,AE25/$AM25,0)+IF($AM25>=4,AB25/$AM25,0)+IF($AM25>=5,O25/$AM25,0)) -> 0
O26: =SUM(C26:N26) -> 0 | AB26: =SUM(P26:AA26) -> 0 | AE26: =SUM(AC26:AD26) -> 0 | AH26: =SUM(AF26:AG26) -> 0 | AK26: =SUM(AI26:AJ26) -> 0 | AM26: 3 | AN26: =IF(OR($AM26=0,AS26),0,O26/$AM26) -> 0 | AO26: =IF(OR($AM26=0,AS26),0,AB26/$AM26+IF($AM26>=2,O26/$AM26,0)) -> 0 | AP26: =IF(OR($AM26=0,AS26),0,AE26/$AM26+IF($AM26>=2,AB26/$AM26,0)+IF($AM26>=3,O26/$AM26,0)) -> 0 | AQ26: =IF(OR($AM26=0,AS26),0,AH26/$AM26+IF($AM26>=2,AE26/$AM26,0)+IF($AM26>=3,AB26/$AM26,0)+IF($AM26>=4,O26/$AM26,0)) -> 0 | AR26: =IF(OR($AM26=0,AS26),0,AK26/$AM26+IF($AM26>=2,AH26/$AM26,0)+IF($AM26>=3,AE26/$AM26,0)+IF($AM26>=4,AB26/$AM26,0)+IF($AM26>=5,O26/$AM26,0)) -> 0
O27: =SUM(C27:N27) -> 0 | AB27: =SUM(P27:AA27) -> 0 | AE27: =SUM(AC27:AD27) -> 0 | AH27: =SUM(AF27:AG27) -> 0 | AK27: =SUM(AI27:AJ27) -> 0 | AM27: 3 | AN27: =IF(OR($AM27=0,AS27),0,O27/$AM27) -> 0 | AO27: =IF(OR($AM27=0,AS27),0,AB27/$AM27+IF($AM27>=2,O27/$AM27,0)) -> 0 | AP27: =IF(OR($AM27=0,AS27),0,AE27/$AM27+IF($AM27>=2,AB27/$AM27,0)+IF($AM27>=3,O27/$AM27,0)) -> 0 | AQ27: =IF(OR($AM27=0,AS27),0,AH27/$AM27+IF($AM27>=2,AE27/$AM27,0)+IF($AM27>=3,AB27/$AM27,0)+IF($AM27>=4,O27/$AM27,0)) -> 0 | AR27: =IF(OR($AM27=0,AS27),0,AK27/$AM27+IF($AM27>=2,AH27/$AM27,0)+IF($AM27>=3,AE27/$AM27,0)+IF($AM27>=4,AB27/$AM27,0)+IF($AM27>=5,O27/$AM27,0)) -> 0
B28: TOTAL | C28: =SUM(C9:C27) -> 0 | D28: =SUM(D9:D27) -> 0 | E28: =SUM(E9:E27) -> 0 | F28: =SUM(F9:F27) -> 0 | G28: =SUM(G9:G27) -> 0 | H28: =SUM(H9:H27) -> 6000000 | I28: =SUM(I9:I27) -> 0 | J28: =SUM(J9:J27) -> 0 | ... AK28: =SUM(AK9:AK27) -> 0 | AN28: =SUM(AN9:AN27) -> 2000000 | AO28: =SUM(AO9:AO27) -> 4000000 | AP28: =SUM(AP9:AP27) -> 6666666.7 | AQ28: =SUM(AQ9:AQ27) -> 4666666.7 | AR28: =SUM(AR9:AR27) -> 2666666.7

Sheet Commandes
B2: COMMANDES
B5: Note : Indiquez dans ce tableau pour chaque activité, la prévision du nombre d'unités commandées mensuellement. Attention! On parle de commandes, et non de paiements. Les délais de paiement sont à définir dans l'onglet "CONFIG". Les paiements associés seront automatiquement calculés ci-dessous, en fonction des informations entrées dans l'onglet "CONFIG" en lien avec les "Commandes" renseignées.
C7: Année 1 | O7: Année 2 | AA7: Année 3 | AM7: Année 4 | AY7: Année 5
B8: Commandes réalisées | C8: =Config!$C$7 -> 45505 | D8: =DATE(YEAR(C8),MONTH(C8)+1,DAY(C8)) -> 45536 | E8: =DATE(YEAR(D8),MONTH(D8)+1,DAY(D8)) -> 45566 | F8: =DATE(YEAR(E8),MONTH(E8)+1,DAY(E8)) -> 45597 | G8: =DATE(YEAR(F8),MONTH(F8)+1,DAY(F8)) -> 45627 | H8: =DATE(YEAR(G8),MONTH(G8)+1,DAY(G8)) -> 45658 | I8: =DATE(YEAR(H8),MONTH(H8)+1,DAY(H8)) -> 45689 | J8: =DATE(YEAR(I8),MONTH(I8)+1,DAY(I8)) -> 45717 | K8: =DATE(YEAR(J8),MONTH(J8)+1,DAY(J8)) -> 45748 | ... BJ8: =DATE(YEAR(BI8),MONTH(BI8)+1,DAY(BI8)) -> 47300
B9: =Config!$B$14 -> Abonnement Basique | E9: 30 | F9: 50 | G9: 75 | H9: 100 | I9: =H9*1.1 -> 110 | J9: =I9*1.1 -> 121 | K9: =J9*1.1 -> 133.1 | L9: =K9*1.1 -> 146.41 | M9: =L9*1.1 -> 161.051 | N9: =M9*1.1 -> 177.1561 | O9: =N9*1.1 -> 194.87171 | P9: =O9*1.25 -> 243.58964 | Q9: =P9*1.25 -> 304.48705 | R9: =Q9*1.25 -> 380.60881 | S9: =R9*1.25 -> 475.76101 | T9: =S9*1.25 -> 594.70126 | U9: =T9*1.25 -> 743.37658 | V9: =U9*1.25 -> 929.22072 | W9: =V9*1.25 -> 1161.5259 | ... AK9: =AJ9*1.25 -> 26410.041 | AL9: 10000 | AM9: 12000 | AN9: 12000 | AO9: 12000 | AP9: 15000 | AQ9: 15000 | AR9: 15000 | AS9: 17000 | AT9: 17000 | AU9: 17000 | AV9: 20000 | AW9: 20000 | AX9: 20000 | AY9: 25000 | AZ9: 25000 | BA9: 25000 | BB9: 25000 | BC9: 25000 | BD9: 25000 | BE9: 30000 | BF9: 30000 | BG9: 30000 | BH9: 30000 | BI9: 30000 | BJ9: 30000
B10: =Config!$B$15 -> Abonnement Premium | E10: 50 | F10: 100 | G10: 200 | H10: 500 | I10: 800 | J10: 1000 | K10: 1200 | L10: 1200 | M10: 1500 | N10: 1500 | O10: 2000 | P10: 2200 | Q10: 2500 | R10: 2600 | S10: 2700 | T10: 2900 | U10: 3000 | V10: 3200 | W10: 3400 | X10: 3500 | Y10: 3600 | Z10: 3750 | AA10: 3900 | AB10: 4000 | AC10: 4000 | AD10: 4000 | AE10: 4000 | AF10: 4000 | AG10: 4000 | AH10: 4000 | AI10: 4000 | AJ10: 4000 | AK10: 4000 | AL10: 4000 | AM10: 7000 | AN10: 7000 | AO10: 7000 | AP10: 7000 | AQ10: 7000 | AR10: 7000 | AS10: 10000 | AT10: 10000 | AU10: 10000 | AV10: 10000 | AW10: 10000 | AX10: 10000 | AY10: 15000 | AZ10: 15000 | BA10: 15000 | BB10: 15000 | BC10: 15000 | BD10: 15000 | BE10: 20000 | BF10: 20000 | BG10: 20000 | BH10: 20000 | BI10: 20000 | BJ10: 20000
B11: =Config!$B$16 -> Conseil Personnalisé | H11: 600 | I11: 600 | J11: 600 | K11: 600 | L11: 600 | M11: 600 | N11: 600 | O11: 900 | P11: 900 | Q11: 900 | R11: 900 | S11: 900 | T11: 900 | U11: 900 | V11: 900 | W11: 900 | X11: 900 | Y11: 900 | Z11: 900 | AA11: 1500 | AB11: 1500 | AC11: 1500 | AD11: 1500 | AE11: 1500 | AF11: 1500 | AG11: 1500 | AH11: 1500 | AI11: 1500 | AJ11: 1500 | AK11: 1500 | AL11: 1500 | AM11: 1500 | AN11: 1500 | AO11: 1500 | AP11: 1500 | AQ11: 1500 | AR11: 1500 | AS11: 1500 | AT11: 1500 | AU11: 1500 | AV11: 1500 | AW11: 1500 | AX11: 1500 | AY11: 1500 | AZ11: 1500 | BA11: 1500 | BB11: 1500 | BC11: 1500 | BD11: 1500 | BE11: 1500 | BF11: 1500 | BG11: 1500 | BH11: 1500 | BI11: 1500 | BJ11: 1500
B12: =Config!$B$17 -> Plateforme de Marché en Ligne
B13: =Config!$B$18 -> Formations et Ateliers
B14: =Config!$B$19 -> Commission ventes 2%
B15: =Config!$B$20
B16: =Config!$B$21
B17: =Config!$B$22
B18: =Config!$B$23
B19: =Config!$B$24
B20: =Config!$B$25

Sheet Synthèse
B2: SYNTHESE
B5: Note : Cette synthèse permet d'analyser son projet avec une vision centralisée. Tout est calculé automatiquement.
B7: Chiffre d'affaires et résultats prévisionnels (en € HT) | J7: Trésorerie et BFR sur 5 ans
B21: Point mort annuel (moyen) (en € HT)
D23: Année 1 | E23: Année 2 | F23: Année 3 | G23: Année 4 | H23: Année 5
B24: Point mort | D24: =IF('Comptes de résultats'!C9<>0,IF('Comptes de résultats'!C12/'Comptes de résultats'!C9<>0,('Comptes de résultats'!C15+'Comptes de résultats'!C19+'Comptes de résultats'!C21+'Comptes de résultats'!C25+'Comptes de résultats'!C29-'Comptes de résultats'!C20)/('Comptes de résultats'!C12/'Comptes de résultats'!C9),0),0) -> 0 | E24: =IF('Comptes de résultats'!D9<>0,IF('Comptes de résultats'!D12/'Comptes de résultats'!D9<>0,('Comptes de résultats'!D15+'Comptes de résultats'!D19+'Comptes de résultats'!D21+'Comptes de résultats'!D25+'Comptes de résultats'!D29-'Comptes de résultats'!D20)/('Comptes de résultats'!D12/'Comptes de résultats'!D9),0),0) -> 0 | F24: =IF('Comptes de résultats'!E9<>0,IF('Comptes de résultats'!E12/'Comptes de résultats'!E9<>0,('Comptes de résultats'!E15+'Comptes de résultats'!E19+'Comptes de résultats'!E21+'Comptes de résultats'!E25+'Comptes de résultats'!E29-'Comptes de résultats'!E20)/('Comptes de résultats'!E12/'Comptes de résultats'!E9),0),0) -> 0 | G24: =IF('Comptes de résultats'!F9<>0,IF('Comptes de résultats'!F12/'Comptes de résultats'!F9<>0,('Comptes de résultats'!F15+'Comptes de résultats'!F19+'Comptes de résultats'!F21+'Comptes de résultats'!F25+'Comptes de résultats'!F29-'Comptes de résultats'!F20)/('Comptes de résultats'!F12/'Comptes de résultats'!F9),0),0) -> 0 | H24: =IF('Comptes de résultats'!G9<>0,IF('Comptes de résultats'!G12/'Comptes de résultats'!G9<>0,('Comptes de résultats'!G15+'Comptes de résultats'!G19+'Comptes de résultats'!G21+'Comptes de résultats'!G25+'Comptes de résultats'!G29-'Comptes de résultats'!G20)/('Comptes de résultats'!G12/'Comptes de résultats'!G9),0),0) -> 0
B26: Note d'aide à l'analyse : Le graphique du "chiffre d'affaires et résultats prévisionnels" vous permet de visualiser l'évolution prévisionnelle du CA et du résultat net. Evaluez le volume et la croissance du CA et du résultat au regard de vos objectifs et de vos moyens. Le point mort est le seuil de CA à partir duquel l'entreprise est "rentable" pour un niveau de charges fixes (salaires, charge externes, ...). Comparez votre CA et le point mort année par année. Votre objectif doit être, à court ou moyen terme, d'obtenir un CA supérieur au point mort. Le graphique "Trésorerie et BFR" vous permet de visualiser et d'analyser l'évolution de la trésorerie et du BFR sur 5 ans. Il est impératif que la trésorerie soit toujours positive. Concernant le BFR, si il est positif et qu'il augmente cela représente une augmentation de besoin en financement alors que si il est négatif et diminue dans le temps, il s'agira d'une source de financement. Attention à bien en analyser les fluctuations et les impacts sur les besoins en financement.

Sheet Trésorerie
B2: TRESORERIE
B5: Note : Renseignez ici les encaissements liés à l'apport et augmentation en capital, de comptes courants, prêts remboursables et prêts bancaires, ainsi que les décaissements liés aux remboursements des comptes courants et des prêts (en fonction de vos échéanciers).
C7: Année 1 | O7: Année 2 | AA7: Année 3 | AM7: Année 4 | AY7: Année 5
C8: =Config!$C$7 -> 45505 | D8: =DATE(YEAR(C8),MONTH(C8)+1,DAY(C8)) -> 45536 | E8: =DATE(YEAR(D8),MONTH(D8)+1,DAY(D8)) -> 45566 | F8: =DATE(YEAR(E8),MONTH(E8)+1,DAY(E8)) -> 45597 | G8: =DATE(YEAR(F8),MONTH(F8)+1,DAY(F8)) -> 45627 | H8: =DATE(YEAR(G8),MONTH(G8)+1,DAY(G8)) -> 45658 | I8: =DATE(YEAR(H8),MONTH(H8)+1,DAY(H8)) -> 45689 | J8: =DATE(YEAR(I8),MONTH(I8)+1,DAY(I8)) -> 45717 | K8: =DATE(YEAR(J8),MONTH(J8)+1,DAY(J8)) -> 45748 | ... BJ8: =DATE(YEAR(BI8),MONTH(BI8)+1,DAY(BI8)) -> 47300
B10: Solde de début de mois | C10: 0 | D10: =C71 -> -7524676.3 | E10: =D71 -> -14317976 | F10: =E71 -> -21111276 | G10: =F71 -> -27904576 | H10: =G71 -> -34697875 | I10: =H71 -> -50416675 | J10: =I71 -> -57735475 | K10: =J71 -> -66254275 | ... BJ10: =BI71 -> -1475502012
B12: Encaissements
B14: Exploitation
B15: Chiffre d'affaires encaissé | C15: ='Commandes - Calculs auto'!C22 -> 0 | D15: ='Commandes - Calculs auto'!D22 -> 0 | E15: ='Commandes - Calculs auto'!E22 -> 1700000 | F15: ='Commandes - Calculs auto'!F22 -> 3250000 | G15: ='Commandes - Calculs auto'!G22 -> 6125000 | H15: ='Commandes - Calculs auto'!H22 -> 21200000 | I15: ='Commandes - Calculs auto'!I22 -> 28850000 | J15: ='Commandes - Calculs auto'!J22 -> 34015000 | ... BJ15: ='Commandes - Calculs auto'!BJ22 -> 968000000
B16: TVA encaissée | C16: =TVA!C43 -> 0 | D16: =TVA!D43 -> 0 | E16: =TVA!E43 -> 340000 | F16: =TVA!F43 -> 650000 | G16: =TVA!G43 -> 1225000 | H16: =TVA!H43 -> 4240000 | I16: =TVA!I43 -> 5770000 | J16: =TVA!J43 -> 6803000 | ... BJ16: =TVA!BJ43 -> 193600000
B17: Remboursement TVA | D17: =C48 -> 731376.54 | E17: =D48 -> 731376.54 | F17: =E48 -> 1071376.5 | G17: =F48 -> 1381376.5 | H17: =G48 -> 1956376.5 | I17: =H48 -> 6171376.5 | J17: =I48 -> 6501376.5 | K17: =J48 -> 7534376.5 | ... BJ17: =BI48 -> 2.0193167e+08
B19: Hors exploitation
B20: Capital fondateurs
B21: Capital investisseurs
B22: Prêts bancaires Court Terme
B23: Prêts bancaires Moyen/Long Terme
B24: Subventions (total) | C24: =SUM(C25:C28) -> 0 | D24: =SUM(D25:D28) -> 0 | E24: =SUM(E25:E28) -> 0 | F24: =SUM(F25:F28) -> 0 | G24: =SUM(G25:G28) -> 0 | H24: =SUM(H25:H28) -> 0 | I24: =SUM(I25:I28) -> 0 | J24: =SUM(J25:J28) -> 0 | ... BJ24: =SUM(BJ25:BJ28) -> 0
B25: Subvention 1
B26: Subvention 2
B27: Subvention 3
B28: Autres subventions
B29: Comptes courants (total) | C29: =SUM(C30:C33) -> 0 | D29: =SUM(D30:D33) -> 0 | E29: =SUM(E30:E33) -> 0 | F29: =SUM(F30:F33) -> 0 | G29: =SUM(G30:G33) -> 0 | H29: =SUM(H30:H33) -> 0 | I29: =SUM(I30:I33) -> 0 | J29: =SUM(J30:J33) -> 0 | ... BJ29: =SUM(BJ30:BJ33) -> 0
B30: Compte courant 1
B31: Compte courant 2
B32: Compte courant 3
B33: Autres comptes courants
B34: Avances remboursables (total) | C34: =SUM(C35:C38) -> 0 | D34: =SUM(D35:D38) -> 0 | E34: =SUM(E35:E38) -> 0 | F34: =SUM(F35:F38) -> 0 | G34: =SUM(G35:G38) -> 0 | H34: =SUM(H35:H38) -> 0 | I34: =SUM(I35:I38) -> 0 | J34: =SUM(J35:J38) -> 0 | ... BJ34: =SUM(BJ35:BJ38) -> 0
B35: Avances remboursables 1
B36: Avances remboursables 2
B37: Avances remboursables 3
B38: Autres avances remboursables
B40: Total des encaissements mensuels | C40: =SUM(C15:C17)+SUM(C20:C23)+C24+C29+C34 -> 0 | D40: =SUM(D15:D17)+SUM(D20:D23)+D24+D29+D34 -> 731376.54 | E40: =SUM(E15:E17)+SUM(E20:E23)+E24+E29+E34 -> 2771376.5 | F40: =SUM(F15:F17)+SUM(F20:F23)+F24+F29+F34 -> 4971376.5 | G40: =SUM(G15:G17)+SUM(G20:G23)+G24+G29+G34 -> 8731376.5 | H40: =SUM(H15:H17)+SUM(H20:H23)+H24+H29+H34 -> 27396377 | I40: =SUM(I15:I17)+SUM(I20:I23)+I24+I29+I34 -> 40791377 | J40: =SUM(J15:J17)+SUM(J20:J23)+J24+J29+J34 -> 47319377 | ... BJ40: =SUM(BJ15:BJ17)+SUM(BJ20:BJ23)+BJ24+BJ29+BJ34 -> 1363531667
B42: Décaissements
B44: Exploitation
B45: Variation de stocks
B46: Achats et services décaissés | C46: ='Charges variables'!C22 -> 0 | D46: ='Charges variables'!D22 -> 0 | E46: ='Charges variables'!E22 -> 1700000 | F46: ='Charges variables'!F22 -> 3250000 | G46: ='Charges variables'!G22 -> 6125000 | H46: ='Charges variables'!H22 -> 21200000 | I46: ='Charges variables'!I22 -> 28850000 | J46: ='Charges variables'!J22 -> 34015000 | ... BJ46: ='Charges variables'!BJ22 -> 968000000
B47: Autres charges externes | C47: ='Charges externes'!I29 -> 3656882.7 | D47: ='Charges externes'!J29 -> 3656882.7 | E47: ='Charges externes'!K29 -> 3656882.7 | F47: ='Charges externes'!L29 -> 3656882.7 | G47: ='Charges externes'!M29 -> 3656882.7 | H47: ='Charges externes'!N29 -> 3656882.7 | I47: ='Charges externes'!O29 -> 3656882.7 | J47: ='Charges externes'!P29 -> 3656882.7 | ... BJ47: ='Charges externes'!BP29 -> 41658333
B48: TVA décaissée | C48: =TVA!C24 -> 731376.54 | D48: =TVA!D24 -> 731376.54 | E48: =TVA!E24 -> 1071376.5 | F48: =TVA!F24 -> 1381376.5 | G48: =TVA!G24 -> 1956376.5 | H48: =TVA!H24 -> 6171376.5 | I48: =TVA!I24 -> 6501376.5 | J48: =TVA!J24 -> 7534376.5 | ... BJ48: =TVA!BJ24 -> 2.0193167e+08
B49: TVA reversée | D49: =C16 -> 0 | E49: =D16 -> 0 | F49: =E16 -> 340000 | G49: =F16 -> 650000 | H49: =G16 -> 1225000 | I49: =H16 -> 4240000 | J49: =I16 -> 5770000 | K49: =J16 -> 6803000 | ... BJ49: =BI16 -> 193600000
B50: Charges de personnel | C50: ='Personnel - Calculs auto'!B81 -> 3094000 | D50: ='Personnel - Calculs auto'!C81 -> 3094000 | E50: ='Personnel - Calculs auto'!D81 -> 3094000 | F50: ='Personnel - Calculs auto'!E81 -> 3094000 | G50: ='Personnel - Calculs auto'!F81 -> 3094000 | H50: ='Personnel - Calculs auto'!G81 -> 4819500 | I50: ='Personnel - Calculs auto'!H81 -> 4819500 | J50: ='Personnel - Calculs auto'!I81 -> 4819500 | ... N50: ='Personnel - Calculs auto'!M81 -> 4819500 | O50: ='Personnel - Calculs auto'!O81 -> 8726666.7 | P50: ='Personnel - Calculs auto'!P81 -> 8726666.7 | Q50: ='Personnel - Calculs auto'!Q81 -> 8726666.7 | R50: ='Personnel - Calculs auto'!R81 -> 8726666.7 | S50: ='Personnel - Calculs auto'!S81 -> 8726666.7 | T50: ='Personnel - Calculs auto'!T81 -> 9678666.7 | U50: ='Personnel - Calculs auto'!U81 -> 9678666.7 | V50: ='Personnel - Calculs auto'!V81 -> 9678666.7 | ... Z50: ='Personnel - Calculs auto'!Z81 -> 9678666.7 | AA50: ='Personnel - Calculs auto'!$AB$81/6 -> 16798833 | AB50: ='Personnel - Calculs auto'!$AB$81/6 -> 16798833 | AC50: ='Personnel - Calculs auto'!$AB$81/6 -> 16798833 | AD50: ='Personnel - Calculs auto'!$AB$81/6 -> 16798833 | AE50: ='Personnel - Calculs auto'!$AB$81/6 -> 16798833 | AF50: ='Personnel - Calculs auto'!$AB$81/6 -> 16798833 | AG50: ='Personnel - Calculs auto'!$AC$81/6 -> 18345833 | AH50: ='Personnel - Calculs auto'!$AC$81/6 -> 18345833 | AI50: ='Personnel - Calculs auto'!$AC$81/6 -> 18345833 | AJ50: ='Personnel - Calculs auto'!$AC$81/6 -> 18345833 | AK50: ='Personnel - Calculs auto'!$AC$81/6 -> 18345833 | AL50: ='Personnel - Calculs auto'!$AC$81/6 -> 18345833 | AM50: ='Personnel - Calculs auto'!$AE$81/6 -> 0 | AN50: ='Personnel - Calculs auto'!$AE$81/6 -> 0 | AO50: ='Personnel - Calculs auto'!$AE$81/6 -> 0 | AP50: ='Personnel - Calculs auto'!$AE$81/6 -> 0 | AQ50: ='Personnel - Calculs auto'!$AE$81/6 -> 0 | AR50: ='Personnel - Calculs auto'!$AE$81/6 -> 0 | AS50: ='Personnel - Calculs auto'!$AF$81/6 -> 0 | AT50: ='Personnel - Calculs auto'!$AF$81/6 -> 0 | AU50: ='Personnel - Calculs auto'!$AF$81/6 -> 0 | AV50: ='Personnel - Calculs auto'!$AF$81/6 -> 0 | AW50: ='Personnel - Calculs auto'!$AF$81/6 -> 0 | AX50: ='Personnel - Calculs auto'!$AF$81/6 -> 0 | AY50: ='Personnel - Calculs auto'!$AH$81/6 -> 0 | AZ50: ='Personnel - Calculs auto'!$AH$81/6 -> 0 | BA50: ='Personnel - Calculs auto'!$AH$81/6 -> 0 | BB50: ='Personnel - Calculs auto'!$AH$81/6 -> 0 | BC50: ='Personnel - Calculs auto'!$AH$81/6 -> 0 | BD50: ='Personnel - Calculs auto'!$AH$81/6 -> 0 | BE50: ='Personnel - Calculs auto'!$AI$81/6 -> 0 | BF50: ='Personnel - Calculs auto'!$AI$81/6 -> 0 | BG50: ='Personnel - Calculs auto'!$AI$81/6 -> 0 | BH50: ='Personnel - Calculs auto'!$AI$81/6 -> 0 | BI50: ='Personnel - Calculs auto'!$AI$81/6 -> 0 | BJ50: ='Personnel - Calculs auto'!$AI$81/6 -> 0
B51: Impôts et taxes | C51: ='Impôts et taxes'!$C$14/12 -> 42417.049 | D51: ='Impôts et taxes'!$C$14/12 -> 42417.049 | E51: ='Impôts et taxes'!$C$14/12 -> 42417.049 | F51: ='Impôts et taxes'!$C$14/12 -> 42417.049 | G51: ='Impôts et taxes'!$C$14/12 -> 42417.049 | H51: ='Impôts et taxes'!$C$14/12 -> 42417.049 | I51: ='Impôts et taxes'!$C$14/12 -> 42417.049 | J51: ='Impôts et taxes'!$C$14/12 -> 42417.049 | ... N51: ='Impôts et taxes'!$C$14/12 -> 42417.049 | O51: ='Impôts et taxes'!$D$14/12 -> 113619.93 | P51: ='Impôts et taxes'!$D$14/12 -> 113619.93 | Q51: ='Impôts et taxes'!$D$14/12+'Comptes de résultats'!C34+(0.25*'Comptes de résultats'!C34) -> 113619.93 | R51: ='Impôts et taxes'!$D$14/12 -> 113619.93 | S51: ='Impôts et taxes'!$D$14/12 -> 113619.93 | T51: ='Impôts et taxes'!$D$14/12+(0.25*'Comptes de résultats'!C34) -> 113619.93 | U51: ='Impôts et taxes'!$D$14/12 -> 113619.93 | V51: ='Impôts et taxes'!$D$14/12 -> 113619.93 | W51: ='Impôts et taxes'!$D$14/12+(0.25*'Comptes de résultats'!C34) -> 113619.93 | X51: ='Impôts et taxes'!$D$14/12 -> 113619.93 | Y51: ='Impôts et taxes'!$D$14/12 -> 113619.93 | Z51: ='Impôts et taxes'!$D$14/12+(0.25*'Comptes de résultats'!C34) -> 113619.93 | AA51: ='Impôts et taxes'!$E$14/12 -> 331145.88 | AB51: ='Impôts et taxes'!$E$14/12 -> 331145.88 | AC51: ='Impôts et taxes'!$E$14/12+'Comptes de résultats'!D34-'Comptes de résultats'!C34+(0.25*'Comptes de résultats'!D34) -> 331145.88 | AD51: ='Impôts et taxes'!$E$14/12 -> 331145.88 | AE51: ='Impôts et taxes'!$E$14/12 -> 331145.88 | AF51: ='Impôts et taxes'!$E$14/12+(0.25*'Comptes de résultats'!D34) -> 331145.88 | AG51: ='Impôts et taxes'!$E$14/12 -> 331145.88 | AH51: ='Impôts et taxes'!$E$14/12 -> 331145.88 | AI51: ='Impôts et taxes'!$E$14/12+(0.25*'Comptes de résultats'!D34) -> 331145.88 | AJ51: ='Impôts et taxes'!$E$14/12 -> 331145.88 | AK51: ='Impôts et taxes'!$E$14/12 -> 331145.88 | AL51: ='Impôts et taxes'!$E$14/12+(0.25*'Comptes de résultats'!D34) -> 331145.88 | AM51: ='Impôts et taxes'!$F$14/12 -> 404529.41 | AN51: ='Impôts et taxes'!$F$14/12 -> 404529.41 | AO51: ='Impôts et taxes'!$F$14/12+'Comptes de résultats'!E34-'Comptes de résultats'!D34+(0.25*'Comptes de résultats'!E34) -> 404529.41 | AP51: ='Impôts et taxes'!$F$14/12 -> 404529.41 | AQ51: ='Impôts et taxes'!$F$14/12 -> 404529.41 | AR51: ='Impôts et taxes'!$F$14/12+(0.25*'Comptes de résultats'!E34) -> 404529.41 | AS51: ='Impôts et taxes'!$F$14/12 -> 404529.41 | AT51: ='Impôts et taxes'!$F$14/12 -> 404529.41 | AU51: ='Impôts et taxes'!$F$14/12+(0.25*'Comptes de résultats'!E34) -> 404529.41 | AV51: ='Impôts et taxes'!$F$14/12 -> 404529.41 | AW51: ='Impôts et taxes'!$F$14/12 -> 404529.41 | AX51: ='Impôts et taxes'!$F$14/12+(0.25*'Comptes de résultats'!E34) -> 404529.41 | AY51: ='Impôts et taxes'!$G$14/12 -> 772216.91 | AZ51: ='Impôts et taxes'!$G$14/12 -> 772216.91 | BA51: ='Impôts et taxes'!$G$14/12+'Comptes de résultats'!F34-'Comptes de résultats'!E34+(0.25*'Comptes de résultats'!F34) -> 772216.91 | BB51: ='Impôts et taxes'!$G$14/12 -> 772216.91 | BC51: ='Impôts et taxes'!$G$14/12 -> 772216.91 | BD51: ='Impôts et taxes'!$G$14/12+(0.25*'Comptes de résultats'!F34) -> 772216.91 | BE51: ='Impôts et taxes'!$G$14/12 -> 772216.91 | BF51: ='Impôts et taxes'!$G$14/12 -> 772216.91 | BG51: ='Impôts et taxes'!$G$14/12+(0.25*'Comptes de résultats'!F34) -> 772216.91 | BH51: ='Impôts et taxes'!$G$14/12 -> 772216.91 | BI51: ='Impôts et taxes'!$G$14/12 -> 772216.91 | BJ51: ='Impôts et taxes'!$G$14/12+(0.25*'Comptes de résultats'!F34) -> 772216.91
B53: Hors exploitation
B54: Investissements | C54: =Investissements!C28-Investissements!C9-C55 -> 0 | D54: =Investissements!D28-Investissements!D9-D55 -> 0 | E54: =Investissements!E28-Investissements!E9-E55 -> 0 | F54: =Investissements!F28-Investissements!F9-F55 -> 0 | G54: =Investissements!G28-Investissements!G9-G55 -> 0 | H54: =Investissements!H28-Investissements!H9-H55 -> 6000000 | I54: =Investissements!I28-Investissements!I9-I55 -> 0 | J54: =Investissements!J28-Investissements!J9-J55 -> 0 | ... N54: =Investissements!N28-Investissements!N9-N55 -> 0 | O54: =Investissements!P28-Investissements!P9-O55 -> 6000000 | P54: =Investissements!Q28-Investissements!Q9-P55 -> 0 | Q54: =Investissements!R28-Investissements!R9-Q55 -> 0 | R54: =Investissements!S28-Investissements!S9-R55 -> 0 | S54: =Investissements!T28-Investissements!T9-S55 -> 0 | T54: =Investissements!U28-Investissements!U9-T55 -> 0 | U54: =Investissements!V28-Investissements!V9-U55 -> 0 | V54: =Investissements!W28-Investissements!W9-V55 -> 0 | ... Z54: =Investissements!AA28-Investissements!AA9-Z55 -> 0 | AA54: =Investissements!AC28-Investissements!AC9-AA55 -> 8000000 | AG54: =Investissements!AD28-Investissements!AD9-AG55 -> 0 | AM54: =Investissements!AF28-Investissements!AF9-AM55 -> 0 | AS54: =Investissements!AG28-Investissements!AG9-AS55 -> 0 | AY54: =Investissements!AI28-Investissements!AI9-AY55 -> 0 | BE54: =Investissements!AJ28-Investissements!AJ9-BE55 -> 0
B55: Investissement par crédit bail | C55: =SUMPRODUCT((Investissements!C9:C27)*(Investissements!$AS9:$AS27)) -> 0 | D55: =SUMPRODUCT((Investissements!D9:D27)*(Investissements!$AS9:$AS27)) -> 0 | E55: =SUMPRODUCT((Investissements!E9:E27)*(Investissements!$AS9:$AS27)) -> 0 | F55: =SUMPRODUCT((Investissements!F9:F27)*(Investissements!$AS9:$AS27)) -> 0 | G55: =SUMPRODUCT((Investissements!G9:G27)*(Investissements!$AS9:$AS27)) -> 0 | H55: =SUMPRODUCT((Investissements!H9:H27)*(Investissements!$AS9:$AS27)) -> 0 | I55: =SUMPRODUCT((Investissements!I9:I27)*(Investissements!$AS9:$AS27)) -> 0 | J55: =SUMPRODUCT((Investissements!J9:J27)*(Investissements!$AS9:$AS27)) -> 0 | ... N55: =SUMPRODUCT((Investissements!N9:N27)*(Investissements!$AS9:$AS27)) -> 0 | O55: =SUMPRODUCT((Investissements!P9:P27)*(Investissements!$AS9:$AS27)) -> 0 | P55: =SUMPRODUCT((Investissements!Q9:Q27)*(Investissements!$AS9:$AS27)) -> 0 | Q55: =SUMPRODUCT((Investissements!R9:R27)*(Investissements!$AS9:$AS27)) -> 0 | R55: =SUMPRODUCT((Investissements!S9:S27)*(Investissements!$AS9:$AS27)) -> 0 | S55: =SUMPRODUCT((Investissements!T9:T27)*(Investissements!$AS9:$AS27)) -> 0 | T55: =SUMPRODUCT((Investissements!U9:U27)*(Investissements!$AS9:$AS27)) -> 0 | U55: =SUMPRODUCT((Investissements!V9:V27)*(Investissements!$AS9:$AS27)) -> 0 | V55: =SUMPRODUCT((Investissements!W9:W27)*(Investissements!$AS9:$AS27)) -> 0 | ... Z55: =SUMPRODUCT((Investissements!AA9:AA27)*(Investissements!$AS9:$AS27)) -> 0 | AA55: =SUMPRODUCT((Investissements!AC9:AC27)*(Investissements!$AS9:$AS27)) -> 0 | AG55: =SUMPRODUCT((Investissements!AD9:AD27)*(Investissements!$AS9:$AS27)) -> 0 | AM55: =SUMPRODUCT((Investissements!AF9:AF27)*(Investissements!$AS9:$AS27)) -> 0 | AS55: =SUMPRODUCT((Investissements!AG9:AG27)*(Investissements!$AS9:$AS27)) -> 0 | AY55: =SUMPRODUCT((Investissements!AI9:AI27)*(Investissements!$AS9:$AS27)) -> 0 | BE55: =SUMPRODUCT((Investissements!AJ9:AJ27)*(Investissements!$AS9:$AS27)) -> 0
B56: Remboursement prêts bancaires CT | C56: {=-PMT(Config!$C$99/12,Config!$C$101,SUM(INDEX($C22:$BJ22,,IF((COLUMN(C$56)-COLUMN($C$56)+1)>Config!$C$101,(COLUMN(C$56)-COLUMN($C$56)+1)-Config!$C$101,0)+1):INDEX($C22:$BJ22,,COLUMN(C$56)-COLUMN($C$56)+1)),,)} -> 0 | D56: {=-PMT(Config!$C$99/12,Config!$C$101,SUM(INDEX($C22:$BJ22,,IF((COLUMN(D$56)-COLUMN($C$56)+1)>Config!$C$101,(COLUMN(D$56)-COLUMN($C$56)+1)-Config!$C$101,0)+1):INDEX($C22:$BJ22,,COLUMN(D$56)-COLUMN($C$56)+1)),,)} -> 0 | E56: {=-PMT(Config!$C$99/12,Config!$C$101,SUM(INDEX($C22:$BJ22,,IF((COLUMN(E$56)-COLUMN($C$56)+1)>Config!$C$101,(COLUMN(E$56)-COLUMN($C$56)+1)-Config!$C$101,0)+1):INDEX($C22:$BJ22,,COLUMN(E$56)-COLUMN($C$56)+1)),,)} -> 0 | F56: {=-PMT(Config!$C$99/12,Config!$C$101,SUM(INDEX($C22:$BJ22,,IF((COLUMN(F$56)-COLUMN($C$56)+1)>Config!$C$101,(COLUMN(F$56)-COLUMN($C$56)+1)-Config!$C$101,0)+1):INDEX($C22:$BJ22,,COLUMN(F$56)-COLUMN($C$56)+1)),,)} -> 0 | G56: {=-PMT(Config!$C$99/12,Config!$C$101,SUM(INDEX($C22:$BJ22,,IF((COLUMN(G$56)-COLUMN($C$56)+1)>Config!$C$101,(COLUMN(G$56)-COLUMN($C$56)+1)-Config!$C$101,0)+1):INDEX($C22:$BJ22,,COLUMN(G$56)-COLUMN($C$56)+1)),,)} -> 0 | H56: {=-PMT(Config!$C$99/12,Config!$C$101,SUM(INDEX($C22:$BJ22,,IF((COLUMN(H$56)-COLUMN($C$56)+1)>Config!$C$101,(COLUMN(H$56)-COLUMN($C$56)+1)-Config!$C$101,0)+1):INDEX($C22:$BJ22,,COLUMN(H$56)-COLUMN($C$56)+1)),,)} -> 0 | I56: {=-PMT(Config!$C$99/12,Config!$C$101,SUM(INDEX($C22:$BJ22,,IF((COLUMN(I$56)-COLUMN($C$56)+1)>Config!$C$101,(COLUMN(I$56)-COLUMN($C$56)+1)-Config!$C$101,0)+1):INDEX($C22:$BJ22,,COLUMN(I$56)-COLUMN($C$56)+1)),,)} -> 0 | J56: {=-PMT(Config!$C$99/12,Config!$C$101,SUM(INDEX($C22:$BJ22,,IF((COLUMN(J$56)-COLUMN($C$56)+1)>Config!$C$101,(COLUMN(J$56)-COLUMN($C$56)+1)-Config!$C$101,0)+1):INDEX($C22:$BJ22,,COLUMN(J$56)-COLUMN($C$56)+1)),,)} -> 0 | ... BJ56: {=-PMT(Config!$C$99/12,Config!$C$101,SUM(INDEX($C22:$BJ22,,IF((COLUMN(BJ$56)-COLUMN($C$56)+1)>Config!$C$101,(COLUMN(BJ$56)-COLUMN($C$56)+1)-Config!$C$101,0)+1):INDEX($C22:$BJ22,,COLUMN(BJ$56)-COLUMN($C$56)+1)),,)} -> 0
B57: Remboursement prêts bancaires MT/LT | C57: {=-PMT(Config!$D$99/12,Config!$D$101,SUM(INDEX($C23:$BJ23,,IF((COLUMN(C$57)-COLUMN($C$57)+1)>Config!$D$101,(COLUMN(C$57)-COLUMN($C$57)+1)-Config!$D$101,0)+1):INDEX($C23:$BJ23,,COLUMN(C$57)-COLUMN($C$57)+1)),,)} -> 0 | D57: {=-PMT(Config!$D$99/12,Config!$D$101,SUM(INDEX($C23:$BJ23,,IF((COLUMN(D$57)-COLUMN($C$57)+1)>Config!$D$101,(COLUMN(D$57)-COLUMN($C$57)+1)-Config!$D$101,0)+1):INDEX($C23:$BJ23,,COLUMN(D$57)-COLUMN($C$57)+1)),,)} -> 0 | E57: {=-PMT(Config!$D$99/12,Config!$D$101,SUM(INDEX($C23:$BJ23,,IF((COLUMN(E$57)-COLUMN($C$57)+1)>Config!$D$101,(COLUMN(E$57)-COLUMN($C$57)+1)-Config!$D$101,0)+1):INDEX($C23:$BJ23,,COLUMN(E$57)-COLUMN($C$57)+1)),,)} -> 0 | F57: {=-PMT(Config!$D$99/12,Config!$D$101,SUM(INDEX($C23:$BJ23,,IF((COLUMN(F$57)-COLUMN($C$57)+1)>Config!$D$101,(COLUMN(F$57)-COLUMN($C$57)+1)-Config!$D$101,0)+1):INDEX($C23:$BJ23,,COLUMN(F$57)-COLUMN($C$57)+1)),,)} -> 0 | G57: {=-PMT(Config!$D$99/12,Config!$D$101,SUM(INDEX($C23:$BJ23,,IF((COLUMN(G$57)-COLUMN($C$57)+1)>Config!$D$101,(COLUMN(G$57)-COLUMN($C$57)+1)-Config!$D$101,0)+1):INDEX($C23:$BJ23,,COLUMN(G$57)-COLUMN($C$57)+1)),,)} -> 0 | H57: {=-PMT(Config!$D$99/12,Config!$D$101,SUM(INDEX($C23:$BJ23,,IF((COLUMN(H$57)-COLUMN($C$57)+1)>Config!$D$101,(COLUMN(H$57)-COLUMN($C$57)+1)-Config!$D$101,0)+1):INDEX($C23:$BJ23,,COLUMN(H$57)-COLUMN($C$57)+1)),,)} -> 0 | I57: {=-PMT(Config!$D$99/12,Config!$D$101,SUM(INDEX($C23:$BJ23,,IF((COLUMN(I$57)-COLUMN($C$57)+1)>Config!$D$101,(COLUMN(I$57)-COLUMN($C$57)+1)-Config!$D$101,0)+1):INDEX($C23:$BJ23,,COLUMN(I$57)-COLUMN($C$57)+1)),,)} -> 0 | J57: {=-PMT(Config!$D$99/12,Config!$D$101,SUM(INDEX($C23:$BJ23,,IF((COLUMN(J$57)-COLUMN($C$57)+1)>Config!$D$101,(COLUMN(J$57)-COLUMN($C$57)+1)-Config!$D$101,0)+1):INDEX($C23:$BJ23,,COLUMN(J$57)-COLUMN($C$57)+1)),,)} -> 0 | ... BJ57: {=-PMT(Config!$D$99/12,Config!$D$101,SUM(INDEX($C23:$BJ23,,IF((COLUMN(BJ$57)-COLUMN($C$57)+1)>Config!$D$101,(COLUMN(BJ$57)-COLUMN($C$57)+1)-Config!$D$101,0)+1):INDEX($C23:$BJ23,,COLUMN(BJ$57)-COLUMN($C$57)+1)),,)} -> 0
B58: Remboursements comptes courants (total) | C58: =SUM(C59:C62) -> 0 | D58: =SUM(D59:D62) -> 0 | E58: =SUM(E59:E62) -> 0 | F58: =SUM(F59:F62) -> 0 | G58: =SUM(G59:G62) -> 0 | H58: =SUM(H59:H62) -> 0 | I58: =SUM(I59:I62) -> 0 | J58: =SUM(J59:J62) -> 0 | ... BJ58: =SUM(BJ59:BJ62) -> 0
B59: =B30 -> Compte courant 1
B60: =B31 -> Compte courant 2
B61: =B32 -> Compte courant 3
B62: =B33 -> Autres comptes courants
B63: Remboursements avances remboursables (total) | C63: =SUM(C64:C67) -> 0 | D63: =SUM(D64:D67) -> 0 | E63: =SUM(E64:E67) -> 0 | F63: =SUM(F64:F67) -> 0 | G63: =SUM(G64:G67) -> 0 | H63: =SUM(H64:H67) -> 0 | I63: =SUM(I64:I67) -> 0 | J63: =SUM(J64:J67) -> 0 | ... BJ63: =SUM(BJ64:BJ67) -> 0
B64: =B35 -> Avances remboursables 1
B65: =B36 -> Avances remboursables 2
B66: =B37 -> Avances remboursables 3
B67: =B38 -> Autres avances remboursables
B69: Total des décaissements mensuels | C69: =SUM(C45:C51)+SUM(C54:C58)+C63 -> 7524676.3 | D69: =SUM(D45:D51)+SUM(D54:D58)+D63 -> 7524676.3 | E69: =SUM(E45:E51)+SUM(E54:E58)+E63 -> 9564676.3 | F69: =SUM(F45:F51)+SUM(F54:F58)+F63 -> 11764676 | G69: =SUM(G45:G51)+SUM(G54:G58)+G63 -> 15524676 | H69: =SUM(H45:H51)+SUM(H54:H58)+H63 -> 43115176 | I69: =SUM(I45:I51)+SUM(I54:I58)+I63 -> 48110176 | J69: =SUM(J45:J51)+SUM(J54:J58)+J63 -> 55838176 | ... BJ69: =SUM(BJ45:BJ51)+SUM(BJ54:BJ58)+BJ63 -> 1405962217
B71: Solde de fin de mois | C71: =C10+C40-C69 -> -7524676.3 | D71: =D10+D40-D69 -> -14317976 | E71: =E10+E40-E69 -> -21111276 | F71: =F10+F40-F69 -> -27904576 | G71: =G10+G40-G69 -> -34697875 | H71: =H10+H40-H69 -> -50416675 | I71: =I10+I40-I69 -> -57735475 | J71: =J10+J40-J69 -> -66254275 | ... BJ71: =BJ10+BJ40-BJ69 -> -1517932562

Sheet Pilotage
B2: OUTIL DE PILOTAGE
B5: Note : Ce tableau sur 12 mois est à utiliser comme un exemple de base d'outil de pilotage pour l'entrepreneur qu'il pourra s'approprier et adapter aux besoins de gestion propre à son entreprise.
B7: Intitulés | E7: =Config!$C$7 -> 45505 | F7: =DATE(YEAR(E7),MONTH(E7)+1,DAY(E7)) -> 45536 | G7: =DATE(YEAR(F7),MONTH(F7)+1,DAY(F7)) -> 45566 | H7: =DATE(YEAR(G7),MONTH(G7)+1,DAY(G7)) -> 45597 | I7: =DATE(YEAR(H7),MONTH(H7)+1,DAY(H7)) -> 45627 | J7: =DATE(YEAR(I7),MONTH(I7)+1,DAY(I7)) -> 45658 | K7: =DATE(YEAR(J7),MONTH(J7)+1,DAY(J7)) -> 45689 | L7: =DATE(YEAR(K7),MONTH(K7)+1,DAY(K7)) -> 45717 | M7: =DATE(YEAR(L7),MONTH(L7)+1,DAY(L7)) -> 45748 | ... P7: =DATE(YEAR(O7),MONTH(O7)+1,DAY(O7)) -> 45839
B9: Indicateur personnalisable | D9: Prévisions
D10: Cumul prévisions | E10: =E9 | F10: =F9+E10 -> 0 | G10: =G9+F10 -> 0 | H10: =H9+G10 -> 0 | I10: =I9+H10 -> 0 | J10: =J9+I10 -> 0 | K10: =K9+J10 -> 0 | L10: =L9+K10 -> 0 | M10: =M9+L10 -> 0 | ... P10: =P9+O10 -> 0
D12: Réel
D13: Cumul réel | E13: =E12 | F13: =F12+E13 -> 0 | G13: =G12+F13 -> 0 | H13: =H12+G13 -> 0 | I13: =I12+H13 -> 0 | J13: =J12+I13 -> 0 | K13: =K12+J13 -> 0 | L13: =L12+K13 -> 0 | M13: =M12+L13 -> 0 | ... P13: =P12+O13 -> 0
D15: Ecart cumulé | E15: =E13-E10 -> 0 | F15: =F13-F10 -> 0 | G15: =G13-G10 -> 0 | H15: =H13-H10 -> 0 | I15: =I13-I10 -> 0 | J15: =J13-J10 -> 0 | K15: =K13-K10 -> 0 | L15: =L13-L10 -> 0 | ... P15: =P13-P10 -> 0
B17: Montant des commandes (en € HT) | D17: Prévisions | E17: ='Commandes - Calculs auto'!C42 -> 0 | F17: ='Commandes - Calculs auto'!D42 -> 0 | G17: ='Commandes - Calculs auto'!E42 -> 1700000 | H17: ='Commandes - Calculs auto'!F42 -> 3250000 | I17: ='Commandes - Calculs auto'!G42 -> 6125000 | J17: ='Commandes - Calculs auto'!H42 -> 21200000 | K17: ='Commandes - Calculs auto'!I42 -> 28850000 | L17: ='Commandes - Calculs auto'!J42 -> 34015000 | ... P17: ='Commandes - Calculs auto'!N42 -> 47357342
D18: Cumul prévisions | E18: =E17 -> 0 | F18: =F17+E18 -> 0 | G18: =G17+F18 -> 1700000 | H18: =H17+G18 -> 4950000 | I18: =I17+H18 -> 11075000 | J18: =J17+I18 -> 32275000 | K18: =K17+J18 -> 61125000 | L18: =L17+K18 -> 95140000 | M18: =M17+L18 -> 134336500 | ... P18: =P17+O18 -> 2.6820576e+08
D20: Réel
D21: Cumul réel | E21: =E20 | F21: =F20+E21 -> 0 | G21: =G20+F21 -> 0 | H21: =H20+G21 -> 0 | I21: =I20+H21 -> 0 | J21: =J20+I21 -> 0 | K21: =K20+J21 -> 0 | L21: =L20+K21 -> 0 | M21: =M20+L21 -> 0 | ... P21: =P20+O21 -> 0
D23: Ecart cumulé | E23: =E21-E18 -> 0 | F23: =F21-F18 -> 0 | G23: =G21-G18 -> -1700000 | H23: =H21-H18 -> -4950000 | I23: =I21-I18 -> -11075000 | J23: =J21-J18 -> -32275000 | K23: =K21-K18 -> -61125000 | L23: =L21-L18 -> -95140000 | ... P23: =P21-P18 -> -2.6820576e+08
B25: Chiffre d'affaires encaissé (en € HT) | D25: Prévisions | E25: ='Commandes - Calculs auto'!C22 -> 0 | F25: ='Commandes - Calculs auto'!D22 -> 0 | G25: ='Commandes - Calculs auto'!E22 -> 1700000 | H25: ='Commandes - Calculs auto'!F22 -> 3250000 | I25: ='Commandes - Calculs auto'!G22 -> 6125000 | J25: ='Commandes - Calculs auto'!H22 -> 21200000 | K25: ='Commandes - Calculs auto'!I22 -> 28850000 | L25: ='Commandes - Calculs auto'!J22 -> 34015000 | ... P25: ='Commandes - Calculs auto'!N22 -> 47357342
D26: Cumul prévisions | E26: =E25 -> 0 | F26: =F25+E26 -> 0 | G26: =G25+F26 -> 1700000 | H26: =H25+G26 -> 4950000 | I26: =I25+H26 -> 11075000 | J26: =J25+I26 -> 32275000 | K26: =K25+J26 -> 61125000 | L26: =L25+K26 -> 95140000 | M26: =M25+L26 -> 134336500 | ... P26: =P25+O26 -> 2.6820576e+08
D28: Réel
D29: Cumul réel | E29: =E28 | F29: =F28+E29 -> 0 | G29: =G28+F29 -> 0 | H29: =H28+G29 -> 0 | I29: =I28+H29 -> 0 | J29: =J28+I29 -> 0 | K29: =K28+J29 -> 0 | L29: =L28+K29 -> 0 | M29: =M28+L29 -> 0 | ... P29: =P28+O29 -> 0
D31: Ecart cumulé | E31: =E29-E26 -> 0 | F31: =F29-F26 -> 0 | G31: =G29-G26 -> -1700000 | H31: =H29-H26 -> -4950000 | I31: =I29-I26 -> -11075000 | J31: =J29-J26 -> -32275000 | K31: =K29-K26 -> -61125000 | L31: =L29-L26 -> -95140000 | ... P31: =P29-P26 -> -2.6820576e+08
B33: Marge brute encaissée (en € HT) | D33: Prévisions | E33: =E25-'Charges variables'!C22 -> 0 | F33: =F25-'Charges variables'!D22 -> 0 | G33: =G25-'Charges variables'!E22 -> 0 | H33: =H25-'Charges variables'!F22 -> 0 | I33: =I25-'Charges variables'!G22 -> 0 | J33: =J25-'Charges variables'!H22 -> 0 | K33: =K25-'Charges variables'!I22 -> 0 | L33: =L25-'Charges variables'!J22 -> 0 | ... P33: =P25-'Charges variables'!N22 -> 0
D34: Cumul prévisions | E34: =E33 -> 0 | F34: =F33+E34 -> 0 | G34: =G33+F34 -> 0 | H34: =H33+G34 -> 0 | I34: =I33+H34 -> 0 | J34: =J33+I34 -> 0 | K34: =K33+J34 -> 0 | L34: =L33+K34 -> 0 | M34: =M33+L34 -> 0 | ... P34: =P33+O34 -> 0
D36: Réel
D37: Cumul réel | E37: =E36 | F37: =F36+E37 -> 0 | G37: =G36+F37 -> 0 | H37: =H36+G37 -> 0 | I37: =I36+H37 -> 0 | J37: =J36+I37 -> 0 | K37: =K36+J37 -> 0 | L37: =L36+K37 -> 0 | M37: =M36+L37 -> 0 | ... P37: =P36+O37 -> 0
D39: Ecart cumulé | E39: =E37-E34 -> 0 | F39: =F37-F34 -> 0 | G39: =G37-G34 -> 0 | H39: =H37-H34 -> 0 | I39: =I37-I34 -> 0 | J39: =J37-J34 -> 0 | K39: =K37-K34 -> 0 | L39: =L37-L34 -> 0 | ... P39: =P37-P34 -> 0
B41: Salaires et charges | D41: Prévisions | E41: ='Personnel - Calculs auto'!B81 -> 3094000 | F41: ='Personnel - Calculs auto'!C81 -> 3094000 | G41: ='Personnel - Calculs auto'!D81 -> 3094000 | H41: ='Personnel - Calculs auto'!E81 -> 3094000 | I41: ='Personnel - Calculs auto'!F81 -> 3094000 | J41: ='Personnel - Calculs auto'!G81 -> 4819500 | K41: ='Personnel - Calculs auto'!H81 -> 4819500 | L41: ='Personnel - Calculs auto'!I81 -> 4819500 | ... P41: ='Personnel - Calculs auto'!M81 -> 4819500
D42: Cumul prévisions | E42: =E41 -> 3094000 | F42: =F41+E42 -> 6188000 | G42: =G41+F42 -> 9282000 | H42: =H41+G42 -> 12376000 | I42: =I41+H42 -> 15470000 | J42: =J41+I42 -> 20289500 | K42: =K41+J42 -> 25109000 | L42: =L41+K42 -> 29928500 | M42: =M41+L42 -> 34748000 | ... P42: =P41+O42 -> 49206500
D44: Réel
D45: Cumul réel | E45: =E44 | F45: =F44+E45 -> 0 | G45: =G44+F45 -> 0 | H45: =H44+G45 -> 0 | I45: =I44+H45 -> 0 | J45: =J44+I45 -> 0 | K45: =K44+J45 -> 0 | L45: =L44+K45 -> 0 | M45: =M44+L45 -> 0 | ... P45: =P44+O45 -> 0
D47: Ecart cumulé | E47: =E45-E42 -> -3094000 | F47: =F45-F42 -> -6188000 | G47: =G45-G42 -> -9282000 | H47: =H45-H42 -> -12376000 | I47: =I45-I42 -> -15470000 | J47: =J45-J42 -> -20289500 | K47: =K45-K42 -> -25109000 | L47: =L45-L42 -> -29928500 | ... P47: =P45-P42 -> -49206500
B49: Effectifs fin de mois | D49: Prévisions | E49: {=INDEX(SUMPRODUCT((Personnel!$B$10:$B$29<>1)*(Personnel!D$10:D$29<>0)),0,1)} -> 2 | F49: {=INDEX(SUMPRODUCT((Personnel!$B$10:$B$29<>1)*(Personnel!E$10:E$29<>0)),0,1)} -> 2 | G49: {=INDEX(SUMPRODUCT((Personnel!$B$10:$B$29<>1)*(Personnel!F$10:F$29<>0)),0,1)} -> 2 | H49: {=INDEX(SUMPRODUCT((Personnel!$B$10:$B$29<>1)*(Personnel!G$10:G$29<>0)),0,1)} -> 2 | I49: {=INDEX(SUMPRODUCT((Personnel!$B$10:$B$29<>1)*(Personnel!H$10:H$29<>0)),0,1)} -> 2 | J49: {=INDEX(SUMPRODUCT((Personnel!$B$10:$B$29<>1)*(Personnel!I$10:I$29<>0)),0,1)} -> 4 | K49: {=INDEX(SUMPRODUCT((Personnel!$B$10:$B$29<>1)*(Personnel!J$10:J$29<>0)),0,1)} -> 4 | L49: {=INDEX(SUMPRODUCT((Personnel!$B$10:$B$29<>1)*(Personnel!K$10:K$29<>0)),0,1)} -> 4 | ... P49: {=INDEX(SUMPRODUCT((Personnel!$B$10:$B$29<>1)*(Personnel!O$10:O$29<>0)),0,1)} -> 4
D51: Réel
B53: Trésorerie | D53: Prévisions | E53: ='Trésorerie'!C71 -> -7524676.3 | F53: ='Trésorerie'!D71 -> -14317976 | G53: ='Trésorerie'!E71 -> -21111276 | H53: ='Trésorerie'!F71 -> -27904576 | I53: ='Trésorerie'!G71 -> -34697875 | J53: ='Trésorerie'!H71 -> -50416675 | K53: ='Trésorerie'!I71 -> -57735475 | L53: ='Trésorerie'!J71 -> -66254275 | ... P53: ='Trésorerie'!N71 -> -1.0032947e+08
D55: Réel
D57: Ecart cumulé | E57: =E55-E53 -> 7524676.3 | F57: =F55-F53 -> 14317976 | G57: =G55-G53 -> 21111276 | H57: =H55-H53 -> 27904576 | I57: =I55-I53 -> 34697875 | J57: =J55-J53 -> 50416675 | K57: =K55-K53 -> 57735475 | L57: =L55-L53 -> 66254275 | ... P57: =P55-P53 -> 1.0032947e+08
B59: CA / Effectifs prévisionnels | D59: Instantané | E59: =IF(E49<>0,E25/E49,0) -> 0 | F59: =IF(F49<>0,F25/F49,0) -> 0 | G59: =IF(G49<>0,G25/G49,0) -> 850000 | H59: =IF(H49<>0,H25/H49,0) -> 1625000 | I59: =IF(I49<>0,I25/I49,0) -> 3062500 | J59: =IF(J49<>0,J25/J49,0) -> 5300000 | K59: =IF(K49<>0,K25/K49,0) -> 7212500 | L59: =IF(L49<>0,L25/L49,0) -> 8503750 | ... P59: =IF(P49<>0,P25/P49,0) -> 11839335
D60: Cumulé | E60: =IF(E49<>0,E26/E49,0) -> 0 | F60: =IF(F49<>0,F26/F49,0) -> 0 | G60: =IF(G49<>0,G26/G49,0) -> 850000 | H60: =IF(H49<>0,H26/H49,0) -> 2475000 | I60: =IF(I49<>0,I26/I49,0) -> 5537500 | J60: =IF(J49<>0,J26/J49,0) -> 8068750 | K60: =IF(K49<>0,K26/K49,0) -> 15281250 | L60: =IF(L49<>0,L26/L49,0) -> 23785000 | ... P60: =IF(P49<>0,P26/P49,0) -> 67051439

Sheet Comptes de résultats
B2: COMPTES DE RESULTATS (HT)
B5: Note : Les comptes de résultats sont calculés automatiquement à partir des informations que vous avez renseignées.
C7: Année 1 | D7: Année 2 | E7: Année 3 | F7: Année 4 | G7: Année 5
B9: Chiffre d'affaires (CA) | C9: ='Commandes - Calculs auto'!N43 -> 2.6820576e+08 | D9: ='Commandes - Calculs auto'!Z43 -> 1171803094 | E9: ='Commandes - Calculs auto'!AL43 -> 3374107710 | F9: ='Commandes - Calculs auto'!AX43 -> 5646000000 | G9: ='Commandes - Calculs auto'!BJ43 -> 10416000000
B11: Achats et charges de production | C11: ='Charges variables'!N41 -> 2.6820576e+08 | D11: ='Charges variables'!Z41 -> 1171803094 | E11: ='Charges variables'!AL41 -> 3374107710 | F11: ='Charges variables'!AX41 -> 5646000000 | G11: ='Charges variables'!BJ41 -> 10416000000
B12: Marge brute | C12: =C9-C11 -> 0 | D12: =D9-D11 -> 0 | E12: =E9-E11 -> 0 | F12: =F9-F11 -> 0 | G12: =G9-G11 -> 0
C13: =IF(C$9<>0,C12/C$9,) -> 0 | D13: =IF(D$9<>0,D12/D$9,) -> 0 | E13: =IF(E$9<>0,E12/E$9,) -> 0 | F13: =IF(F$9<>0,F12/F$9,) -> 0 | G13: =IF(G$9<>0,G12/G$9,) -> 0
B15: Charges externes | C15: ='Charges externes'!C29+'Plan de financement'!C28 -> 43882592 | D15: ='Charges externes'!D29+'Plan de financement'!D28 -> 84827806 | E15: ='Charges externes'!E29+'Plan de financement'!E28 -> 184314847 | F15: ='Charges externes'!F29+'Plan de financement'!F28 -> 285250000 | G15: ='Charges externes'!G29+'Plan de financement'!G28 -> 499900000
B16: Valeur ajoutée (VA) | C16: =C12-C15 -> -43882592 | D16: =D12-D15 -> -84827806 | E16: =E12-E15 -> -184314847 | F16: =F12-F15 -> -285250000 | G16: =G12-G15 -> -499900000
C17: =IF(C$9<>0,C16/C$9,) -> -0.1636154 | D17: =IF(D$9<>0,D16/D$9,) -> -0.072390836 | E17: =IF(E$9<>0,E16/E$9,) -> -0.054626249 | F17: =IF(F$9<>0,F16/F$9,) -> -0.050522494 | G17: =IF(G$9<>0,G16/G$9,) -> -0.047993472
B19: Impôts et taxes | C19: ='Impôts et taxes'!C14 -> 509004.59 | D19: ='Impôts et taxes'!D14 -> 1363439.1 | E19: ='Impôts et taxes'!E14 -> 3973750.6 | F19: ='Impôts et taxes'!F14 -> 4854352.9 | G19: ='Impôts et taxes'!G14 -> 9266602.9
B20: Subventions d'exploitation | C20: =SUM('Trésorerie'!C24:N24) -> 0 | D20: =SUM('Trésorerie'!O24:Z24) -> 0 | E20: =SUM('Trésorerie'!AA24:AL24) -> 0 | F20: =SUM('Trésorerie'!AM24:AX24) -> 0 | G20: =SUM('Trésorerie'!AY24:BJ24) -> 0
B21: Charges de personnel | C21: ='Personnel - Calculs auto'!N81 -> 49206500 | D21: ='Personnel - Calculs auto'!AA81 -> 111384000 | E21: ='Personnel - Calculs auto'!AD81 -> 210868000 | F21: ='Personnel - Calculs auto'!AG81 -> 0 | G21: ='Personnel - Calculs auto'!AJ81 -> 0
B22: Excédent brut d'exploitation (EBE) | C22: =C16+C20-C19-C21 -> -93598097 | D22: =D16+D20-D19-D21 -> -197575245 | E22: =E16+E20-E19-E21 -> -3.991566e+08 | F22: =F16+F20-F19-F21 -> -2.9010435e+08 | G22: =G16+G20-G19-G21 -> -5.091666e+08
C23: =IF(C$9<>0,C22/C$9,) -> -0.3489787 | D23: =IF(D$9<>0,D22/D$9,) -> -0.16860789 | E23: =IF(E$9<>0,E22/E$9,) -> -0.1182999 | F23: =IF(F$9<>0,F22/F$9,) -> -0.05138228 | G23: =IF(G$9<>0,G22/G$9,) -> -0.048883122
B25: Dotations aux amortissements | C25: =Investissements!AN28 -> 2000000 | D25: =Investissements!AO28 -> 4000000 | E25: =Investissements!AP28 -> 6666666.7 | F25: =Investissements!AQ28 -> 4666666.7 | G25: =Investissements!AR28 -> 2666666.7
B26: Résultat d'exploitation (REx) | C26: =C22-C25 -> -95598097 | D26: =D22-D25 -> -201575245 | E26: =E22-E25 -> -4.0582326e+08 | F26: =F22-F25 -> -2.9477102e+08 | G26: =G22-G25 -> -5.1183327e+08
C27: =IF(C$9<>0,C26/C$9,) -> -0.35643566 | D27: =IF(D$9<>0,D26/D$9,) -> -0.17202143 | E27: =IF(E$9<>0,E26/E$9,) -> -0.12027573 | F27: =IF(F$9<>0,F26/F$9,) -> -0.052208824 | G27: =IF(G$9<>0,G26/G$9,) -> -0.049139139
B29: Charges financières | C29: =SUM('Trésorerie'!C$56:N$56)*(1-1/(1+Config!$C$100))+SUM('Trésorerie'!C$57:N$57)*(1-1/(1+Config!$D$100)) -> 0 | D29: =SUM('Trésorerie'!O$56:Z$56)*(1-1/(1+Config!$C$100))+SUM('Trésorerie'!O$57:Z$57)*(1-1/(1+Config!$D$100)) -> 0 | E29: =SUM('Trésorerie'!AA$56:AL$56)*(1-1/(1+Config!$C$100))+SUM('Trésorerie'!AA$57:AL$57)*(1-1/(1+Config!$D$100)) -> 0 | F29: =SUM('Trésorerie'!AM$56:AX$56)*(1-1/(1+Config!$C$100))+SUM('Trésorerie'!AM$57:AX$57)*(1-1/(1+Config!$D$100)) -> 0 | G29: =SUM('Trésorerie'!AY$56:BJ$56)*(1-1/(1+Config!$C$100))+SUM('Trésorerie'!AY$57:BJ$57)*(1-1/(1+Config!$D$100)) -> 0
B30: Résultat courant | C30: =C26-C29 -> -95598097 | D30: =D26-D29 -> -201575245 | E30: =E26-E29 -> -4.0582326e+08 | F30: =F26-F29 -> -2.9477102e+08 | G30: =G26-G29 -> -5.1183327e+08
C31: =IF(C$9<>0,C30/C$9,) -> -0.35643566 | D31: =IF(D$9<>0,D30/D$9,) -> -0.17202143 | E31: =IF(E$9<>0,E30/E$9,) -> -0.12027573 | F31: =IF(F$9<>0,F30/F$9,) -> -0.052208824 | G31: =IF(G$9<>0,G30/G$9,) -> -0.049139139
B33: Reports déficitaires | C33: 0 | D33: =IF(C30<0,C30,0) -> -95598097 | E33: =IF(D30+D33<0,D30+D33,0) -> -297173342 | F33: =IF(E30+E33<0,E30+E33,0) -> -7.0299661e+08 | G33: =IF(F30+F33<0,F30+F33,0) -> -9.9776763e+08
B34: Impots sur les sociétés (IS) | C34: =IF((C30)>0,IF((C30)<38120,(C30)*0.15,5718+(C30-38120)/3),0) -> 0 | D34: =IF((D30+D33)>0,IF((D30+D33)<38120,(D30+D33)*0.15,5718+(D30+D33-38120)/3),0) -> 0 | E34: =IF((E30+E33)>0,IF((E30+E33)<38120,(E30+E33)*0.15,5718+(E30+E33-38120)/3),0) -> 0 | F34: =IF((F30+F33)>0,IF((F30+F33)<38120,(F30+F33)*0.15,5718+(F30+F33-38120)/3),0) -> 0 | G34: =IF((G30+G33)>0,IF((G30+G33)<38120,(G30+G33)*0.15,5718+(G30+G33-38120)/3),0) -> 0
B35: Résultat Net (RN) | C35: =C30-C34 -> -95598097 | D35: =D30-D34 -> -201575245 | E35: =E30-E34 -> -4.0582326e+08 | F35: =F30-F34 -> -2.9477102e+08 | G35: =G30-G34 -> -5.1183327e+08
C36: =IF(C$9<>0,C35/C$9,) -> -0.35643566 | D36: =IF(D$9<>0,D35/D$9,) -> -0.17202143 | E36: =IF(E$9<>0,E35/E$9,) -> -0.12027573 | F36: =IF(F$9<>0,F35/F$9,) -> -0.052208824 | G36: =IF(G$9<>0,G35/G$9,) -> -0.049139139

Sheet Plan de financement
B2: PLAN DE FINANCEMENT
B5: Note : Le plan de financement est calculé automatiquement à partir des informations que vous avez renseignées.
C7: Année 1 | D7: Année 2 | E7: Année 3 | F7: Année 4 | G7: Année 5
B9: EMPLOIS (a)
B10: Variation du BFR | C10: =BFR!N22 -> 731376.54 | D10: =BFR!Z22-BFR!N22 -> 682420.23 | E10: =BFR!AL22-BFR!Z22 -> 1658117.4 | F10: =BFR!AX22-BFR!AL22 -> 1682252.6 | G10: =BFR!BJ22-BFR!AX22 -> 3577500
B11: Investissement | C11: =Investissements!O28-Investissements!O9-C13 -> 6000000 | D11: =Investissements!AB28-Investissements!AB9-D13 -> 6000000 | E11: =Investissements!AE28-Investissements!AE9-E13 -> 8000000 | F11: =Investissements!AH28-Investissements!AH9-F13 -> 0 | G11: =Investissements!AK28-Investissements!AK9-G13 -> 0
B12: Investissement par apport en nature | C12: =Investissements!O9 -> 0 | D12: =Investissements!AB9 -> 0 | E12: =Investissements!AE9 -> 0 | F12: =Investissements!AH9 -> 0 | G12: =Investissements!AK9 -> 0
B13: Investissement par crédit bail | C13: =C28 -> 0 | D13: =D28 -> 0 | E13: =E28 -> 0 | F13: =F28 -> 0 | G13: =G28 -> 0
B14: Remboursement des prets bancaires | C14: =SUM('Trésorerie'!C56:N57)-'Comptes de résultats'!C29 -> 0 | D14: =SUM('Trésorerie'!O56:Z57)-'Comptes de résultats'!D29 -> 0 | E14: =SUM('Trésorerie'!AA56:AL57)-'Comptes de résultats'!E29 -> 0 | F14: =SUM('Trésorerie'!AM56:AX57)-'Comptes de résultats'!F29 -> 0 | G14: =SUM('Trésorerie'!AY56:BJ57)-'Comptes de résultats'!G29 -> 0
B15: Remboursement des comptes courants | C15: =SUM('Trésorerie'!C58:N58) -> 0 | D15: =SUM('Trésorerie'!O58:Z58) -> 0 | E15: =SUM('Trésorerie'!AA58:AL58) -> 0 | F15: =SUM('Trésorerie'!AM58:AX58) -> 0 | G15: =SUM('Trésorerie'!AY58:BJ58) -> 0
B16: Remboursement des avances remboursables | C16: =SUM('Trésorerie'!C63:N63) -> 0 | D16: =SUM('Trésorerie'!O63:Z63) -> 0 | E16: =SUM('Trésorerie'!AA63:AL63) -> 0 | F16: =SUM('Trésorerie'!AM63:AX63) -> 0 | G16: =SUM('Trésorerie'!AY63:BJ63) -> 0
B17: CAF négative (hors subvention) | C17: =IF(('Comptes de résultats'!C35+'Comptes de résultats'!C25-'Comptes de résultats'!C20)<0,-('Comptes de résultats'!C35+'Comptes de résultats'!C25-'Comptes de résultats'!C20),0) -> 93598097 | D17: =IF(('Comptes de résultats'!D35+'Comptes de résultats'!D25-'Comptes de résultats'!D20)<0,-('Comptes de résultats'!D35+'Comptes de résultats'!D25-'Comptes de résultats'!D20),0) -> 197575245 | E17: =IF(('Comptes de résultats'!E35+'Comptes de résultats'!E25-'Comptes de résultats'!E20)<0,-('Comptes de résultats'!E35+'Comptes de résultats'!E25-'Comptes de résultats'!E20),0) -> 3.991566e+08 | F17: =IF(('Comptes de résultats'!F35+'Comptes de résultats'!F25-'Comptes de résultats'!F20)<0,-('Comptes de résultats'!F35+'Comptes de résultats'!F25-'Comptes de résultats'!F20),0) -> 2.9010435e+08 | G17: =IF(('Comptes de résultats'!G35+'Comptes de résultats'!G25-'Comptes de résultats'!G20)<0,-('Comptes de résultats'!G35+'Comptes de résultats'!G25-'Comptes de résultats'!G20),0) -> 5.091666e+08
B18: TOTAL EMPLOIS | C18: =SUM(C10:C17) -> 1.0032947e+08 | D18: =SUM(D10:D17) -> 2.0425767e+08 | E18: =SUM(E10:E17) -> 4.0881471e+08 | F18: =SUM(F10:F17) -> 2.9178661e+08 | G18: =SUM(G10:G17) -> 5.127441e+08
B20: RESSOURCES (b)
B21: Capital fondateurs | C21: =SUM('Trésorerie'!C20:N20) -> 0 | D21: =SUM('Trésorerie'!O20:Z20) -> 0 | E21: =SUM('Trésorerie'!AA20:AL20) -> 0 | F21: =SUM('Trésorerie'!AM20:AX20) -> 0 | G21: =SUM('Trésorerie'!AY20:BJ20) -> 0
B22: Capital investisseurs | C22: =SUM('Trésorerie'!C21:N21) -> 0 | D22: =SUM('Trésorerie'!O21:Z21) -> 0 | E22: =SUM('Trésorerie'!AA21:AL21) -> 0 | F22: =SUM('Trésorerie'!AM21:AX21) -> 0 | G22: =SUM('Trésorerie'!AY21:BJ21) -> 0
B23: Apport en nature | C23: =C12 -> 0 | D23: =D12 -> 0 | E23: =E12 -> 0 | F23: =F12 -> 0 | G23: =G12 -> 0
B24: Comptes courants | C24: =SUM('Trésorerie'!C29:N29) -> 0 | D24: =SUM('Trésorerie'!O29:Z29) -> 0 | E24: =SUM('Trésorerie'!AA29:AL29) -> 0 | F24: =SUM('Trésorerie'!AM29:AX29) -> 0 | G24: =SUM('Trésorerie'!AY29:BJ29) -> 0
B25: TOTAL (quasi) FONDS PROPRES | C25: =SUM(C21:C24) -> 0 | D25: =SUM(D21:D24) -> 0 | E25: =SUM(E21:E24) -> 0 | F25: =SUM(F21:F24) -> 0 | G25: =SUM(G21:G24) -> 0
B26: Prêts bancaires CT | C26: =SUM('Trésorerie'!C22:N22) -> 0 | D26: =SUM('Trésorerie'!O22:Z22) -> 0 | E26: =SUM('Trésorerie'!AA22:AL22) -> 0 | F26: =SUM('Trésorerie'!AM22:AX22) -> 0 | G26: =SUM('Trésorerie'!AY22:BJ22) -> 0
B27: Prêts bancaires MT/LT | C27: =SUM('Trésorerie'!C23:N23) -> 0 | D27: =SUM('Trésorerie'!O23:Z23) -> 0 | E27: =SUM('Trésorerie'!AA23:AL23) -> 0 | F27: =SUM('Trésorerie'!AM23:AX23) -> 0 | G27: =SUM('Trésorerie'!AY23:BJ23) -> 0
B28: Crédit bail | C28: =SUM('Trésorerie'!C55:N55) -> 0 | D28: =SUM('Trésorerie'!O55:Z55) -> 0 | E28: =SUM('Trésorerie'!AA55:AL55) -> 0 | F28: =SUM('Trésorerie'!AM55:AX55) -> 0 | G28: =SUM('Trésorerie'!AY55:BJ55) -> 0
B29: Avances et prêts remboursables | C29: =SUM('Trésorerie'!C34:N34) -> 0 | D29: =SUM('Trésorerie'!O34:Z34) -> 0 | E29: =SUM('Trésorerie'!AA34:AL34) -> 0 | F29: =SUM('Trésorerie'!AM34:AX34) -> 0 | G29: =SUM('Trésorerie'!AY34:BJ34) -> 0
B30: Subvention | C30: ='Comptes de résultats'!C20 -> 0 | D30: ='Comptes de résultats'!D20 -> 0 | E30: ='Comptes de résultats'!E20 -> 0 | F30: ='Comptes de résultats'!F20 -> 0 | G30: ='Comptes de résultats'!G20 -> 0
B31: CAF positive (hors subvention) | C31: =IF(('Comptes de résultats'!C35+'Comptes de résultats'!C25-'Comptes de résultats'!C20)>0,'Comptes de résultats'!C35+'Comptes de résultats'!C25-'Comptes de résultats'!C20,0) -> 0 | D31: =IF(('Comptes de résultats'!D35+'Comptes de résultats'!D25-'Comptes de résultats'!D20)>0,'Comptes de résultats'!D35+'Comptes de résultats'!D25-'Comptes de résultats'!D20,0) -> 0 | E31: =IF(('Comptes de résultats'!E35+'Comptes de résultats'!E25-'Comptes de résultats'!E20)>0,'Comptes de résultats'!E35+'Comptes de résultats'!E25-'Comptes de résultats'!E20,0) -> 0 | F31: =IF(('Comptes de résultats'!F35+'Comptes de résultats'!F25-'Comptes de résultats'!F20)>0,'Comptes de résultats'!F35+'Comptes de résultats'!F25-'Comptes de résultats'!F20,0) -> 0 | G31: =IF(('Comptes de résultats'!G35+'Comptes de résultats'!G25-'Comptes de résultats'!G20)>0,'Comptes de résultats'!G35+'Comptes de résultats'!G25-'Comptes de résultats'!G20,0) -> 0
B32: Dette IS | C32: ='Comptes de résultats'!C34 -> 0 | D32: ='Comptes de résultats'!D34-(SUM('Trésorerie'!O51:Z51)-'Impôts et taxes'!D14) -> -4.6566129e-10 | E32: ='Comptes de résultats'!E34-(SUM('Trésorerie'!AA51:AL51)-'Impôts et taxes'!E14) -> 9.3132257e-10 | F32: ='Comptes de résultats'!F34-(SUM('Trésorerie'!AM51:AX51)-'Impôts et taxes'!F14) -> 0 | G32: ='Comptes de résultats'!G34-(SUM('Trésorerie'!AY51:BJ51)-'Impôts et taxes'!G14) -> 1.8626451e-09
B33: TOTAL RESSOURCES | C33: =C25+SUM(C26:C32) -> 0 | D33: =D25+SUM(D26:D32) -> -4.6566129e-10 | E33: =E25+SUM(E26:E32) -> 9.3132257e-10 | F33: =F25+SUM(F26:F32) -> 0 | G33: =G25+SUM(G26:G32) -> 1.8626451e-09
B35: Excédent période (b) - (a) | C35: =C33-C18 -> -1.0032947e+08 | D35: =D33-D18 -> -2.0425767e+08 | E35: =E33-E18 -> -4.0881471e+08 | F35: =F33-F18 -> -2.9178661e+08 | G35: =G33-G18 -> -5.127441e+08
B36: Excédent début période | C36: 0 | D36: =C37 -> -1.0032947e+08 | E36: =D37 -> -3.0458714e+08 | F36: =E37 -> -7.1340185e+08 | G36: =F37 -> -1005188459
B37: EXCEDENT | C37: =C36+C35 -> -1.0032947e+08 | D37: =D36+D35 -> -3.0458714e+08 | E37: =E36+E35 -> -7.1340185e+08 | F37: =F36+F35 -> -1005188459 | G37: =G36+G35 -> -1517932562

Sheet Commandes - Calculs auto
B2: Calculs auto liés aux commandes
B5: Chiffre d'affaires encaissé (en € HT)
C7: Année 1 | O7: Année 2 | AA7: Année 3 | AM7: Année 4 | AY7: Année 5
B8: Activités | C8: =Config!$C$7 -> 45505 | D8: =DATE(YEAR(C8),MONTH(C8)+1,DAY(C8)) -> 45536 | E8: =DATE(YEAR(D8),MONTH(D8)+1,DAY(D8)) -> 45566 | F8: =DATE(YEAR(E8),MONTH(E8)+1,DAY(E8)) -> 45597 | G8: =DATE(YEAR(F8),MONTH(F8)+1,DAY(F8)) -> 45627 | H8: =DATE(YEAR(G8),MONTH(G8)+1,DAY(G8)) -> 45658 | I8: =DATE(YEAR(H8),MONTH(H8)+1,DAY(H8)) -> 45689 | J8: =DATE(YEAR(I8),MONTH(I8)+1,DAY(I8)) -> 45717 | K8: =DATE(YEAR(J8),MONTH(J8)+1,DAY(J8)) -> 45748 | ... BJ8: =DATE(YEAR(BI8),MONTH(BI8)+1,DAY(BI8)) -> 47300
B9: =Config!$B$14 -> Abonnement Basique | C9: {=((Config!$F14*Commandes!C9)+IF(ROUND((C$8-Config!$C$7)/31,0)>=(Config!$D14+Config!$E14),INDEX(Commandes!$C9:$BJ9,,COLUMN(C$8)-COLUMN($C$8)+1-(Config!$D14+Config!$E14)),0)*Config!$G14)*Config!$C14} -> 0 | D9: {=((Config!$F14*Commandes!D9)+IF(ROUND((D$8-Config!$C$7)/31,0)>=(Config!$D14+Config!$E14),INDEX(Commandes!$C9:$BJ9,,COLUMN(D$8)-COLUMN($C$8)+1-(Config!$D14+Config!$E14)),0)*Config!$G14)*Config!$C14} -> 0 | E9: {=((Config!$F14*Commandes!E9)+IF(ROUND((E$8-Config!$C$7)/31,0)>=(Config!$D14+Config!$E14),INDEX(Commandes!$C9:$BJ9,,COLUMN(E$8)-COLUMN($C$8)+1-(Config!$D14+Config!$E14)),0)*Config!$G14)*Config!$C14} -> 450000 | F9: {=((Config!$F14*Commandes!F9)+IF(ROUND((F$8-Config!$C$7)/31,0)>=(Config!$D14+Config!$E14),INDEX(Commandes!$C9:$BJ9,,COLUMN(F$8)-COLUMN($C$8)+1-(Config!$D14+Config!$E14)),0)*Config!$G14)*Config!$C14} -> 750000 | G9: {=((Config!$F14*Commandes!G9)+IF(ROUND((G$8-Config!$C$7)/31,0)>=(Config!$D14+Config!$E14),INDEX(Commandes!$C9:$BJ9,,COLUMN(G$8)-COLUMN($C$8)+1-(Config!$D14+Config!$E14)),0)*Config!$G14)*Config!$C14} -> 1125000 | H9: {=((Config!$F14*Commandes!H9)+IF(ROUND((H$8-Config!$C$7)/31,0)>=(Config!$D14+Config!$E14),INDEX(Commandes!$C9:$BJ9,,COLUMN(H$8)-COLUMN($C$8)+1-(Config!$D14+Config!$E14)),0)*Config!$G14)*Config!$C14} -> 1500000 | I9: {=((Config!$F14*Commandes!I9)+IF(ROUND((I$8-Config!$C$7)/31,0)>=(Config!$D14+Config!$E14),INDEX(Commandes!$C9:$BJ9,,COLUMN(I$8)-COLUMN($C$8)+1-(Config!$D14+Config!$E14)),0)*Config!$G14)*Config!$C14} -> 1650000 | J9: {=((Config!$F14*Commandes!J9)+IF(ROUND((J$8-Config!$C$7)/31,0)>=(Config!$D14+Config!$E14),INDEX(Commandes!$C9:$BJ9,,COLUMN(J$8)-COLUMN($C$8)+1-(Config!$D14+Config!$E14)),0)*Config!$G14)*Config!$C14} -> 1815000 | ... BJ9: {=((Config!$F14*Commandes!BJ9)+IF(ROUND((BJ$8-Config!$C$7)/31,0)>=(Config!$D14+Config!$E14),INDEX(Commandes!$C9:$BJ9,,COLUMN(BJ$8)-COLUMN($C$8)+1-(Config!$D14+Config!$E14)),0)*Config!$G14)*Config!$C14} -> 450000000
B10: =Config!$B$15 -> Abonnement Premium | C10: {=((Config!$F15*Commandes!C10)+IF(ROUND((C$8-Config!$C$7)/31,0)>=(Config!$D15+Config!$E15),INDEX(Commandes!$C10:$BJ10,,COLUMN(C$8)-COLUMN($C$8)+1-(Config!$D15+Config!$E15)),0)*Config!$G15)*Config!$C15} -> 0 | D10: {=((Config!$F15*Commandes!D10)+IF(ROUND((D$8-Config!$C$7)/31,0)>=(Config!$D15+Config!$E15),INDEX(Commandes!$C10:$BJ10,,COLUMN(D$8)-COLUMN($C$8)+1-(Config!$D15+Config!$E15)),0)*Config!$G15)*Config!$C15} -> 0 | E10: {=((Config!$F15*Commandes!E10)+IF(ROUND((E$8-Config!$C$7)/31,0)>=(Config!$D15+Config!$E15),INDEX(Commandes!$C10:$BJ10,,COLUMN(E$8)-COLUMN($C$8)+1-(Config!$D15+Config!$E15)),0)*Config!$G15)*Config!$C15} -> 1250000 | F10: {=((Config!$F15*Commandes!F10)+IF(ROUND((F$8-Config!$C$7)/31,0)>=(Config!$D15+Config!$E15),INDEX(Commandes!$C10:$BJ10,,COLUMN(F$8)-COLUMN($C$8)+1-(Config!$D15+Config!$E15)),0)*Config!$G15)*Config!$C15} -> 2500000 | G10: {=((Config!$F15*Commandes!G10)+IF(ROUND((G$8-Config!$C$7)/31,0)>=(Config!$D15+Config!$E15),INDEX(Commandes!$C10:$BJ10,,COLUMN(G$8)-COLUMN($C$8)+1-(Config!$D15+Config!$E15)),0)*Config!$G15)*Config!$C15} -> 5000000 | H10: {=((Config!$F15*Commandes!H10)+IF(ROUND((H$8-Config!$C$7)/31,0)>=(Config!$D15+Config!$E15),INDEX(Commandes!$C10:$BJ10,,COLUMN(H$8)-COLUMN($C$8)+1-(Config!$D15+Config!$E15)),0)*Config!$G15)*Config!$C15} -> 12500000 | I10: {=((Config!$F15*Commandes!I10)+IF(ROUND((I$8-Config!$C$7)/31,0)>=(Config!$D15+Config!$E15),INDEX(Commandes!$C10:$BJ10,,COLUMN(I$8)-COLUMN($C$8)+1-(Config!$D15+Config!$E15)),0)*Config!$G15)*Config!$C15} -> 20000000 | J10: {=((Config!$F15*Commandes!J10)+IF(ROUND((J$8-Config!$C$7)/31,0)>=(Config!$D15+Config!$E15),INDEX(Commandes!$C10:$BJ10,,COLUMN(J$8)-COLUMN($C$8)+1-(Config!$D15+Config!$E15)),0)*Config!$G15)*Config!$C15} -> 25000000 | ... BJ10: {=((Config!$F15*Commandes!BJ10)+IF(ROUND((BJ$8-Config!$C$7)/31,0)>=(Config!$D15+Config!$E15),INDEX(Commandes!$C10:$BJ10,,COLUMN(BJ$8)-COLUMN($C$8)+1-(Config!$D15+Config!$E15)),0)*Config!$G15)*Config!$C15} -> 500000000
B11: =Config!$B$16 -> Conseil Personnalisé | C11: {=((Config!$F16*Commandes!C11)+IF(ROUND((C$8-Config!$C$7)/31,0)>=(Config!$D16+Config!$E16),INDEX(Commandes!$C11:$BJ11,,COLUMN(C$8)-COLUMN($C$8)+1-(Config!$D16+Config!$E16)),0)*Config!$G16)*Config!$C16} -> 0 | D11: {=((Config!$F16*Commandes!D11)+IF(ROUND((D$8-Config!$C$7)/31,0)>=(Config!$D16+Config!$E16),INDEX(Commandes!$C11:$BJ11,,COLUMN(D$8)-COLUMN($C$8)+1-(Config!$D16+Config!$E16)),0)*Config!$G16)*Config!$C16} -> 0 | E11: {=((Config!$F16*Commandes!E11)+IF(ROUND((E$8-Config!$C$7)/31,0)>=(Config!$D16+Config!$E16),INDEX(Commandes!$C11:$BJ11,,COLUMN(E$8)-COLUMN($C$8)+1-(Config!$D16+Config!$E16)),0)*Config!$G16)*Config!$C16} -> 0 | F11: {=((Config!$F16*Commandes!F11)+IF(ROUND((F$8-Config!$C$7)/31,0)>=(Config!$D16+Config!$E16),INDEX(Commandes!$C11:$BJ11,,COLUMN(F$8)-COLUMN($C$8)+1-(Config!$D16+Config!$E16)),0)*Config!$G16)*Config!$C16} -> 0 | G11: {=((Config!$F16*Commandes!G11)+IF(ROUND((G$8-Config!$C$7)/31,0)>=(Config!$D16+Config!$E16),INDEX(Commandes!$C11:$BJ11,,COLUMN(G$8)-COLUMN($C$8)+1-(Config!$D16+Config!$E16)),0)*Config!$G16)*Config!$C16} -> 0 | H11: {=((Config!$F16*Commandes!H11)+IF(ROUND((H$8-Config!$C$7)/31,0)>=(Config!$D16+Config!$E16),INDEX(Commandes!$C11:$BJ11,,COLUMN(H$8)-COLUMN($C$8)+1-(Config!$D16+Config!$E16)),0)*Config!$G16)*Config!$C16} -> 7200000 | I11: {=((Config!$F16*Commandes!I11)+IF(ROUND((I$8-Config!$C$7)/31,0)>=(Config!$D16+Config!$E16),INDEX(Commandes!$C11:$BJ11,,COLUMN(I$8)-COLUMN($C$8)+1-(Config!$D16+Config!$E16)),0)*Config!$G16)*Config!$C16} -> 7200000 | J11: {=((Config!$F16*Commandes!J11)+IF(ROUND((J$8-Config!$C$7)/31,0)>=(Config!$D16+Config!$E16),INDEX(Commandes!$C11:$BJ11,,COLUMN(J$8)-COLUMN($C$8)+1-(Config!$D16+Config!$E16)),0)*Config!$G16)*Config!$C16} -> 7200000 | ... BJ11: {=((Config!$F16*Commandes!BJ11)+IF(ROUND((BJ$8-Config!$C$7)/31,0)>=(Config!$D16+Config!$E16),INDEX(Commandes!$C11:$BJ11,,COLUMN(BJ$8)-COLUMN($C$8)+1-(Config!$D16+Config!$E16)),0)*Config!$G16)*Config!$C16} -> 18000000
B12: =Config!$B$17 -> Plateforme de Marché en Ligne | C12: {=((Config!$F17*Commandes!C12)+IF(ROUND((C$8-Config!$C$7)/31,0)>=(Config!$D17+Config!$E17),INDEX(Commandes!$C12:$BJ12,,COLUMN(C$8)-COLUMN($C$8)+1-(Config!$D17+Config!$E17)),0)*Config!$G17)*Config!$C17} -> 0 | D12: {=((Config!$F17*Commandes!D12)+IF(ROUND((D$8-Config!$C$7)/31,0)>=(Config!$D17+Config!$E17),INDEX(Commandes!$C12:$BJ12,,COLUMN(D$8)-COLUMN($C$8)+1-(Config!$D17+Config!$E17)),0)*Config!$G17)*Config!$C17} -> 0 | E12: {=((Config!$F17*Commandes!E12)+IF(ROUND((E$8-Config!$C$7)/31,0)>=(Config!$D17+Config!$E17),INDEX(Commandes!$C12:$BJ12,,COLUMN(E$8)-COLUMN($C$8)+1-(Config!$D17+Config!$E17)),0)*Config!$G17)*Config!$C17} -> 0 | F12: {=((Config!$F17*Commandes!F12)+IF(ROUND((F$8-Config!$C$7)/31,0)>=(Config!$D17+Config!$E17),INDEX(Commandes!$C12:$BJ12,,COLUMN(F$8)-COLUMN($C$8)+1-(Config!$D17+Config!$E17)),0)*Config!$G17)*Config!$C17} -> 0 | G12: {=((Config!$F17*Commandes!G12)+IF(ROUND((G$8-Config!$C$7)/31,0)>=(Config!$D17+Config!$E17),INDEX(Commandes!$C12:$BJ12,,COLUMN(G$8)-COLUMN($C$8)+1-(Config!$D17+Config!$E17)),0)*Config!$G17)*Config!$C17} -> 0 | H12: {=((Config!$F17*Commandes!H12)+IF(ROUND((H$8-Config!$C$7)/31,0)>=(Config!$D17+Config!$E17),INDEX(Commandes!$C12:$BJ12,,COLUMN(H$8)-COLUMN($C$8)+1-(Config!$D17+Config!$E17)),0)*Config!$G17)*Config!$C17} -> 0 | I12: {=((Config!$F17*Commandes!I12)+IF(ROUND((I$8-Config!$C$7)/31,0)>=(Config!$D17+Config!$E17),INDEX(Commandes!$C12:$BJ12,,COLUMN(I$8)-COLUMN($C$8)+1-(Config!$D17+Config!$E17)),0)*Config!$G17)*Config!$C17} -> 0 | J12: {=((Config!$F17*Commandes!J12)+IF(ROUND((J$8-Config!$C$7)/31,0)>=(Config!$D17+Config!$E17),INDEX(Commandes!$C12:$BJ12,,COLUMN(J$8)-COLUMN($C$8)+1-(Config!$D17+Config!$E17)),0)*Config!$G17)*Config!$C17} -> 0 | ... BJ12: {=((Config!$F17*Commandes!BJ12)+IF(ROUND((BJ$8-Config!$C$7)/31,0)>=(Config!$D17+Config!$E17),INDEX(Commandes!$C12:$BJ12,,COLUMN(BJ$8)-COLUMN($C$8)+1-(Config!$D17+Config!$E17)),0)*Config!$G17)*Config!$C17} -> 0
B13: =Config!$B$18 -> Formations et Ateliers | C13: {=((Config!$F18*Commandes!C13)+IF(ROUND((C$8-Config!$C$7)/31,0)>=(Config!$D18+Config!$E18),INDEX(Commandes!$C13:$BJ13,,COLUMN(C$8)-COLUMN($C$8)+1-(Config!$D18+Config!$E18)),0)*Config!$G18)*Config!$C18} -> 0 | D13: {=((Config!$F18*Commandes!D13)+IF(ROUND((D$8-Config!$C$7)/31,0)>=(Config!$D18+Config!$E18),INDEX(Commandes!$C13:$BJ13,,COLUMN(D$8)-COLUMN($C$8)+1-(Config!$D18+Config!$E18)),0)*Config!$G18)*Config!$C18} -> 0 | E13: {=((Config!$F18*Commandes!E13)+IF(ROUND((E$8-Config!$C$7)/31,0)>=(Config!$D18+Config!$E18),INDEX(Commandes!$C13:$BJ13,,COLUMN(E$8)-COLUMN($C$8)+1-(Config!$D18+Config!$E18)),0)*Config!$G18)*Config!$C18} -> 0 | F13: {=((Config!$F18*Commandes!F13)+IF(ROUND((F$8-Config!$C$7)/31,0)>=(Config!$D18+Config!$E18),INDEX(Commandes!$C13:$BJ13,,COLUMN(F$8)-COLUMN($C$8)+1-(Config!$D18+Config!$E18)),0)*Config!$G18)*Config!$C18} -> 0 | G13: {=((Config!$F18*Commandes!G13)+IF(ROUND((G$8-Config!$C$7)/31,0)>=(Config!$D18+Config!$E18),INDEX(Commandes!$C13:$BJ13,,COLUMN(G$8)-COLUMN($C$8)+1-(Config!$D18+Config!$E18)),0)*Config!$G18)*Config!$C18} -> 0 | H13: {=((Config!$F18*Commandes!H13)+IF(ROUND((H$8-Config!$C$7)/31,0)>=(Config!$D18+Config!$E18),INDEX(Commandes!$C13:$BJ13,,COLUMN(H$8)-COLUMN($C$8)+1-(Config!$D18+Config!$E18)),0)*Config!$G18)*Config!$C18} -> 0 | I13: {=((Config!$F18*Commandes!I13)+IF(ROUND((I$8-Config!$C$7)/31,0)>=(Config!$D18+Config!$E18),INDEX(Commandes!$C13:$BJ13,,COLUMN(I$8)-COLUMN($C$8)+1-(Config!$D18+Config!$E18)),0)*Config!$G18)*Config!$C18} -> 0 | J13: {=((Config!$F18*Commandes!J13)+IF(ROUND((J$8-Config!$C$7)/31,0)>=(Config!$D18+Config!$E18),INDEX(Commandes!$C13:$BJ13,,COLUMN(J$8)-COLUMN($C$8)+1-(Config!$D18+Config!$E18)),0)*Config!$G18)*Config!$C18} -> 0 | ... BJ13: {=((Config!$F18*Commandes!BJ13)+IF(ROUND((BJ$8-Config!$C$7)/31,0)>=(Config!$D18+Config!$E18),INDEX(Commandes!$C13:$BJ13,,COLUMN(BJ$8)-COLUMN($C$8)+1-(Config!$D18+Config!$E18)),0)*Config!$G18)*Config!$C18} -> 0
